Workbook

Sheet Guide
B1: FOREX TRADE JOURNAL - HOW TO USE
B2: A self-calculating journal and analytics suite. Log each trade once; every tab updates.
B4: SET UP (2 minutes)
B5: 1. Settings | C5: Enter your real account balances, default risk %, risk rules and prop-challenge rules. Blue on yellow = editable.
B6: 2. Lists | C6: Rename pairs, setups, emotions, mistake tags and moods; fill blank yellow cells to add your own. Pip size / value drive lot-size checks.
B7: 3. Clear the sample | C7: Journal row 6 is an example so you can see the format. Overwrite it.
B8: TABS
B9: Dashboard | C9: Account-filtered KPI cards, edge finder, prop status and 8 charts. Pick the account in the gold cell top right.
B10: Journal | C10: One row per trade. Blue = you type, grey = automatic. Helper columns on the far right are grouped; click [+] above the column letters to expand.
B11: Daily Journal | C11: Weekday rows from your start date: sleep, mood, plan and review. Trades and P&L fill in; Analytics links mood and sleep to results.
B12: Analytics | C12: 18 breakdown tables (session, pair, setup, hour, hold time, emotion, mistakes, rule checks, accounts, months, mood and sleep).
B13: Weekly Review | C13: 26 weeks of numbers plus three reflection columns.
B14: Goals & Prop | C14: Prop-firm progress bars against your limits, plus monthly goals.
B15: Playbook | C15: Your setups with concise rules and a live Keep / Refine / Review verdict.
B16: Backtest | C16: Log tested trades in R to validate a setup before risking money.
B17: Chart Data | C17: Calculation sheet for the dashboard. Do not edit.
B18: LOGGING A TRADE
B19: Before the trade | C19: Fill Trade Info, Analysis, the 7 confirmations, Planned Entry / Planned Stop, then Entry, Stop, Target, Lot size and Risk %.
B20: After the trade | C20: Enter Exit Price, Exit Time and Fees. Result, outcome, P&L, balance, slippage, hold time and rule check calculate themselves.
B21: Open trades | C21: Leave Exit Price blank. The trade is excluded from statistics until closed.
B22: Rules | C22: Enter trades in date order with no gaps, using dropdowns. Risk % is typed as a percentage (1% or 0.01).
B23: RISK-RULE FLAGS (Journal 'Rule Check')
B24: Oversized | C24: Lot size exceeds the suggested lots (risk $ / stop pips / pip value) by more than the tolerance on Settings.
B25: Overtraded | C25: More trades on the same day (same account) than Max Trades per Day.
B26: Daily loss hit | C26: The day's loss before this trade had already reached Max Daily Loss (% of day-start balance).
B27: Weekly loss hit | C27: The week's loss before this trade had already reached Max Weekly Loss (% of week-start balance).
B28: KEY DEFINITIONS
B29: Win rate | C29: Wins / closed trades. Break-even trades (within the threshold) count as non-wins.
B30: Expectancy (avg R) | C30: Average R per trade. Above 0 means a positive edge over the sample.
B31: Profit factor | C31: Gross profit / gross loss. Above 1 is profitable.
B32: Max drawdown | C32: Largest fall from a balance peak, as a percentage of that peak (for the selected view).
B33: Payoff ratio | C33: Average win (R) divided by average loss (R).
B34: Slippage | C34: (Entry vs Planned Entry) in pips; positive = a worse fill than planned.
B35: ASSUMPTIONS
B36: Currency | C36: Accounts assumed USD (labels say $); the maths works in any currency.
B37: Balances | C37: Account balances (10,000 and 50,000) and all prop-firm limits are placeholders, not your data. Replace them on Settings.
B38: Pip values | C38: Approximate; they move with exchange rates. Confirm with your broker.
B39: Capacity | C39: 500 trades on the Journal. Copy the last row's formulas down to extend, then widen the ranges on other sheets.
B40: Equity chart | C40: Shows 100 trades at a time from the trade # on the Dashboard; the line holds flat after your latest trade.
B41: Educational tool | C41: This workbook records and analyses your trading. It is not financial advice.

Sheet Dashboard
B1: FOREX TRADING PERFORMANCE DASHBOARD | J1: ACCOUNT VIEW > | L1: All Accounts
B2: ="Closed trades in view: "&'Chart Data'!$C$5&" | Journal start: "&TEXT(Settings!$C$7,"dd mmm yyyy")&" | Updates automatically from the Journal tab" -> Closed trades in view: 1 | Journal start: 28 Sep 2026 | Updates automatically from the Journal tab
B4: PERFORMANCE SNAPSHOT
B5: NET P&L ($) | D5: ACCOUNT BALANCE ($) | F5: RETURN % | H5: WIN RATE | J5: PROFIT FACTOR | L5: EXPECTANCY (R)
B6: ='Chart Data'!$C$9 -> 229.5 | D6: ='Chart Data'!$C$18 -> 60229.5 | F6: =IFERROR('Chart Data'!$C$9/'Chart Data'!$C$17,0) -> 0.003825 | H6: =IFERROR('Chart Data'!$C$6/'Chart Data'!$C$5,0) -> 1 | J6: =IF('Chart Data'!$C$11=0,"-",'Chart Data'!$C$10/'Chart Data'!$C$11) -> - | L6: =IFERROR('Chart Data'!$C$12/'Chart Data'!$C$5,0) -> 2.33
B7: ="Profit "&TEXT('Chart Data'!$C$10,"$#,##0")&" | Loss "&TEXT('Chart Data'!$C$11,"$#,##0") -> Profit $230 | Loss $0 | D7: ="Start "&TEXT('Chart Data'!$C$17,"$#,##0") -> Start $60,000 | F7: on starting balance | H7: ="W "&'Chart Data'!$C$6&" / L "&'Chart Data'!$C$7&" / BE "&'Chart Data'!$C$8 -> W 1 / L 0 / BE 0 | J7: above 1.0 = profitable | L7: average R per trade
B9: CLOSED TRADES | D9: MAX DRAWDOWN | F9: AVERAGE WIN (R) | H9: AVERAGE LOSS (R) | J9: PAYOFF RATIO | L9: BEST TRADE (R)
B10: ='Chart Data'!$C$5 -> 1 | D10: ='Chart Data'!$C$19 -> 0 | F10: ='Chart Data'!$C$13 -> 2.33 | H10: ='Chart Data'!$C$14 -> 0 | J10: =IFERROR('Chart Data'!$C$13/ABS('Chart Data'!$C$14),0) -> 0 | L10: ='Chart Data'!$C$15 -> 2.33
B11: in the selected view | D11: peak to trough | F11: winning trades | H11: losing trades | J11: avg win / avg loss | L11: ="Worst "&TEXT('Chart Data'!$C$16,"0.00")&"R" -> Worst 2.33R
B13: DISCIPLINE & RISK CONTROL
B14: PLAN ADHERENCE | D14: RULE BREACHES | F14: A+ SETUP WIN RATE | H14: SWEEP TRADES WIN RATE | J14: LONGEST WIN STREAK | L14: LONGEST LOSS STREAK
B15: =IFERROR('Chart Data'!$C$20/('Chart Data'!$C$20+'Chart Data'!$C$21),0) -> 1 | D15: ='Chart Data'!$C$22 -> 0 | F15: =IF(N(Analytics!$C$87)=0,0,Analytics!$G$87) -> 1 | H15: =IF(N(Analytics!$C$73)=0,0,Analytics!$G$73) -> 1 | J15: ='Chart Data'!$C$24 -> 1 | L15: ='Chart Data'!$C$25 -> 0
B16: ="Yes "&'Chart Data'!$C$20&" / No "&'Chart Data'!$C$21 -> Yes 1 / No 0 | D16: =TEXT(IFERROR('Chart Data'!$C$22/'Chart Data'!$C$5,0),"0%")&" of trades flagged" -> 0% of trades flagged | F16: =N(Analytics!$C$87)&" A+ trades" -> 1 A+ trades | H16: =N(Analytics!$C$73)&" sweep trades" -> 1 sweep trades | J16: trades in a row | L16: ="Avg planned RR "&TEXT('Chart Data'!$C$23,"0.0")&"R" -> Avg planned RR 3.0R
B18: WHERE YOUR EDGE IS (and where it leaks)
B19: BEST SESSION | D19: BEST SETUP | F19: BEST PAIR | H19: BEST WEEKDAY | J19: WEAKEST SETUP | L19: COSTLIEST MISTAKE
B20: ='Chart Data'!$C$28 -> London | D20: ='Chart Data'!$C$30 -> Liquidity Sweep Reversal | F20: ='Chart Data'!$C$32 -> XAUUSD | H20: ='Chart Data'!$C$34 -> Mon | J20: ='Chart Data'!$C$36 -> None yet | L20: ='Chart Data'!$C$38 -> None yet
B21: ="Net "&TEXT('Chart Data'!$C$29,"$#,##0;-$#,##0") -> Net $230 | D21: ="Net "&TEXT('Chart Data'!$C$31,"$#,##0;-$#,##0") -> Net $230 | F21: ="Net "&TEXT('Chart Data'!$C$33,"$#,##0;-$#,##0") -> Net $230 | H21: ="Net "&TEXT('Chart Data'!$C$35,"$#,##0;-$#,##0") -> Net $230 | J21: ="Net "&TEXT('Chart Data'!$C$37,"$#,##0;-$#,##0") -> Net $0 | L21: ="Net "&TEXT('Chart Data'!$C$39,"$#,##0;-$#,##0") -> Net $0
B23: ="PROP CHALLENGE - "&'Goals & Prop'!$C$6&" - "&'Goals & Prop'!$C$22 -> PROP CHALLENGE - Prop Challenge - ON TRACK
B24: PROFIT TARGET PROGRESS | F24: DAILY LOSS LIMIT USED | J24: DRAWDOWN LIMIT USED
B25: ='Goals & Prop'!$C$12 -> 0 | F25: ='Goals & Prop'!$C$16 -> 0 | J25: ='Goals & Prop'!$C$19 -> 0
B26: =REPT("█",ROUND('Goals & Prop'!$C$12*24,0))&REPT("░",24-ROUND('Goals & Prop'!$C$12*24,0)) -> ░░░░░░░░░░░░░░░░░░░░░░░░ | F26: =REPT("█",ROUND('Goals & Prop'!$C$16*24,0))&REPT("░",24-ROUND('Goals & Prop'!$C$16*24,0)) -> ░░░░░░░░░░░░░░░░░░░░░░░░ | J26: =REPT("█",ROUND('Goals & Prop'!$C$19*24,0))&REPT("░",24-ROUND('Goals & Prop'!$C$19*24,0)) -> ░░░░░░░░░░░░░░░░░░░░░░░░
B27: CHARTS | J27: Equity window starts at trade # | L27: 1 | M27: (100 trades shown)

Sheet Journal
A1: FOREX TRADE JOURNAL
A2: Row 6 is a SAMPLE trade - overwrite it. Blue text = you type; grey = auto. Enter trades in date order, no gaps. Leave Exit Price blank for an open trade. Helper columns at the far right are grouped (click [+] to expand).
A4: TRADE INFO | K4: ANALYSIS & CONTEXT | Q4: CONFIRMATIONS (Yes / No) | Z4: EXECUTION (enter) | AI4: RESULTS (auto) | AW4: RISK RULES (auto) | BC4: PSYCHOLOGY & REVIEW | BJ4: HELPERS (auto, grouped)
A5: Trade # | B5: Date | C5: Day | D5: Wk | E5: Account | F5: Session | G5: Entry Time | H5: Exit Time | I5: Pair | J5: Direction | K5: HTF Bias | L5: Setup / Model | M5: Zone Type | N5: Liquidity Sweep? | O5: Sweep Type | P5: Analysis Notes | Q5: Structure Shift (MSS/CHoCH) | R5: Displacement | S5: FVG / Imbalance | T5: Rejection Candle | U5: HTF Aligned | V5: Killzone Timing | W5: News Clear | X5: Confirm. Count | Y5: Setup Grade | Z5: Planned Entry | AA5: Planned Stop | AB5: Entry Price | AC5: Stop Loss | AD5: Take Profit | AE5: Exit Price | AF5: Lot Size | AG5: Risk % | AH5: Fees ($) | AI5: Risk ($) | AJ5: Planned RR | AK5: Result (R) | AL5: Outcome | AM5: Net P&L ($) | AN5: Balance ($) | AO5: Cum. R | AP5: Result (pips) | AQ5: Hold (min) | AR5: Hold Bucket | AS5: Entry Hour | AT5: Slippage (pips, + = worse) | AU5: Stop Moved? | AV5: Suggested Lots | AW5: Balance Before ($) | AX5: Trade # Today | AY5: Day P&L Before ($) | AZ5: Day P&L After ($) | BA5: Week P&L Before ($) | BB5: Rule Check | BC5: Emotion at Entry | BD5: Followed Plan? | BE5: Mistake Tag | BF5: MFE (R) | BG5: MAE (R) | BH5: Screenshot / Chart Link | BI5: Lesson Learned / Journal | BJ5: Account Key | BK5: Acct Start ($) | BL5: Pip Size | BM5: Pip Value ($/lot) | BN5: Acct Peak ($) | BO5: Acct Drawdown % | BP5: In View (1/0) | BQ5: View Trade # | BR5: View Balance ($) | BS5: View Peak ($) | BT5: View Drawdown % | BU5: Win Streak | BV5: Loss Streak
A6: =IF(B6="","",ROW()-5) -> 1 | B6: 46293 | C6: =IF(B6="","",CHOOSE(WEEKDAY(B6,2),"Mon","Tue","Wed","Thu","Fri","Sat","Sun")) -> Mon | D6: =IF(B6="","",WEEKNUM(B6,2)) -> 40 | E6: Main Account | F6: London | G6: 0.35416667 | I6: XAUUSD | J6: Short | K6: Bearish | L6: Liquidity Sweep Reversal | M6: Order Block | N6: Yes | O6: Asia High | P6: Asia high swept at London open into 4H supply. 5m MSS + displacement left an FVG; entered on the FVG retest. | Q6: Yes | R6: Yes | S6: Yes | T6: No | U6: Yes | V6: Yes | W6: Yes | X6: =IF(B6="","",COUNTIF(Q6:W6,"Yes")) -> 6 | Y6: =IF(B6="","",IF(X6>=Settings!$C$16,"A+",IF(X6>=Settings!$C$17,"A",IF(X6>=Settings!$C$18,"B","C")))) -> A+ | AB6: 4120.5 | AC6: 4128 | AD6: 4098 | AE6: 4103 | AG6: 0.01 | AH6: 3.5 | AI6: =IF(B6="","",ROUND(IF(AG6="",Settings!$C$5,AG6)*AW6,2)) -> 100 | AJ6: =IF(OR(B6="",AB6="",AC6="",AD6=""),"",IFERROR(ROUND(ABS(AD6-AB6)/ABS(AB6-AC6),2),"")) -> 3 | AK6: =IF(OR(B6="",AB6="",AC6="",AE6=""),"",IFERROR(ROUND(IF(J6="Short",AB6-AE6,AE6-AB6)/ABS(AB6-AC6),2),"")) -> 2.33 | AL6: =IF(AK6="","",IF(ABS(AK6)<=Settings!$C$6,"BE",IF(AK6>0,"Win","Loss"))) -> Win | AM6: =IF(OR(AK6="",AI6=""),"",ROUND(AK6*AI6-N(AH6),2)) -> 229.5 | AN6: =IF(AM6="","",ROUND(BK6+SUMIFS(AM$6:AM6,BJ$6:BJ6,BJ6),2)) -> 10229.5 | AO6: =IF(AK6="","",ROUND(SUMIFS(AK$6:AK6,BJ$6:BJ6,BJ6),2)) -> 2.33 | AP6: =IF(OR(AK6="",BL6=""),"",IFERROR(ROUND(IF(J6="Short",AB6-AE6,AE6-AB6)/BL6,1),"")) -> 175 | AQ6: =IF(OR(G6="",H6=""),"",ROUND(MOD(H6-G6,1)*1440,0)) | AR6: =IF(AQ6="","",IF(AQ6<15,"Under 15m",IF(AQ6<60,"15-60m",IF(AQ6<240,"1-4 hours","4+ hours")))) | AS6: =IF(G6="","",HOUR(G6)) -> 8 | AT6: =IF(OR(Z6="",AB6="",BL6=""),"",IFERROR(ROUND(IF(J6="Short",Z6-AB6,AB6-Z6)/BL6,1),"")) | AU6: =IF(OR(AA6="",AC6=""),"",IF(AA6=AC6,"No","Yes")) | AV6: =IF(OR(B6="",BL6="",BM6="",AB6="",AC6=""),"",IFERROR(ROUND(AI6/(ABS(AB6-AC6)/BL6*BM6),2),"")) -> 0.13 | AW6: =IF(B6="","",ROUND(BK6+SUMIFS(AM$5:AM5,BJ$5:BJ5,BJ6),2)) -> 10000 | AX6: =IF(B6="","",COUNTIFS(B$6:B6,B6,BJ$6:BJ6,BJ6)) -> 1 | AY6: =IF(B6="","",ROUND(SUMIFS(AM$5:AM5,B$5:B5,B6,BJ$5:BJ5,BJ6),2)) -> 0 | AZ6: =IF(AM6="","",ROUND(AY6+AM6,2)) -> 229.5 | BA6: =IF(B6="","",ROUND(SUMIFS(AM$5:AM5,B$5:B5,">="&(B6-WEEKDAY(B6,2)+1),B$5:B5,"<="&B6,BJ$5:BJ5,BJ6),2)) -> 0 | BB6: =IF(B6="","",IF(AND(AF6<>"",AV6<>"",N(AF6)>N(AV6)*(1+Settings!$C$13)),"Oversized",IF(AX6>Settings!$C$10,"Overtraded",IF(AY6<=-Settings!$C$11*(AW6-AY6),"Daily loss hit",IF(BA6<=-Settings!$C$12*(AW6-BA6),"Weekly loss hit","OK"))))) -> OK | BC6: Calm / Focused | BD6: Yes | BE6: None (Followed Plan) | BF6: 3 | BG6: 0.4 | BH6: (paste your TradingView / screenshot link here) | BI6: Waited for the sweep and the structure shift before entering. Patience paid; no chasing. | BJ6: =IF(B6="","",IF(E6="",Settings!$F$5,E6)) -> Main Account | BK6: =IF(B6="","",IFERROR(INDEX(Settings!$G$5:$G$10,MATCH(BJ6,Settings!$F$5:$F$10,0)),Settings!$G$5)) -> 10000 | BL6: =IF(I6="","",IFERROR(1/(1/INDEX(Lists!$C$6:$C$17,MATCH(I6,Lists!$B$6:$B$17,0))),"")) -> 0.1 | BM6: =IF(I6="","",IFERROR(1/(1/INDEX(Lists!$D$6:$D$17,MATCH(I6,Lists!$B$6:$B$17,0))),"")) -> 10 | BN6: =IF(AN6="","",MAX(BK6,_xlfn.MAXIFS(AN$6:AN6,BJ$6:BJ6,BJ6))) -> 10229.5 | BO6: =IF(AN6="","",(AN6-BN6)/BN6) -> 0 | BP6: =IF(OR(B6="",AL6=""),0,IF(OR(Settings!$C$28="All Accounts",BJ6=Settings!$C$28),1,0)) -> 1 | BQ6: =IF(BP6=1,SUM(BP$6:BP6),"") -> 1 | BR6: =IF(BP6=1,ROUND(Settings!$C$29+SUMIFS(AM$6:AM6,BP$6:BP6,1),2),"") -> 60229.5 | BS6: =IF(BP6=1,MAX(Settings!$C$29,MAX(BR$6:BR6)),"") -> 60229.5 | BT6: =IF(BP6=1,(BR6-BS6)/BS6,"") -> 0 | BU6: =IF(BP6=1,IF(AL6="Win",1+IF(BQ6=1,0,INDEX(BU$5:BU5,MATCH(BQ6-1,BQ$5:BQ5,0))),0),"") -> 1 | BV6: =IF(BP6=1,IF(AL6="Loss",1+IF(BQ6=1,0,INDEX(BV$5:BV5,MATCH(BQ6-1,BQ$5:BQ5,0))),0),"") -> 0
A7: =IF(B7="","",ROW()-5) | C7: =IF(B7="","",CHOOSE(WEEKDAY(B7,2),"Mon","Tue","Wed","Thu","Fri","Sat","Sun")) | D7: =IF(B7="","",WEEKNUM(B7,2)) | X7: =IF(B7="","",COUNTIF(Q7:W7,"Yes")) | Y7: =IF(B7="","",IF(X7>=Settings!$C$16,"A+",IF(X7>=Settings!$C$17,"A",IF(X7>=Settings!$C$18,"B","C")))) | AI7: =IF(B7="","",ROUND(IF(AG7="",Settings!$C$5,AG7)*AW7,2)) | AJ7: =IF(OR(B7="",AB7="",AC7="",AD7=""),"",IFERROR(ROUND(ABS(AD7-AB7)/ABS(AB7-AC7),2),"")) | AK7: =IF(OR(B7="",AB7="",AC7="",AE7=""),"",IFERROR(ROUND(IF(J7="Short",AB7-AE7,AE7-AB7)/ABS(AB7-AC7),2),"")) | AL7: =IF(AK7="","",IF(ABS(AK7)<=Settings!$C$6,"BE",IF(AK7>0,"Win","Loss"))) | AM7: =IF(OR(AK7="",AI7=""),"",ROUND(AK7*AI7-N(AH7),2)) | AN7: =IF(AM7="","",ROUND(BK7+SUMIFS(AM$6:AM7,BJ$6:BJ7,BJ7),2)) | AO7: =IF(AK7="","",ROUND(SUMIFS(AK$6:AK7,BJ$6:BJ7,BJ7),2)) | AP7: =IF(OR(AK7="",BL7=""),"",IFERROR(ROUND(IF(J7="Short",AB7-AE7,AE7-AB7)/BL7,1),"")) | AQ7: =IF(OR(G7="",H7=""),"",ROUND(MOD(H7-G7,1)*1440,0)) | AR7: =IF(AQ7="","",IF(AQ7<15,"Under 15m",IF(AQ7<60,"15-60m",IF(AQ7<240,"1-4 hours","4+ hours")))) | AS7: =IF(G7="","",HOUR(G7)) | AT7: =IF(OR(Z7="",AB7="",BL7=""),"",IFERROR(ROUND(IF(J7="Short",Z7-AB7,AB7-Z7)/BL7,1),"")) | AU7: =IF(OR(AA7="",AC7=""),"",IF(AA7=AC7,"No","Yes")) | AV7: =IF(OR(B7="",BL7="",BM7="",AB7="",AC7=""),"",IFERROR(ROUND(AI7/(ABS(AB7-AC7)/BL7*BM7),2),"")) | AW7: =IF(B7="","",ROUND(BK7+SUMIFS(AM$5:AM6,BJ$5:BJ6,BJ7),2)) | AX7: =IF(B7="","",COUNTIFS(B$6:B7,B7,BJ$6:BJ7,BJ7)) | AY7: =IF(B7="","",ROUND(SUMIFS(AM$5:AM6,B$5:B6,B7,BJ$5:BJ6,BJ7),2)) | AZ7: =IF(AM7="","",ROUND(AY7+AM7,2)) | BA7: =IF(B7="","",ROUND(SUMIFS(AM$5:AM6,B$5:B6,">="&(B7-WEEKDAY(B7,2)+1),B$5:B6,"<="&B7,BJ$5:BJ6,BJ7),2)) | BB7: =IF(B7="","",IF(AND(AF7<>"",AV7<>"",N(AF7)>N(AV7)*(1+Settings!$C$13)),"Oversized",IF(AX7>Settings!$C$10,"Overtraded",IF(AY7<=-Settings!$C$11*(AW7-AY7),"Daily loss hit",IF(BA7<=-Settings!$C$12*(AW7-BA7),"Weekly loss hit","OK"))))) | BJ7: =IF(B7="","",IF(E7="",Settings!$F$5,E7)) | BK7: =IF(B7="","",IFERROR(INDEX(Settings!$G$5:$G$10,MATCH(BJ7,Settings!$F$5:$F$10,0)),Settings!$G$5)) | BL7: =IF(I7="","",IFERROR(1/(1/INDEX(Lists!$C$6:$C$17,MATCH(I7,Lists!$B$6:$B$17,0))),"")) | BM7: =IF(I7="","",IFERROR(1/(1/INDEX(Lists!$D$6:$D$17,MATCH(I7,Lists!$B$6:$B$17,0))),"")) | BN7: =IF(AN7="","",MAX(BK7,_xlfn.MAXIFS(AN$6:AN7,BJ$6:BJ7,BJ7))) | BO7: =IF(AN7="","",(AN7-BN7)/BN7) | BP7: =IF(OR(B7="",AL7=""),0,IF(OR(Settings!$C$28="All Accounts",BJ7=Settings!$C$28),1,0)) -> 0 | BQ7: =IF(BP7=1,SUM(BP$6:BP7),"") | BR7: =IF(BP7=1,ROUND(Settings!$C$29+SUMIFS(AM$6:AM7,BP$6:BP7,1),2),"") | BS7: =IF(BP7=1,MAX(Settings!$C$29,MAX(BR$6:BR7)),"") | BT7: =IF(BP7=1,(BR7-BS7)/BS7,"") | BU7: =IF(BP7=1,IF(AL7="Win",1+IF(BQ7=1,0,INDEX(BU$5:BU6,MATCH(BQ7-1,BQ$5:BQ6,0))),0),"") | BV7: =IF(BP7=1,IF(AL7="Loss",1+IF(BQ7=1,0,INDEX(BV$5:BV6,MATCH(BQ7-1,BQ$5:BQ6,0))),0),"")
A8: =IF(B8="","",ROW()-5) | C8: =IF(B8="","",CHOOSE(WEEKDAY(B8,2),"Mon","Tue","Wed","Thu","Fri","Sat","Sun")) | D8: =IF(B8="","",WEEKNUM(B8,2)) | X8: =IF(B8="","",COUNTIF(Q8:W8,"Yes")) | Y8: =IF(B8="","",IF(X8>=Settings!$C$16,"A+",IF(X8>=Settings!$C$17,"A",IF(X8>=Settings!$C$18,"B","C")))) | AI8: =IF(B8="","",ROUND(IF(AG8="",Settings!$C$5,AG8)*AW8,2)) | AJ8: =IF(OR(B8="",AB8="",AC8="",AD8=""),"",IFERROR(ROUND(ABS(AD8-AB8)/ABS(AB8-AC8),2),"")) | AK8: =IF(OR(B8="",AB8="",AC8="",AE8=""),"",IFERROR(ROUND(IF(J8="Short",AB8-AE8,AE8-AB8)/ABS(AB8-AC8),2),"")) | AL8: =IF(AK8="","",IF(ABS(AK8)<=Settings!$C$6,"BE",IF(AK8>0,"Win","Loss"))) | AM8: =IF(OR(AK8="",AI8=""),"",ROUND(AK8*AI8-N(AH8),2)) | AN8: =IF(AM8="","",ROUND(BK8+SUMIFS(AM$6:AM8,BJ$6:BJ8,BJ8),2)) | AO8: =IF(AK8="","",ROUND(SUMIFS(AK$6:AK8,BJ$6:BJ8,BJ8),2)) | AP8: =IF(OR(AK8="",BL8=""),"",IFERROR(ROUND(IF(J8="Short",AB8-AE8,AE8-AB8)/BL8,1),"")) | AQ8: =IF(OR(G8="",H8=""),"",ROUND(MOD(H8-G8,1)*1440,0)) | AR8: =IF(AQ8="","",IF(AQ8<15,"Under 15m",IF(AQ8<60,"15-60m",IF(AQ8<240,"1-4 hours","4+ hours")))) | AS8: =IF(G8="","",HOUR(G8)) | AT8: =IF(OR(Z8="",AB8="",BL8=""),"",IFERROR(ROUND(IF(J8="Short",Z8-AB8,AB8-Z8)/BL8,1),"")) | AU8: =IF(OR(AA8="",AC8=""),"",IF(AA8=AC8,"No","Yes")) | AV8: =IF(OR(B8="",BL8="",BM8="",AB8="",AC8=""),"",IFERROR(ROUND(AI8/(ABS(AB8-AC8)/BL8*BM8),2),"")) | AW8: =IF(B8="","",ROUND(BK8+SUMIFS(AM$5:AM7,BJ$5:BJ7,BJ8),2)) | AX8: =IF(B8="","",COUNTIFS(B$6:B8,B8,BJ$6:BJ8,BJ8)) | AY8: =IF(B8="","",ROUND(SUMIFS(AM$5:AM7,B$5:B7,B8,BJ$5:BJ7,BJ8),2)) | AZ8: =IF(AM8="","",ROUND(AY8+AM8,2)) | BA8: =IF(B8="","",ROUND(SUMIFS(AM$5:AM7,B$5:B7,">="&(B8-WEEKDAY(B8,2)+1),B$5:B7,"<="&B8,BJ$5:BJ7,BJ8),2)) | BB8: =IF(B8="","",IF(AND(AF8<>"",AV8<>"",N(AF8)>N(AV8)*(1+Settings!$C$13)),"Oversized",IF(AX8>Settings!$C$10,"Overtraded",IF(AY8<=-Settings!$C$11*(AW8-AY8),"Daily loss hit",IF(BA8<=-Settings!$C$12*(AW8-BA8),"Weekly loss hit","OK"))))) | BJ8: =IF(B8="","",IF(E8="",Settings!$F$5,E8)) | BK8: =IF(B8="","",IFERROR(INDEX(Settings!$G$5:$G$10,MATCH(BJ8,Settings!$F$5:$F$10,0)),Settings!$G$5)) | BL8: =IF(I8="","",IFERROR(1/(1/INDEX(Lists!$C$6:$C$17,MATCH(I8,Lists!$B$6:$B$17,0))),"")) | BM8: =IF(I8="","",IFERROR(1/(1/INDEX(Lists!$D$6:$D$17,MATCH(I8,Lists!$B$6:$B$17,0))),"")) | BN8: =IF(AN8="","",MAX(BK8,_xlfn.MAXIFS(AN$6:AN8,BJ$6:BJ8,BJ8))) | BO8: =IF(AN8="","",(AN8-BN8)/BN8) | BP8: =IF(OR(B8="",AL8=""),0,IF(OR(Settings!$C$28="All Accounts",BJ8=Settings!$C$28),1,0)) -> 0 | BQ8: =IF(BP8=1,SUM(BP$6:BP8),"") | BR8: =IF(BP8=1,ROUND(Settings!$C$29+SUMIFS(AM$6:AM8,BP$6:BP8,1),2),"") | BS8: =IF(BP8=1,MAX(Settings!$C$29,MAX(BR$6:BR8)),"") | BT8: =IF(BP8=1,(BR8-BS8)/BS8,"") | BU8: =IF(BP8=1,IF(AL8="Win",1+IF(BQ8=1,0,INDEX(BU$5:BU7,MATCH(BQ8-1,BQ$5:BQ7,0))),0),"") | BV8: =IF(BP8=1,IF(AL8="Loss",1+IF(BQ8=1,0,INDEX(BV$5:BV7,MATCH(BQ8-1,BQ$5:BQ7,0))),0),"")
A9: =IF(B9="","",ROW()-5) | C9: =IF(B9="","",CHOOSE(WEEKDAY(B9,2),"Mon","Tue","Wed","Thu","Fri","Sat","Sun")) | D9: =IF(B9="","",WEEKNUM(B9,2)) | X9: =IF(B9="","",COUNTIF(Q9:W9,"Yes")) | Y9: =IF(B9="","",IF(X9>=Settings!$C$16,"A+",IF(X9>=Settings!$C$17,"A",IF(X9>=Settings!$C$18,"B","C")))) | AI9: =IF(B9="","",ROUND(IF(AG9="",Settings!$C$5,AG9)*AW9,2)) | AJ9: =IF(OR(B9="",AB9="",AC9="",AD9=""),"",IFERROR(ROUND(ABS(AD9-AB9)/ABS(AB9-AC9),2),"")) | AK9: =IF(OR(B9="",AB9="",AC9="",AE9=""),"",IFERROR(ROUND(IF(J9="Short",AB9-AE9,AE9-AB9)/ABS(AB9-AC9),2),"")) | AL9: =IF(AK9="","",IF(ABS(AK9)<=Settings!$C$6,"BE",IF(AK9>0,"Win","Loss"))) | AM9: =IF(OR(AK9="",AI9=""),"",ROUND(AK9*AI9-N(AH9),2)) | AN9: =IF(AM9="","",ROUND(BK9+SUMIFS(AM$6:AM9,BJ$6:BJ9,BJ9),2)) | AO9: =IF(AK9="","",ROUND(SUMIFS(AK$6:AK9,BJ$6:BJ9,BJ9),2)) | AP9: =IF(OR(AK9="",BL9=""),"",IFERROR(ROUND(IF(J9="Short",AB9-AE9,AE9-AB9)/BL9,1),"")) | AQ9: =IF(OR(G9="",H9=""),"",ROUND(MOD(H9-G9,1)*1440,0)) | AR9: =IF(AQ9="","",IF(AQ9<15,"Under 15m",IF(AQ9<60,"15-60m",IF(AQ9<240,"1-4 hours","4+ hours")))) | AS9: =IF(G9="","",HOUR(G9)) | AT9: =IF(OR(Z9="",AB9="",BL9=""),"",IFERROR(ROUND(IF(J9="Short",Z9-AB9,AB9-Z9)/BL9,1),"")) | AU9: =IF(OR(AA9="",AC9=""),"",IF(AA9=AC9,"No","Yes")) | AV9: =IF(OR(B9="",BL9="",BM9="",AB9="",AC9=""),"",IFERROR(ROUND(AI9/(ABS(AB9-AC9)/BL9*BM9),2),"")) | AW9: =IF(B9="","",ROUND(BK9+SUMIFS(AM$5:AM8,BJ$5:BJ8,BJ9),2)) | AX9: =IF(B9="","",COUNTIFS(B$6:B9,B9,BJ$6:BJ9,BJ9)) | AY9: =IF(B9="","",ROUND(SUMIFS(AM$5:AM8,B$5:B8,B9,BJ$5:BJ8,BJ9),2)) | AZ9: =IF(AM9="","",ROUND(AY9+AM9,2)) | BA9: =IF(B9="","",ROUND(SUMIFS(AM$5:AM8,B$5:B8,">="&(B9-WEEKDAY(B9,2)+1),B$5:B8,"<="&B9,BJ$5:BJ8,BJ9),2)) | BB9: =IF(B9="","",IF(AND(AF9<>"",AV9<>"",N(AF9)>N(AV9)*(1+Settings!$C$13)),"Oversized",IF(AX9>Settings!$C$10,"Overtraded",IF(AY9<=-Settings!$C$11*(AW9-AY9),"Daily loss hit",IF(BA9<=-Settings!$C$12*(AW9-BA9),"Weekly loss hit","OK"))))) | BJ9: =IF(B9="","",IF(E9="",Settings!$F$5,E9)) | BK9: =IF(B9="","",IFERROR(INDEX(Settings!$G$5:$G$10,MATCH(BJ9,Settings!$F$5:$F$10,0)),Settings!$G$5)) | BL9: =IF(I9="","",IFERROR(1/(1/INDEX(Lists!$C$6:$C$17,MATCH(I9,Lists!$B$6:$B$17,0))),"")) | BM9: =IF(I9="","",IFERROR(1/(1/INDEX(Lists!$D$6:$D$17,MATCH(I9,Lists!$B$6:$B$17,0))),"")) | BN9: =IF(AN9="","",MAX(BK9,_xlfn.MAXIFS(AN$6:AN9,BJ$6:BJ9,BJ9))) | BO9: =IF(AN9="","",(AN9-BN9)/BN9) | BP9: =IF(OR(B9="",AL9=""),0,IF(OR(Settings!$C$28="All Accounts",BJ9=Settings!$C$28),1,0)) -> 0 | BQ9: =IF(BP9=1,SUM(BP$6:BP9),"") | BR9: =IF(BP9=1,ROUND(Settings!$C$29+SUMIFS(AM$6:AM9,BP$6:BP9,1),2),"") | BS9: =IF(BP9=1,MAX(Settings!$C$29,MAX(BR$6:BR9)),"") | BT9: =IF(BP9=1,(BR9-BS9)/BS9,"") | BU9: =IF(BP9=1,IF(AL9="Win",1+IF(BQ9=1,0,INDEX(BU$5:BU8,MATCH(BQ9-1,BQ$5:BQ8,0))),0),"") | BV9: =IF(BP9=1,IF(AL9="Loss",1+IF(BQ9=1,0,INDEX(BV$5:BV8,MATCH(BQ9-1,BQ$5:BQ8,0))),0),"")
A10: =IF(B10="","",ROW()-5) | C10: =IF(B10="","",CHOOSE(WEEKDAY(B10,2),"Mon","Tue","Wed","Thu","Fri","Sat","Sun")) | D10: =IF(B10="","",WEEKNUM(B10,2)) | X10: =IF(B10="","",COUNTIF(Q10:W10,"Yes")) | Y10: =IF(B10="","",IF(X10>=Settings!$C$16,"A+",IF(X10>=Settings!$C$17,"A",IF(X10>=Settings!$C$18,"B","C")))) | AI10: =IF(B10="","",ROUND(IF(AG10="",Settings!$C$5,AG10)*AW10,2)) | AJ10: =IF(OR(B10="",AB10="",AC10="",AD10=""),"",IFERROR(ROUND(ABS(AD10-AB10)/ABS(AB10-AC10),2),"")) | AK10: =IF(OR(B10="",AB10="",AC10="",AE10=""),"",IFERROR(ROUND(IF(J10="Short",AB10-AE10,AE10-AB10)/ABS(AB10-AC10),2),"")) | AL10: =IF(AK10="","",IF(ABS(AK10)<=Settings!$C$6,"BE",IF(AK10>0,"Win","Loss"))) | AM10: =IF(OR(AK10="",AI10=""),"",ROUND(AK10*AI10-N(AH10),2)) | AN10: =IF(AM10="","",ROUND(BK10+SUMIFS(AM$6:AM10,BJ$6:BJ10,BJ10),2)) | AO10: =IF(AK10="","",ROUND(SUMIFS(AK$6:AK10,BJ$6:BJ10,BJ10),2)) | AP10: =IF(OR(AK10="",BL10=""),"",IFERROR(ROUND(IF(J10="Short",AB10-AE10,AE10-AB10)/BL10,1),"")) | AQ10: =IF(OR(G10="",H10=""),"",ROUND(MOD(H10-G10,1)*1440,0)) | AR10: =IF(AQ10="","",IF(AQ10<15,"Under 15m",IF(AQ10<60,"15-60m",IF(AQ10<240,"1-4 hours","4+ hours")))) | AS10: =IF(G10="","",HOUR(G10)) | AT10: =IF(OR(Z10="",AB10="",BL10=""),"",IFERROR(ROUND(IF(J10="Short",Z10-AB10,AB10-Z10)/BL10,1),"")) | AU10: =IF(OR(AA10="",AC10=""),"",IF(AA10=AC10,"No","Yes")) | AV10: =IF(OR(B10="",BL10="",BM10="",AB10="",AC10=""),"",IFERROR(ROUND(AI10/(ABS(AB10-AC10)/BL10*BM10),2),"")) | AW10: =IF(B10="","",ROUND(BK10+SUMIFS(AM$5:AM9,BJ$5:BJ9,BJ10),2)) | AX10: =IF(B10="","",COUNTIFS(B$6:B10,B10,BJ$6:BJ10,BJ10)) | AY10: =IF(B10="","",ROUND(SUMIFS(AM$5:AM9,B$5:B9,B10,BJ$5:BJ9,BJ10),2)) | AZ10: =IF(AM10="","",ROUND(AY10+AM10,2)) | BA10: =IF(B10="","",ROUND(SUMIFS(AM$5:AM9,B$5:B9,">="&(B10-WEEKDAY(B10,2)+1),B$5:B9,"<="&B10,BJ$5:BJ9,BJ10),2)) | BB10: =IF(B10="","",IF(AND(AF10<>"",AV10<>"",N(AF10)>N(AV10)*(1+Settings!$C$13)),"Oversized",IF(AX10>Settings!$C$10,"Overtraded",IF(AY10<=-Settings!$C$11*(AW10-AY10),"Daily loss hit",IF(BA10<=-Settings!$C$12*(AW10-BA10),"Weekly loss hit","OK"))))) | BJ10: =IF(B10="","",IF(E10="",Settings!$F$5,E10)) | BK10: =IF(B10="","",IFERROR(INDEX(Settings!$G$5:$G$10,MATCH(BJ10,Settings!$F$5:$F$10,0)),Settings!$G$5)) | BL10: =IF(I10="","",IFERROR(1/(1/INDEX(Lists!$C$6:$C$17,MATCH(I10,Lists!$B$6:$B$17,0))),"")) | BM10: =IF(I10="","",IFERROR(1/(1/INDEX(Lists!$D$6:$D$17,MATCH(I10,Lists!$B$6:$B$17,0))),"")) | BN10: =IF(AN10="","",MAX(BK10,_xlfn.MAXIFS(AN$6:AN10,BJ$6:BJ10,BJ10))) | BO10: =IF(AN10="","",(AN10-BN10)/BN10) | BP10: =IF(OR(B10="",AL10=""),0,IF(OR(Settings!$C$28="All Accounts",BJ10=Settings!$C$28),1,0)) -> 0 | BQ10: =IF(BP10=1,SUM(BP$6:BP10),"") | BR10: =IF(BP10=1,ROUND(Settings!$C$29+SUMIFS(AM$6:AM10,BP$6:BP10,1),2),"") | BS10: =IF(BP10=1,MAX(Settings!$C$29,MAX(BR$6:BR10)),"") | BT10: =IF(BP10=1,(BR10-BS10)/BS10,"") | BU10: =IF(BP10=1,IF(AL10="Win",1+IF(BQ10=1,0,INDEX(BU$5:BU9,MATCH(BQ10-1,BQ$5:BQ9,0))),0),"") | BV10: =IF(BP10=1,IF(AL10="Loss",1+IF(BQ10=1,0,INDEX(BV$5:BV9,MATCH(BQ10-1,BQ$5:BQ9,0))),0),"")
A11: =IF(B11="","",ROW()-5) | C11: =IF(B11="","",CHOOSE(WEEKDAY(B11,2),"Mon","Tue","Wed","Thu","Fri","Sat","Sun")) | D11: =IF(B11="","",WEEKNUM(B11,2)) | X11: =IF(B11="","",COUNTIF(Q11:W11,"Yes")) | Y11: =IF(B11="","",IF(X11>=Settings!$C$16,"A+",IF(X11>=Settings!$C$17,"A",IF(X11>=Settings!$C$18,"B","C")))) | AI11: =IF(B11="","",ROUND(IF(AG11="",Settings!$C$5,AG11)*AW11,2)) | AJ11: =IF(OR(B11="",AB11="",AC11="",AD11=""),"",IFERROR(ROUND(ABS(AD11-AB11)/ABS(AB11-AC11),2),"")) | AK11: =IF(OR(B11="",AB11="",AC11="",AE11=""),"",IFERROR(ROUND(IF(J11="Short",AB11-AE11,AE11-AB11)/ABS(AB11-AC11),2),"")) | AL11: =IF(AK11="","",IF(ABS(AK11)<=Settings!$C$6,"BE",IF(AK11>0,"Win","Loss"))) | AM11: =IF(OR(AK11="",AI11=""),"",ROUND(AK11*AI11-N(AH11),2)) | AN11: =IF(AM11="","",ROUND(BK11+SUMIFS(AM$6:AM11,BJ$6:BJ11,BJ11),2)) | AO11: =IF(AK11="","",ROUND(SUMIFS(AK$6:AK11,BJ$6:BJ11,BJ11),2)) | AP11: =IF(OR(AK11="",BL11=""),"",IFERROR(ROUND(IF(J11="Short",AB11-AE11,AE11-AB11)/BL11,1),"")) | AQ11: =IF(OR(G11="",H11=""),"",ROUND(MOD(H11-G11,1)*1440,0)) | AR11: =IF(AQ11="","",IF(AQ11<15,"Under 15m",IF(AQ11<60,"15-60m",IF(AQ11<240,"1-4 hours","4+ hours")))) | AS11: =IF(G11="","",HOUR(G11)) | AT11: =IF(OR(Z11="",AB11="",BL11=""),"",IFERROR(ROUND(IF(J11="Short",Z11-AB11,AB11-Z11)/BL11,1),"")) | AU11: =IF(OR(AA11="",AC11=""),"",IF(AA11=AC11,"No","Yes")) | AV11: =IF(OR(B11="",BL11="",BM11="",AB11="",AC11=""),"",IFERROR(ROUND(AI11/(ABS(AB11-AC11)/BL11*BM11),2),"")) | AW11: =IF(B11="","",ROUND(BK11+SUMIFS(AM$5:AM10,BJ$5:BJ10,BJ11),2)) | AX11: =IF(B11="","",COUNTIFS(B$6:B11,B11,BJ$6:BJ11,BJ11)) | AY11: =IF(B11="","",ROUND(SUMIFS(AM$5:AM10,B$5:B10,B11,BJ$5:BJ10,BJ11),2)) | AZ11: =IF(AM11="","",ROUND(AY11+AM11,2)) | BA11: =IF(B11="","",ROUND(SUMIFS(AM$5:AM10,B$5:B10,">="&(B11-WEEKDAY(B11,2)+1),B$5:B10,"<="&B11,BJ$5:BJ10,BJ11),2)) | BB11: =IF(B11="","",IF(AND(AF11<>"",AV11<>"",N(AF11)>N(AV11)*(1+Settings!$C$13)),"Oversized",IF(AX11>Settings!$C$10,"Overtraded",IF(AY11<=-Settings!$C$11*(AW11-AY11),"Daily loss hit",IF(BA11<=-Settings!$C$12*(AW11-BA11),"Weekly loss hit","OK"))))) | BJ11: =IF(B11="","",IF(E11="",Settings!$F$5,E11)) | BK11: =IF(B11="","",IFERROR(INDEX(Settings!$G$5:$G$10,MATCH(BJ11,Settings!$F$5:$F$10,0)),Settings!$G$5)) | BL11: =IF(I11="","",IFERROR(1/(1/INDEX(Lists!$C$6:$C$17,MATCH(I11,Lists!$B$6:$B$17,0))),"")) | BM11: =IF(I11="","",IFERROR(1/(1/INDEX(Lists!$D$6:$D$17,MATCH(I11,Lists!$B$6:$B$17,0))),"")) | BN11: =IF(AN11="","",MAX(BK11,_xlfn.MAXIFS(AN$6:AN11,BJ$6:BJ11,BJ11))) | BO11: =IF(AN11="","",(AN11-BN11)/BN11) | BP11: =IF(OR(B11="",AL11=""),0,IF(OR(Settings!$C$28="All Accounts",BJ11=Settings!$C$28),1,0)) -> 0 | BQ11: =IF(BP11=1,SUM(BP$6:BP11),"") | BR11: =IF(BP11=1,ROUND(Settings!$C$29+SUMIFS(AM$6:AM11,BP$6:BP11,1),2),"") | BS11: =IF(BP11=1,MAX(Settings!$C$29,MAX(BR$6:BR11)),"") | BT11: =IF(BP11=1,(BR11-BS11)/BS11,"") | BU11: =IF(BP11=1,IF(AL11="Win",1+IF(BQ11=1,0,INDEX(BU$5:BU10,MATCH(BQ11-1,BQ$5:BQ10,0))),0),"") | BV11: =IF(BP11=1,IF(AL11="Loss",1+IF(BQ11=1,0,INDEX(BV$5:BV10,MATCH(BQ11-1,BQ$5:BQ10,0))),0),"")
A12: =IF(B12="","",ROW()-5) | C12: =IF(B12="","",CHOOSE(WEEKDAY(B12,2),"Mon","Tue","Wed","Thu","Fri","Sat","Sun")) | D12: =IF(B12="","",WEEKNUM(B12,2)) | X12: =IF(B12="","",COUNTIF(Q12:W12,"Yes")) | Y12: =IF(B12="","",IF(X12>=Settings!$C$16,"A+",IF(X12>=Settings!$C$17,"A",IF(X12>=Settings!$C$18,"B","C")))) | AI12: =IF(B12="","",ROUND(IF(AG12="",Settings!$C$5,AG12)*AW12,2)) | AJ12: =IF(OR(B12="",AB12="",AC12="",AD12=""),"",IFERROR(ROUND(ABS(AD12-AB12)/ABS(AB12-AC12),2),"")) | AK12: =IF(OR(B12="",AB12="",AC12="",AE12=""),"",IFERROR(ROUND(IF(J12="Short",AB12-AE12,AE12-AB12)/ABS(AB12-AC12),2),"")) | AL12: =IF(AK12="","",IF(ABS(AK12)<=Settings!$C$6,"BE",IF(AK12>0,"Win","Loss"))) | AM12: =IF(OR(AK12="",AI12=""),"",ROUND(AK12*AI12-N(AH12),2)) | AN12: =IF(AM12="","",ROUND(BK12+SUMIFS(AM$6:AM12,BJ$6:BJ12,BJ12),2)) | AO12: =IF(AK12="","",ROUND(SUMIFS(AK$6:AK12,BJ$6:BJ12,BJ12),2)) | AP12: =IF(OR(AK12="",BL12=""),"",IFERROR(ROUND(IF(J12="Short",AB12-AE12,AE12-AB12)/BL12,1),"")) | AQ12: =IF(OR(G12="",H12=""),"",ROUND(MOD(H12-G12,1)*1440,0)) | AR12: =IF(AQ12="","",IF(AQ12<15,"Under 15m",IF(AQ12<60,"15-60m",IF(AQ12<240,"1-4 hours","4+ hours")))) | AS12: =IF(G12="","",HOUR(G12)) | AT12: =IF(OR(Z12="",AB12="",BL12=""),"",IFERROR(ROUND(IF(J12="Short",Z12-AB12,AB12-Z12)/BL12,1),"")) | AU12: =IF(OR(AA12="",AC12=""),"",IF(AA12=AC12,"No","Yes")) | AV12: =IF(OR(B12="",BL12="",BM12="",AB12="",AC12=""),"",IFERROR(ROUND(AI12/(ABS(AB12-AC12)/BL12*BM12),2),"")) | AW12: =IF(B12="","",ROUND(BK12+SUMIFS(AM$5:AM11,BJ$5:BJ11,BJ12),2)) | AX12: =IF(B12="","",COUNTIFS(B$6:B12,B12,BJ$6:BJ12,BJ12)) | AY12: =IF(B12="","",ROUND(SUMIFS(AM$5:AM11,B$5:B11,B12,BJ$5:BJ11,BJ12),2)) | AZ12: =IF(AM12="","",ROUND(AY12+AM12,2)) | BA12: =IF(B12="","",ROUND(SUMIFS(AM$5:AM11,B$5:B11,">="&(B12-WEEKDAY(B12,2)+1),B$5:B11,"<="&B12,BJ$5:BJ11,BJ12),2)) | BB12: =IF(B12="","",IF(AND(AF12<>"",AV12<>"",N(AF12)>N(AV12)*(1+Settings!$C$13)),"Oversized",IF(AX12>Settings!$C$10,"Overtraded",IF(AY12<=-Settings!$C$11*(AW12-AY12),"Daily loss hit",IF(BA12<=-Settings!$C$12*(AW12-BA12),"Weekly loss hit","OK"))))) | BJ12: =IF(B12="","",IF(E12="",Settings!$F$5,E12)) | BK12: =IF(B12="","",IFERROR(INDEX(Settings!$G$5:$G$10,MATCH(BJ12,Settings!$F$5:$F$10,0)),Settings!$G$5)) | BL12: =IF(I12="","",IFERROR(1/(1/INDEX(Lists!$C$6:$C$17,MATCH(I12,Lists!$B$6:$B$17,0))),"")) | BM12: =IF(I12="","",IFERROR(1/(1/INDEX(Lists!$D$6:$D$17,MATCH(I12,Lists!$B$6:$B$17,0))),"")) | BN12: =IF(AN12="","",MAX(BK12,_xlfn.MAXIFS(AN$6:AN12,BJ$6:BJ12,BJ12))) | BO12: =IF(AN12="","",(AN12-BN12)/BN12) | BP12: =IF(OR(B12="",AL12=""),0,IF(OR(Settings!$C$28="All Accounts",BJ12=Settings!$C$28),1,0)) -> 0 | BQ12: =IF(BP12=1,SUM(BP$6:BP12),"") | BR12: =IF(BP12=1,ROUND(Settings!$C$29+SUMIFS(AM$6:AM12,BP$6:BP12,1),2),"") | BS12: =IF(BP12=1,MAX(Settings!$C$29,MAX(BR$6:BR12)),"") | BT12: =IF(BP12=1,(BR12-BS12)/BS12,"") | BU12: =IF(BP12=1,IF(AL12="Win",1+IF(BQ12=1,0,INDEX(BU$5:BU11,MATCH(BQ12-1,BQ$5:BQ11,0))),0),"") | BV12: =IF(BP12=1,IF(AL12="Loss",1+IF(BQ12=1,0,INDEX(BV$5:BV11,MATCH(BQ12-1,BQ$5:BQ11,0))),0),"")
A13: =IF(B13="","",ROW()-5) | C13: =IF(B13="","",CHOOSE(WEEKDAY(B13,2),"Mon","Tue","Wed","Thu","Fri","Sat","Sun")) | D13: =IF(B13="","",WEEKNUM(B13,2)) | X13: =IF(B13="","",COUNTIF(Q13:W13,"Yes")) | Y13: =IF(B13="","",IF(X13>=Settings!$C$16,"A+",IF(X13>=Settings!$C$17,"A",IF(X13>=Settings!$C$18,"B","C")))) | AI13: =IF(B13="","",ROUND(IF(AG13="",Settings!$C$5,AG13)*AW13,2)) | AJ13: =IF(OR(B13="",AB13="",AC13="",AD13=""),"",IFERROR(ROUND(ABS(AD13-AB13)/ABS(AB13-AC13),2),"")) | AK13: =IF(OR(B13="",AB13="",AC13="",AE13=""),"",IFERROR(ROUND(IF(J13="Short",AB13-AE13,AE13-AB13)/ABS(AB13-AC13),2),"")) | AL13: =IF(AK13="","",IF(ABS(AK13)<=Settings!$C$6,"BE",IF(AK13>0,"Win","Loss"))) | AM13: =IF(OR(AK13="",AI13=""),"",ROUND(AK13*AI13-N(AH13),2)) | AN13: =IF(AM13="","",ROUND(BK13+SUMIFS(AM$6:AM13,BJ$6:BJ13,BJ13),2)) | AO13: =IF(AK13="","",ROUND(SUMIFS(AK$6:AK13,BJ$6:BJ13,BJ13),2)) | AP13: =IF(OR(AK13="",BL13=""),"",IFERROR(ROUND(IF(J13="Short",AB13-AE13,AE13-AB13)/BL13,1),"")) | AQ13: =IF(OR(G13="",H13=""),"",ROUND(MOD(H13-G13,1)*1440,0)) | AR13: =IF(AQ13="","",IF(AQ13<15,"Under 15m",IF(AQ13<60,"15-60m",IF(AQ13<240,"1-4 hours","4+ hours")))) | AS13: =IF(G13="","",HOUR(G13)) | AT13: =IF(OR(Z13="",AB13="",BL13=""),"",IFERROR(ROUND(IF(J13="Short",Z13-AB13,AB13-Z13)/BL13,1),"")) | AU13: =IF(OR(AA13="",AC13=""),"",IF(AA13=AC13,"No","Yes")) | AV13: =IF(OR(B13="",BL13="",BM13="",AB13="",AC13=""),"",IFERROR(ROUND(AI13/(ABS(AB13-AC13)/BL13*BM13),2),"")) | AW13: =IF(B13="","",ROUND(BK13+SUMIFS(AM$5:AM12,BJ$5:BJ12,BJ13),2)) | AX13: =IF(B13="","",COUNTIFS(B$6:B13,B13,BJ$6:BJ13,BJ13)) | AY13: =IF(B13="","",ROUND(SUMIFS(AM$5:AM12,B$5:B12,B13,BJ$5:BJ12,BJ13),2)) | AZ13: =IF(AM13="","",ROUND(AY13+AM13,2)) | BA13: =IF(B13="","",ROUND(SUMIFS(AM$5:AM12,B$5:B12,">="&(B13-WEEKDAY(B13,2)+1),B$5:B12,"<="&B13,BJ$5:BJ12,BJ13),2)) | BB13: =IF(B13="","",IF(AND(AF13<>"",AV13<>"",N(AF13)>N(AV13)*(1+Settings!$C$13)),"Oversized",IF(AX13>Settings!$C$10,"Overtraded",IF(AY13<=-Settings!$C$11*(AW13-AY13),"Daily loss hit",IF(BA13<=-Settings!$C$12*(AW13-BA13),"Weekly loss hit","OK"))))) | BJ13: =IF(B13="","",IF(E13="",Settings!$F$5,E13)) | BK13: =IF(B13="","",IFERROR(INDEX(Settings!$G$5:$G$10,MATCH(BJ13,Settings!$F$5:$F$10,0)),Settings!$G$5)) | BL13: =IF(I13="","",IFERROR(1/(1/INDEX(Lists!$C$6:$C$17,MATCH(I13,Lists!$B$6:$B$17,0))),"")) | BM13: =IF(I13="","",IFERROR(1/(1/INDEX(Lists!$D$6:$D$17,MATCH(I13,Lists!$B$6:$B$17,0))),"")) | BN13: =IF(AN13="","",MAX(BK13,_xlfn.MAXIFS(AN$6:AN13,BJ$6:BJ13,BJ13))) | BO13: =IF(AN13="","",(AN13-BN13)/BN13) | BP13: =IF(OR(B13="",AL13=""),0,IF(OR(Settings!$C$28="All Accounts",BJ13=Settings!$C$28),1,0)) -> 0 | BQ13: =IF(BP13=1,SUM(BP$6:BP13),"") | BR13: =IF(BP13=1,ROUND(Settings!$C$29+SUMIFS(AM$6:AM13,BP$6:BP13,1),2),"") | BS13: =IF(BP13=1,MAX(Settings!$C$29,MAX(BR$6:BR13)),"") | BT13: =IF(BP13=1,(BR13-BS13)/BS13,"") | BU13: =IF(BP13=1,IF(AL13="Win",1+IF(BQ13=1,0,INDEX(BU$5:BU12,MATCH(BQ13-1,BQ$5:BQ12,0))),0),"") | BV13: =IF(BP13=1,IF(AL13="Loss",1+IF(BQ13=1,0,INDEX(BV$5:BV12,MATCH(BQ13-1,BQ$5:BQ12,0))),0),"")
A14: =IF(B14="","",ROW()-5) | C14: =IF(B14="","",CHOOSE(WEEKDAY(B14,2),"Mon","Tue","Wed","Thu","Fri","Sat","Sun")) | D14: =IF(B14="","",WEEKNUM(B14,2)) | X14: =IF(B14="","",COUNTIF(Q14:W14,"Yes")) | Y14: =IF(B14="","",IF(X14>=Settings!$C$16,"A+",IF(X14>=Settings!$C$17,"A",IF(X14>=Settings!$C$18,"B","C")))) | AI14: =IF(B14="","",ROUND(IF(AG14="",Settings!$C$5,AG14)*AW14,2)) | AJ14: =IF(OR(B14="",AB14="",AC14="",AD14=""),"",IFERROR(ROUND(ABS(AD14-AB14)/ABS(AB14-AC14),2),"")) | AK14: =IF(OR(B14="",AB14="",AC14="",AE14=""),"",IFERROR(ROUND(IF(J14="Short",AB14-AE14,AE14-AB14)/ABS(AB14-AC14),2),"")) | AL14: =IF(AK14="","",IF(ABS(AK14)<=Settings!$C$6,"BE",IF(AK14>0,"Win","Loss"))) | AM14: =IF(OR(AK14="",AI14=""),"",ROUND(AK14*AI14-N(AH14),2)) | AN14: =IF(AM14="","",ROUND(BK14+SUMIFS(AM$6:AM14,BJ$6:BJ14,BJ14),2)) | AO14: =IF(AK14="","",ROUND(SUMIFS(AK$6:AK14,BJ$6:BJ14,BJ14),2)) | AP14: =IF(OR(AK14="",BL14=""),"",IFERROR(ROUND(IF(J14="Short",AB14-AE14,AE14-AB14)/BL14,1),"")) | AQ14: =IF(OR(G14="",H14=""),"",ROUND(MOD(H14-G14,1)*1440,0)) | AR14: =IF(AQ14="","",IF(AQ14<15,"Under 15m",IF(AQ14<60,"15-60m",IF(AQ14<240,"1-4 hours","4+ hours")))) | AS14: =IF(G14="","",HOUR(G14)) | AT14: =IF(OR(Z14="",AB14="",BL14=""),"",IFERROR(ROUND(IF(J14="Short",Z14-AB14,AB14-Z14)/BL14,1),"")) | AU14: =IF(OR(AA14="",AC14=""),"",IF(AA14=AC14,"No","Yes")) | AV14: =IF(OR(B14="",BL14="",BM14="",AB14="",AC14=""),"",IFERROR(ROUND(AI14/(ABS(AB14-AC14)/BL14*BM14),2),"")) | AW14: =IF(B14="","",ROUND(BK14+SUMIFS(AM$5:AM13,BJ$5:BJ13,BJ14),2)) | AX14: =IF(B14="","",COUNTIFS(B$6:B14,B14,BJ$6:BJ14,BJ14)) | AY14: =IF(B14="","",ROUND(SUMIFS(AM$5:AM13,B$5:B13,B14,BJ$5:BJ13,BJ14),2)) | AZ14: =IF(AM14="","",ROUND(AY14+AM14,2)) | BA14: =IF(B14="","",ROUND(SUMIFS(AM$5:AM13,B$5:B13,">="&(B14-WEEKDAY(B14,2)+1),B$5:B13,"<="&B14,BJ$5:BJ13,BJ14),2)) | BB14: =IF(B14="","",IF(AND(AF14<>"",AV14<>"",N(AF14)>N(AV14)*(1+Settings!$C$13)),"Oversized",IF(AX14>Settings!$C$10,"Overtraded",IF(AY14<=-Settings!$C$11*(AW14-AY14),"Daily loss hit",IF(BA14<=-Settings!$C$12*(AW14-BA14),"Weekly loss hit","OK"))))) | BJ14: =IF(B14="","",IF(E14="",Settings!$F$5,E14)) | BK14: =IF(B14="","",IFERROR(INDEX(Settings!$G$5:$G$10,MATCH(BJ14,Settings!$F$5:$F$10,0)),Settings!$G$5)) | BL14: =IF(I14="","",IFERROR(1/(1/INDEX(Lists!$C$6:$C$17,MATCH(I14,Lists!$B$6:$B$17,0))),"")) | BM14: =IF(I14="","",IFERROR(1/(1/INDEX(Lists!$D$6:$D$17,MATCH(I14,Lists!$B$6:$B$17,0))),"")) | BN14: =IF(AN14="","",MAX(BK14,_xlfn.MAXIFS(AN$6:AN14,BJ$6:BJ14,BJ14))) | BO14: =IF(AN14="","",(AN14-BN14)/BN14) | BP14: =IF(OR(B14="",AL14=""),0,IF(OR(Settings!$C$28="All Accounts",BJ14=Settings!$C$28),1,0)) -> 0 | BQ14: =IF(BP14=1,SUM(BP$6:BP14),"") | BR14: =IF(BP14=1,ROUND(Settings!$C$29+SUMIFS(AM$6:AM14,BP$6:BP14,1),2),"") | BS14: =IF(BP14=1,MAX(Settings!$C$29,MAX(BR$6:BR14)),"") | BT14: =IF(BP14=1,(BR14-BS14)/BS14,"") | BU14: =IF(BP14=1,IF(AL14="Win",1+IF(BQ14=1,0,INDEX(BU$5:BU13,MATCH(BQ14-1,BQ$5:BQ13,0))),0),"") | BV14: =IF(BP14=1,IF(AL14="Loss",1+IF(BQ14=1,0,INDEX(BV$5:BV13,MATCH(BQ14-1,BQ$5:BQ13,0))),0),"")
A15: =IF(B15="","",ROW()-5) | C15: =IF(B15="","",CHOOSE(WEEKDAY(B15,2),"Mon","Tue","Wed","Thu","Fri","Sat","Sun")) | D15: =IF(B15="","",WEEKNUM(B15,2)) | X15: =IF(B15="","",COUNTIF(Q15:W15,"Yes")) | Y15: =IF(B15="","",IF(X15>=Settings!$C$16,"A+",IF(X15>=Settings!$C$17,"A",IF(X15>=Settings!$C$18,"B","C")))) | AI15: =IF(B15="","",ROUND(IF(AG15="",Settings!$C$5,AG15)*AW15,2)) | AJ15: =IF(OR(B15="",AB15="",AC15="",AD15=""),"",IFERROR(ROUND(ABS(AD15-AB15)/ABS(AB15-AC15),2),"")) | AK15: =IF(OR(B15="",AB15="",AC15="",AE15=""),"",IFERROR(ROUND(IF(J15="Short",AB15-AE15,AE15-AB15)/ABS(AB15-AC15),2),"")) | AL15: =IF(AK15="","",IF(ABS(AK15)<=Settings!$C$6,"BE",IF(AK15>0,"Win","Loss"))) | AM15: =IF(OR(AK15="",AI15=""),"",ROUND(AK15*AI15-N(AH15),2)) | AN15: =IF(AM15="","",ROUND(BK15+SUMIFS(AM$6:AM15,BJ$6:BJ15,BJ15),2)) | AO15: =IF(AK15="","",ROUND(SUMIFS(AK$6:AK15,BJ$6:BJ15,BJ15),2)) | AP15: =IF(OR(AK15="",BL15=""),"",IFERROR(ROUND(IF(J15="Short",AB15-AE15,AE15-AB15)/BL15,1),"")) | AQ15: =IF(OR(G15="",H15=""),"",ROUND(MOD(H15-G15,1)*1440,0)) | AR15: =IF(AQ15="","",IF(AQ15<15,"Under 15m",IF(AQ15<60,"15-60m",IF(AQ15<240,"1-4 hours","4+ hours")))) | AS15: =IF(G15="","",HOUR(G15)) | AT15: =IF(OR(Z15="",AB15="",BL15=""),"",IFERROR(ROUND(IF(J15="Short",Z15-AB15,AB15-Z15)/BL15,1),"")) | AU15: =IF(OR(AA15="",AC15=""),"",IF(AA15=AC15,"No","Yes")) | AV15: =IF(OR(B15="",BL15="",BM15="",AB15="",AC15=""),"",IFERROR(ROUND(AI15/(ABS(AB15-AC15)/BL15*BM15),2),"")) | AW15: =IF(B15="","",ROUND(BK15+SUMIFS(AM$5:AM14,BJ$5:BJ14,BJ15),2)) | AX15: =IF(B15="","",COUNTIFS(B$6:B15,B15,BJ$6:BJ15,BJ15)) | AY15: =IF(B15="","",ROUND(SUMIFS(AM$5:AM14,B$5:B14,B15,BJ$5:BJ14,BJ15),2)) | AZ15: =IF(AM15="","",ROUND(AY15+AM15,2)) | BA15: =IF(B15="","",ROUND(SUMIFS(AM$5:AM14,B$5:B14,">="&(B15-WEEKDAY(B15,2)+1),B$5:B14,"<="&B15,BJ$5:BJ14,BJ15),2)) | BB15: =IF(B15="","",IF(AND(AF15<>"",AV15<>"",N(AF15)>N(AV15)*(1+Settings!$C$13)),"Oversized",IF(AX15>Settings!$C$10,"Overtraded",IF(AY15<=-Settings!$C$11*(AW15-AY15),"Daily loss hit",IF(BA15<=-Settings!$C$12*(AW15-BA15),"Weekly loss hit","OK"))))) | BJ15: =IF(B15="","",IF(E15="",Settings!$F$5,E15)) | BK15: =IF(B15="","",IFERROR(INDEX(Settings!$G$5:$G$10,MATCH(BJ15,Settings!$F$5:$F$10,0)),Settings!$G$5)) | BL15: =IF(I15="","",IFERROR(1/(1/INDEX(Lists!$C$6:$C$17,MATCH(I15,Lists!$B$6:$B$17,0))),"")) | BM15: =IF(I15="","",IFERROR(1/(1/INDEX(Lists!$D$6:$D$17,MATCH(I15,Lists!$B$6:$B$17,0))),"")) | BN15: =IF(AN15="","",MAX(BK15,_xlfn.MAXIFS(AN$6:AN15,BJ$6:BJ15,BJ15))) | BO15: =IF(AN15="","",(AN15-BN15)/BN15) | BP15: =IF(OR(B15="",AL15=""),0,IF(OR(Settings!$C$28="All Accounts",BJ15=Settings!$C$28),1,0)) -> 0 | BQ15: =IF(BP15=1,SUM(BP$6:BP15),"") | BR15: =IF(BP15=1,ROUND(Settings!$C$29+SUMIFS(AM$6:AM15,BP$6:BP15,1),2),"") | BS15: =IF(BP15=1,MAX(Settings!$C$29,MAX(BR$6:BR15)),"") | BT15: =IF(BP15=1,(BR15-BS15)/BS15,"") | BU15: =IF(BP15=1,IF(AL15="Win",1+IF(BQ15=1,0,INDEX(BU$5:BU14,MATCH(BQ15-1,BQ$5:BQ14,0))),0),"") | BV15: =IF(BP15=1,IF(AL15="Loss",1+IF(BQ15=1,0,INDEX(BV$5:BV14,MATCH(BQ15-1,BQ$5:BQ14,0))),0),"")
A16: =IF(B16="","",ROW()-5) | C16: =IF(B16="","",CHOOSE(WEEKDAY(B16,2),"Mon","Tue","Wed","Thu","Fri","Sat","Sun")) | D16: =IF(B16="","",WEEKNUM(B16,2)) | X16: =IF(B16="","",COUNTIF(Q16:W16,"Yes")) | Y16: =IF(B16="","",IF(X16>=Settings!$C$16,"A+",IF(X16>=Settings!$C$17,"A",IF(X16>=Settings!$C$18,"B","C")))) | AI16: =IF(B16="","",ROUND(IF(AG16="",Settings!$C$5,AG16)*AW16,2)) | AJ16: =IF(OR(B16="",AB16="",AC16="",AD16=""),"",IFERROR(ROUND(ABS(AD16-AB16)/ABS(AB16-AC16),2),"")) | AK16: =IF(OR(B16="",AB16="",AC16="",AE16=""),"",IFERROR(ROUND(IF(J16="Short",AB16-AE16,AE16-AB16)/ABS(AB16-AC16),2),"")) | AL16: =IF(AK16="","",IF(ABS(AK16)<=Settings!$C$6,"BE",IF(AK16>0,"Win","Loss"))) | AM16: =IF(OR(AK16="",AI16=""),"",ROUND(AK16*AI16-N(AH16),2)) | AN16: =IF(AM16="","",ROUND(BK16+SUMIFS(AM$6:AM16,BJ$6:BJ16,BJ16),2)) | AO16: =IF(AK16="","",ROUND(SUMIFS(AK$6:AK16,BJ$6:BJ16,BJ16),2)) | AP16: =IF(OR(AK16="",BL16=""),"",IFERROR(ROUND(IF(J16="Short",AB16-AE16,AE16-AB16)/BL16,1),"")) | AQ16: =IF(OR(G16="",H16=""),"",ROUND(MOD(H16-G16,1)*1440,0)) | AR16: =IF(AQ16="","",IF(AQ16<15,"Under 15m",IF(AQ16<60,"15-60m",IF(AQ16<240,"1-4 hours","4+ hours")))) | AS16: =IF(G16="","",HOUR(G16)) | AT16: =IF(OR(Z16="",AB16="",BL16=""),"",IFERROR(ROUND(IF(J16="Short",Z16-AB16,AB16-Z16)/BL16,1),"")) | AU16: =IF(OR(AA16="",AC16=""),"",IF(AA16=AC16,"No","Yes")) | AV16: =IF(OR(B16="",BL16="",BM16="",AB16="",AC16=""),"",IFERROR(ROUND(AI16/(ABS(AB16-AC16)/BL16*BM16),2),"")) | AW16: =IF(B16="","",ROUND(BK16+SUMIFS(AM$5:AM15,BJ$5:BJ15,BJ16),2)) | AX16: =IF(B16="","",COUNTIFS(B$6:B16,B16,BJ$6:BJ16,BJ16)) | AY16: =IF(B16="","",ROUND(SUMIFS(AM$5:AM15,B$5:B15,B16,BJ$5:BJ15,BJ16),2)) | AZ16: =IF(AM16="","",ROUND(AY16+AM16,2)) | BA16: =IF(B16="","",ROUND(SUMIFS(AM$5:AM15,B$5:B15,">="&(B16-WEEKDAY(B16,2)+1),B$5:B15,"<="&B16,BJ$5:BJ15,BJ16),2)) | BB16: =IF(B16="","",IF(AND(AF16<>"",AV16<>"",N(AF16)>N(AV16)*(1+Settings!$C$13)),"Oversized",IF(AX16>Settings!$C$10,"Overtraded",IF(AY16<=-Settings!$C$11*(AW16-AY16),"Daily loss hit",IF(BA16<=-Settings!$C$12*(AW16-BA16),"Weekly loss hit","OK"))))) | BJ16: =IF(B16="","",IF(E16="",Settings!$F$5,E16)) | BK16: =IF(B16="","",IFERROR(INDEX(Settings!$G$5:$G$10,MATCH(BJ16,Settings!$F$5:$F$10,0)),Settings!$G$5)) | BL16: =IF(I16="","",IFERROR(1/(1/INDEX(Lists!$C$6:$C$17,MATCH(I16,Lists!$B$6:$B$17,0))),"")) | BM16: =IF(I16="","",IFERROR(1/(1/INDEX(Lists!$D$6:$D$17,MATCH(I16,Lists!$B$6:$B$17,0))),"")) | BN16: =IF(AN16="","",MAX(BK16,_xlfn.MAXIFS(AN$6:AN16,BJ$6:BJ16,BJ16))) | BO16: =IF(AN16="","",(AN16-BN16)/BN16) | BP16: =IF(OR(B16="",AL16=""),0,IF(OR(Settings!$C$28="All Accounts",BJ16=Settings!$C$28),1,0)) -> 0 | BQ16: =IF(BP16=1,SUM(BP$6:BP16),"") | BR16: =IF(BP16=1,ROUND(Settings!$C$29+SUMIFS(AM$6:AM16,BP$6:BP16,1),2),"") | BS16: =IF(BP16=1,MAX(Settings!$C$29,MAX(BR$6:BR16)),"") | BT16: =IF(BP16=1,(BR16-BS16)/BS16,"") | BU16: =IF(BP16=1,IF(AL16="Win",1+IF(BQ16=1,0,INDEX(BU$5:BU15,MATCH(BQ16-1,BQ$5:BQ15,0))),0),"") | BV16: =IF(BP16=1,IF(AL16="Loss",1+IF(BQ16=1,0,INDEX(BV$5:BV15,MATCH(BQ16-1,BQ$5:BQ15,0))),0),"")
A17: =IF(B17="","",ROW()-5) | C17: =IF(B17="","",CHOOSE(WEEKDAY(B17,2),"Mon","Tue","Wed","Thu","Fri","Sat","Sun")) | D17: =IF(B17="","",WEEKNUM(B17,2)) | X17: =IF(B17="","",COUNTIF(Q17:W17,"Yes")) | Y17: =IF(B17="","",IF(X17>=Settings!$C$16,"A+",IF(X17>=Settings!$C$17,"A",IF(X17>=Settings!$C$18,"B","C")))) | AI17: =IF(B17="","",ROUND(IF(AG17="",Settings!$C$5,AG17)*AW17,2)) | AJ17: =IF(OR(B17="",AB17="",AC17="",AD17=""),"",IFERROR(ROUND(ABS(AD17-AB17)/ABS(AB17-AC17),2),"")) | AK17: =IF(OR(B17="",AB17="",AC17="",AE17=""),"",IFERROR(ROUND(IF(J17="Short",AB17-AE17,AE17-AB17)/ABS(AB17-AC17),2),"")) | AL17: =IF(AK17="","",IF(ABS(AK17)<=Settings!$C$6,"BE",IF(AK17>0,"Win","Loss"))) | AM17: =IF(OR(AK17="",AI17=""),"",ROUND(AK17*AI17-N(AH17),2)) | AN17: =IF(AM17="","",ROUND(BK17+SUMIFS(AM$6:AM17,BJ$6:BJ17,BJ17),2)) | AO17: =IF(AK17="","",ROUND(SUMIFS(AK$6:AK17,BJ$6:BJ17,BJ17),2)) | AP17: =IF(OR(AK17="",BL17=""),"",IFERROR(ROUND(IF(J17="Short",AB17-AE17,AE17-AB17)/BL17,1),"")) | AQ17: =IF(OR(G17="",H17=""),"",ROUND(MOD(H17-G17,1)*1440,0)) | AR17: =IF(AQ17="","",IF(AQ17<15,"Under 15m",IF(AQ17<60,"15-60m",IF(AQ17<240,"1-4 hours","4+ hours")))) | AS17: =IF(G17="","",HOUR(G17)) | AT17: =IF(OR(Z17="",AB17="",BL17=""),"",IFERROR(ROUND(IF(J17="Short",Z17-AB17,AB17-Z17)/BL17,1),"")) | AU17: =IF(OR(AA17="",AC17=""),"",IF(AA17=AC17,"No","Yes")) | AV17: =IF(OR(B17="",BL17="",BM17="",AB17="",AC17=""),"",IFERROR(ROUND(AI17/(ABS(AB17-AC17)/BL17*BM17),2),"")) | AW17: =IF(B17="","",ROUND(BK17+SUMIFS(AM$5:AM16,BJ$5:BJ16,BJ17),2)) | AX17: =IF(B17="","",COUNTIFS(B$6:B17,B17,BJ$6:BJ17,BJ17)) | AY17: =IF(B17="","",ROUND(SUMIFS(AM$5:AM16,B$5:B16,B17,BJ$5:BJ16,BJ17),2)) | AZ17: =IF(AM17="","",ROUND(AY17+AM17,2)) | BA17: =IF(B17="","",ROUND(SUMIFS(AM$5:AM16,B$5:B16,">="&(B17-WEEKDAY(B17,2)+1),B$5:B16,"<="&B17,BJ$5:BJ16,BJ17),2)) | BB17: =IF(B17="","",IF(AND(AF17<>"",AV17<>"",N(AF17)>N(AV17)*(1+Settings!$C$13)),"Oversized",IF(AX17>Settings!$C$10,"Overtraded",IF(AY17<=-Settings!$C$11*(AW17-AY17),"Daily loss hit",IF(BA17<=-Settings!$C$12*(AW17-BA17),"Weekly loss hit","OK"))))) | BJ17: =IF(B17="","",IF(E17="",Settings!$F$5,E17)) | BK17: =IF(B17="","",IFERROR(INDEX(Settings!$G$5:$G$10,MATCH(BJ17,Settings!$F$5:$F$10,0)),Settings!$G$5)) | BL17: =IF(I17="","",IFERROR(1/(1/INDEX(Lists!$C$6:$C$17,MATCH(I17,Lists!$B$6:$B$17,0))),"")) | BM17: =IF(I17="","",IFERROR(1/(1/INDEX(Lists!$D$6:$D$17,MATCH(I17,Lists!$B$6:$B$17,0))),"")) | BN17: =IF(AN17="","",MAX(BK17,_xlfn.MAXIFS(AN$6:AN17,BJ$6:BJ17,BJ17))) | BO17: =IF(AN17="","",(AN17-BN17)/BN17) | BP17: =IF(OR(B17="",AL17=""),0,IF(OR(Settings!$C$28="All Accounts",BJ17=Settings!$C$28),1,0)) -> 0 | BQ17: =IF(BP17=1,SUM(BP$6:BP17),"") | BR17: =IF(BP17=1,ROUND(Settings!$C$29+SUMIFS(AM$6:AM17,BP$6:BP17,1),2),"") | BS17: =IF(BP17=1,MAX(Settings!$C$29,MAX(BR$6:BR17)),"") | BT17: =IF(BP17=1,(BR17-BS17)/BS17,"") | BU17: =IF(BP17=1,IF(AL17="Win",1+IF(BQ17=1,0,INDEX(BU$5:BU16,MATCH(BQ17-1,BQ$5:BQ16,0))),0),"") | BV17: =IF(BP17=1,IF(AL17="Loss",1+IF(BQ17=1,0,INDEX(BV$5:BV16,MATCH(BQ17-1,BQ$5:BQ16,0))),0),"")
A18: =IF(B18="","",ROW()-5) | C18: =IF(B18="","",CHOOSE(WEEKDAY(B18,2),"Mon","Tue","Wed","Thu","Fri","Sat","Sun")) | D18: =IF(B18="","",WEEKNUM(B18,2)) | X18: =IF(B18="","",COUNTIF(Q18:W18,"Yes")) | Y18: =IF(B18="","",IF(X18>=Settings!$C$16,"A+",IF(X18>=Settings!$C$17,"A",IF(X18>=Settings!$C$18,"B","C")))) | AI18: =IF(B18="","",ROUND(IF(AG18="",Settings!$C$5,AG18)*AW18,2)) | AJ18: =IF(OR(B18="",AB18="",AC18="",AD18=""),"",IFERROR(ROUND(ABS(AD18-AB18)/ABS(AB18-AC18),2),"")) | AK18: =IF(OR(B18="",AB18="",AC18="",AE18=""),"",IFERROR(ROUND(IF(J18="Short",AB18-AE18,AE18-AB18)/ABS(AB18-AC18),2),"")) | AL18: =IF(AK18="","",IF(ABS(AK18)<=Settings!$C$6,"BE",IF(AK18>0,"Win","Loss"))) | AM18: =IF(OR(AK18="",AI18=""),"",ROUND(AK18*AI18-N(AH18),2)) | AN18: =IF(AM18="","",ROUND(BK18+SUMIFS(AM$6:AM18,BJ$6:BJ18,BJ18),2)) | AO18: =IF(AK18="","",ROUND(SUMIFS(AK$6:AK18,BJ$6:BJ18,BJ18),2)) | AP18: =IF(OR(AK18="",BL18=""),"",IFERROR(ROUND(IF(J18="Short",AB18-AE18,AE18-AB18)/BL18,1),"")) | AQ18: =IF(OR(G18="",H18=""),"",ROUND(MOD(H18-G18,1)*1440,0)) | AR18: =IF(AQ18="","",IF(AQ18<15,"Under 15m",IF(AQ18<60,"15-60m",IF(AQ18<240,"1-4 hours","4+ hours")))) | AS18: =IF(G18="","",HOUR(G18)) | AT18: =IF(OR(Z18="",AB18="",BL18=""),"",IFERROR(ROUND(IF(J18="Short",Z18-AB18,AB18-Z18)/BL18,1),"")) | AU18: =IF(OR(AA18="",AC18=""),"",IF(AA18=AC18,"No","Yes")) | AV18: =IF(OR(B18="",BL18="",BM18="",AB18="",AC18=""),"",IFERROR(ROUND(AI18/(ABS(AB18-AC18)/BL18*BM18),2),"")) | AW18: =IF(B18="","",ROUND(BK18+SUMIFS(AM$5:AM17,BJ$5:BJ17,BJ18),2)) | AX18: =IF(B18="","",COUNTIFS(B$6:B18,B18,BJ$6:BJ18,BJ18)) | AY18: =IF(B18="","",ROUND(SUMIFS(AM$5:AM17,B$5:B17,B18,BJ$5:BJ17,BJ18),2)) | AZ18: =IF(AM18="","",ROUND(AY18+AM18,2)) | BA18: =IF(B18="","",ROUND(SUMIFS(AM$5:AM17,B$5:B17,">="&(B18-WEEKDAY(B18,2)+1),B$5:B17,"<="&B18,BJ$5:BJ17,BJ18),2)) | BB18: =IF(B18="","",IF(AND(AF18<>"",AV18<>"",N(AF18)>N(AV18)*(1+Settings!$C$13)),"Oversized",IF(AX18>Settings!$C$10,"Overtraded",IF(AY18<=-Settings!$C$11*(AW18-AY18),"Daily loss hit",IF(BA18<=-Settings!$C$12*(AW18-BA18),"Weekly loss hit","OK"))))) | BJ18: =IF(B18="","",IF(E18="",Settings!$F$5,E18)) | BK18: =IF(B18="","",IFERROR(INDEX(Settings!$G$5:$G$10,MATCH(BJ18,Settings!$F$5:$F$10,0)),Settings!$G$5)) | BL18: =IF(I18="","",IFERROR(1/(1/INDEX(Lists!$C$6:$C$17,MATCH(I18,Lists!$B$6:$B$17,0))),"")) | BM18: =IF(I18="","",IFERROR(1/(1/INDEX(Lists!$D$6:$D$17,MATCH(I18,Lists!$B$6:$B$17,0))),"")) | BN18: =IF(AN18="","",MAX(BK18,_xlfn.MAXIFS(AN$6:AN18,BJ$6:BJ18,BJ18))) | BO18: =IF(AN18="","",(AN18-BN18)/BN18) | BP18: =IF(OR(B18="",AL18=""),0,IF(OR(Settings!$C$28="All Accounts",BJ18=Settings!$C$28),1,0)) -> 0 | BQ18: =IF(BP18=1,SUM(BP$6:BP18),"") | BR18: =IF(BP18=1,ROUND(Settings!$C$29+SUMIFS(AM$6:AM18,BP$6:BP18,1),2),"") | BS18: =IF(BP18=1,MAX(Settings!$C$29,MAX(BR$6:BR18)),"") | BT18: =IF(BP18=1,(BR18-BS18)/BS18,"") | BU18: =IF(BP18=1,IF(AL18="Win",1+IF(BQ18=1,0,INDEX(BU$5:BU17,MATCH(BQ18-1,BQ$5:BQ17,0))),0),"") | BV18: =IF(BP18=1,IF(AL18="Loss",1+IF(BQ18=1,0,INDEX(BV$5:BV17,MATCH(BQ18-1,BQ$5:BQ17,0))),0),"")
... A505: =IF(B505="","",ROW()-5) | C505: =IF(B505="","",CHOOSE(WEEKDAY(B505,2),"Mon","Tue","Wed","Thu","Fri","Sat","Sun")) | D505: =IF(B505="","",WEEKNUM(B505,2)) | X505: =IF(B505="","",COUNTIF(Q505:W505,"Yes")) | Y505: =IF(B505="","",IF(X505>=Settings!$C$16,"A+",IF(X505>=Settings!$C$17,"A",IF(X505>=Settings!$C$18,"B","C")))) | AI505: =IF(B505="","",ROUND(IF(AG505="",Settings!$C$5,AG505)*AW505,2)) | AJ505: =IF(OR(B505="",AB505="",AC505="",AD505=""),"",IFERROR(ROUND(ABS(AD505-AB505)/ABS(AB505-AC505),2),"")) | AK505: =IF(OR(B505="",AB505="",AC505="",AE505=""),"",IFERROR(ROUND(IF(J505="Short",AB505-AE505,AE505-AB505)/ABS(AB505-AC505),2),"")) | AL505: =IF(AK505="","",IF(ABS(AK505)<=Settings!$C$6,"BE",IF(AK505>0,"Win","Loss"))) | AM505: =IF(OR(AK505="",AI505=""),"",ROUND(AK505*AI505-N(AH505),2)) | AN505: =IF(AM505="","",ROUND(BK505+SUMIFS(AM$6:AM505,BJ$6:BJ505,BJ505),2)) | AO505: =IF(AK505="","",ROUND(SUMIFS(AK$6:AK505,BJ$6:BJ505,BJ505),2)) | AP505: =IF(OR(AK505="",BL505=""),"",IFERROR(ROUND(IF(J505="Short",AB505-AE505,AE505-AB505)/BL505,1),"")) | AQ505: =IF(OR(G505="",H505=""),"",ROUND(MOD(H505-G505,1)*1440,0)) | AR505: =IF(AQ505="","",IF(AQ505<15,"Under 15m",IF(AQ505<60,"15-60m",IF(AQ505<240,"1-4 hours","4+ hours")))) | AS505: =IF(G505="","",HOUR(G505)) | AT505: =IF(OR(Z505="",AB505="",BL505=""),"",IFERROR(ROUND(IF(J505="Short",Z505-AB505,AB505-Z505)/BL505,1),"")) | AU505: =IF(OR(AA505="",AC505=""),"",IF(AA505=AC505,"No","Yes")) | AV505: =IF(OR(B505="",BL505="",BM505="",AB505="",AC505=""),"",IFERROR(ROUND(AI505/(ABS(AB505-AC505)/BL505*BM505),2),"")) | AW505: =IF(B505="","",ROUND(BK505+SUMIFS(AM$5:AM504,BJ$5:BJ504,BJ505),2)) | AX505: =IF(B505="","",COUNTIFS(B$6:B505,B505,BJ$6:BJ505,BJ505)) | AY505: =IF(B505="","",ROUND(SUMIFS(AM$5:AM504,B$5:B504,B505,BJ$5:BJ504,BJ505),2)) | AZ505: =IF(AM505="","",ROUND(AY505+AM505,2)) | BA505: =IF(B505="","",ROUND(SUMIFS(AM$5:AM504,B$5:B504,">="&(B505-WEEKDAY(B505,2)+1),B$5:B504,"<="&B505,BJ$5:BJ504,BJ505),2)) | BB505: =IF(B505="","",IF(AND(AF505<>"",AV505<>"",N(AF505)>N(AV505)*(1+Settings!$C$13)),"Oversized",IF(AX505>Settings!$C$10,"Overtraded",IF(AY505<=-Settings!$C$11*(AW505-AY505),"Daily loss hit",IF(BA505<=-Settings!$C$12*(AW505-BA505),"Weekly loss hit","OK"))))) | BJ505: =IF(B505="","",IF(E505="",Settings!$F$5,E505)) | BK505: =IF(B505="","",IFERROR(INDEX(Settings!$G$5:$G$10,MATCH(BJ505,Settings!$F$5:$F$10,0)),Settings!$G$5)) | BL505: =IF(I505="","",IFERROR(1/(1/INDEX(Lists!$C$6:$C$17,MATCH(I505,Lists!$B$6:$B$17,0))),"")) | BM505: =IF(I505="","",IFERROR(1/(1/INDEX(Lists!$D$6:$D$17,MATCH(I505,Lists!$B$6:$B$17,0))),"")) | BN505: =IF(AN505="","",MAX(BK505,_xlfn.MAXIFS(AN$6:AN505,BJ$6:BJ505,BJ505))) | BO505: =IF(AN505="","",(AN505-BN505)/BN505) | BP505: =IF(OR(B505="",AL505=""),0,IF(OR(Settings!$C$28="All Accounts",BJ505=Settings!$C$28),1,0)) -> 0 | BQ505: =IF(BP505=1,SUM(BP$6:BP505),"") | BR505: =IF(BP505=1,ROUND(Settings!$C$29+SUMIFS(AM$6:AM505,BP$6:BP505,1),2),"") | BS505: =IF(BP505=1,MAX(Settings!$C$29,MAX(BR$6:BR505)),"") | BT505: =IF(BP505=1,(BR505-BS505)/BS505,"") | BU505: =IF(BP505=1,IF(AL505="Win",1+IF(BQ505=1,0,INDEX(BU$5:BU504,MATCH(BQ505-1,BQ$5:BQ504,0))),0),"") | BV505: =IF(BP505=1,IF(AL505="Loss",1+IF(BQ505=1,0,INDEX(BV$5:BV504,MATCH(BQ505-1,BQ$5:BQ504,0))),0),"")

Sheet Daily Journal
B1: DAILY JOURNAL
B2: One row per trading day (weekdays from your Journal Start Date). Trades and P&L fill in automatically; type sleep, mood and notes in the blue cells.
B5: Date | C5: Day | D5: Trades | E5: Net P&L ($) | F5: Sleep (hrs) | G5: Mood | H5: Pre-market plan / bias | I5: End-of-day review
B6: =WORKDAY(Settings!$C$7-1,1) -> 46293 | C6: =CHOOSE(WEEKDAY(B6,2),"Mon","Tue","Wed","Thu","Fri","Sat","Sun") -> Mon | D6: =COUNTIFS(Journal!$B$6:$B$505,B6,Journal!$BP$6:$BP$505,1) -> 1 | E6: =SUMIFS(Journal!$AM$6:$AM$505,Journal!$B$6:$B$505,B6,Journal!$BP$6:$BP$505,1) -> 229.5
B7: =WORKDAY(B6,1) -> 46294 | C7: =CHOOSE(WEEKDAY(B7,2),"Mon","Tue","Wed","Thu","Fri","Sat","Sun") -> Tue | D7: =COUNTIFS(Journal!$B$6:$B$505,B7,Journal!$BP$6:$BP$505,1) -> 0 | E7: =SUMIFS(Journal!$AM$6:$AM$505,Journal!$B$6:$B$505,B7,Journal!$BP$6:$BP$505,1) -> 0
B8: =WORKDAY(B7,1) -> 46295 | C8: =CHOOSE(WEEKDAY(B8,2),"Mon","Tue","Wed","Thu","Fri","Sat","Sun") -> Wed | D8: =COUNTIFS(Journal!$B$6:$B$505,B8,Journal!$BP$6:$BP$505,1) -> 0 | E8: =SUMIFS(Journal!$AM$6:$AM$505,Journal!$B$6:$B$505,B8,Journal!$BP$6:$BP$505,1) -> 0
B9: =WORKDAY(B8,1) -> 46296 | C9: =CHOOSE(WEEKDAY(B9,2),"Mon","Tue","Wed","Thu","Fri","Sat","Sun") -> Thu | D9: =COUNTIFS(Journal!$B$6:$B$505,B9,Journal!$BP$6:$BP$505,1) -> 0 | E9: =SUMIFS(Journal!$AM$6:$AM$505,Journal!$B$6:$B$505,B9,Journal!$BP$6:$BP$505,1) -> 0
B10: =WORKDAY(B9,1) -> 46297 | C10: =CHOOSE(WEEKDAY(B10,2),"Mon","Tue","Wed","Thu","Fri","Sat","Sun") -> Fri | D10: =COUNTIFS(Journal!$B$6:$B$505,B10,Journal!$BP$6:$BP$505,1) -> 0 | E10: =SUMIFS(Journal!$AM$6:$AM$505,Journal!$B$6:$B$505,B10,Journal!$BP$6:$BP$505,1) -> 0
B11: =WORKDAY(B10,1) -> 46300 | C11: =CHOOSE(WEEKDAY(B11,2),"Mon","Tue","Wed","Thu","Fri","Sat","Sun") -> Mon | D11: =COUNTIFS(Journal!$B$6:$B$505,B11,Journal!$BP$6:$BP$505,1) -> 0 | E11: =SUMIFS(Journal!$AM$6:$AM$505,Journal!$B$6:$B$505,B11,Journal!$BP$6:$BP$505,1) -> 0
B12: =WORKDAY(B11,1) -> 46301 | C12: =CHOOSE(WEEKDAY(B12,2),"Mon","Tue","Wed","Thu","Fri","Sat","Sun") -> Tue | D12: =COUNTIFS(Journal!$B$6:$B$505,B12,Journal!$BP$6:$BP$505,1) -> 0 | E12: =SUMIFS(Journal!$AM$6:$AM$505,Journal!$B$6:$B$505,B12,Journal!$BP$6:$BP$505,1) -> 0
B13: =WORKDAY(B12,1) -> 46302 | C13: =CHOOSE(WEEKDAY(B13,2),"Mon","Tue","Wed","Thu","Fri","Sat","Sun") -> Wed | D13: =COUNTIFS(Journal!$B$6:$B$505,B13,Journal!$BP$6:$BP$505,1) -> 0 | E13: =SUMIFS(Journal!$AM$6:$AM$505,Journal!$B$6:$B$505,B13,Journal!$BP$6:$BP$505,1) -> 0
B14: =WORKDAY(B13,1) -> 46303 | C14: =CHOOSE(WEEKDAY(B14,2),"Mon","Tue","Wed","Thu","Fri","Sat","Sun") -> Thu | D14: =COUNTIFS(Journal!$B$6:$B$505,B14,Journal!$BP$6:$BP$505,1) -> 0 | E14: =SUMIFS(Journal!$AM$6:$AM$505,Journal!$B$6:$B$505,B14,Journal!$BP$6:$BP$505,1) -> 0
B15: =WORKDAY(B14,1) -> 46304 | C15: =CHOOSE(WEEKDAY(B15,2),"Mon","Tue","Wed","Thu","Fri","Sat","Sun") -> Fri | D15: =COUNTIFS(Journal!$B$6:$B$505,B15,Journal!$BP$6:$BP$505,1) -> 0 | E15: =SUMIFS(Journal!$AM$6:$AM$505,Journal!$B$6:$B$505,B15,Journal!$BP$6:$BP$505,1) -> 0
B16: =WORKDAY(B15,1) -> 46307 | C16: =CHOOSE(WEEKDAY(B16,2),"Mon","Tue","Wed","Thu","Fri","Sat","Sun") -> Mon | D16: =COUNTIFS(Journal!$B$6:$B$505,B16,Journal!$BP$6:$BP$505,1) -> 0 | E16: =SUMIFS(Journal!$AM$6:$AM$505,Journal!$B$6:$B$505,B16,Journal!$BP$6:$BP$505,1) -> 0
B17: =WORKDAY(B16,1) -> 46308 | C17: =CHOOSE(WEEKDAY(B17,2),"Mon","Tue","Wed","Thu","Fri","Sat","Sun") -> Tue | D17: =COUNTIFS(Journal!$B$6:$B$505,B17,Journal!$BP$6:$BP$505,1) -> 0 | E17: =SUMIFS(Journal!$AM$6:$AM$505,Journal!$B$6:$B$505,B17,Journal!$BP$6:$BP$505,1) -> 0
B18: =WORKDAY(B17,1) -> 46309 | C18: =CHOOSE(WEEKDAY(B18,2),"Mon","Tue","Wed","Thu","Fri","Sat","Sun") -> Wed | D18: =COUNTIFS(Journal!$B$6:$B$505,B18,Journal!$BP$6:$BP$505,1) -> 0 | E18: =SUMIFS(Journal!$AM$6:$AM$505,Journal!$B$6:$B$505,B18,Journal!$BP$6:$BP$505,1) -> 0
... B135: =WORKDAY(B134,1) -> 46472 | C135: =CHOOSE(WEEKDAY(B135,2),"Mon","Tue","Wed","Thu","Fri","Sat","Sun") -> Fri | D135: =COUNTIFS(Journal!$B$6:$B$505,B135,Journal!$BP$6:$BP$505,1) -> 0 | E135: =SUMIFS(Journal!$AM$6:$AM$505,Journal!$B$6:$B$505,B135,Journal!$BP$6:$BP$505,1) -> 0

Sheet Analytics
B1: ANALYTICS
B2: Every table follows the Account View chosen on the Dashboard (except the Account table). Green = profit, red = loss.
B5: Session - performance by trading session | M5: JUMP TO
B6: Session | C6: Trades | D6: Wins | E6: Losses | F6: BE | G6: Win % | H6: Total R | I6: Avg R | J6: Net P&L ($) | K6: Profit Factor | M6: Session
B7: =IF(Lists!$F$6="","",Lists!$F$6) -> Asia | C7: =IF($B7="","",D7+E7+F7) -> 0 | D7: =IF($B7="","",COUNTIFS(Journal!$F$6:$F$505,$B7,Journal!$AL$6:$AL$505,"Win",Journal!$BP$6:$BP$505,1)) -> 0 | E7: =IF($B7="","",COUNTIFS(Journal!$F$6:$F$505,$B7,Journal!$AL$6:$AL$505,"Loss",Journal!$BP$6:$BP$505,1)) -> 0 | F7: =IF($B7="","",COUNTIFS(Journal!$F$6:$F$505,$B7,Journal!$AL$6:$AL$505,"BE",Journal!$BP$6:$BP$505,1)) -> 0 | G7: =IF($B7="","",IFERROR(D7/C7,0)) -> 0 | H7: =IF($B7="","",SUMIFS(Journal!$AK$6:$AK$505,Journal!$F$6:$F$505,$B7,Journal!$BP$6:$BP$505,1)) -> 0 | I7: =IF($B7="","",IFERROR(H7/C7,0)) -> 0 | J7: =IF($B7="","",SUMIFS(Journal!$AM$6:$AM$505,Journal!$F$6:$F$505,$B7,Journal!$BP$6:$BP$505,1)) -> 0 | K7: =IF($B7="","",IFERROR(SUMIFS(Journal!$AM$6:$AM$505,Journal!$F$6:$F$505,$B7,Journal!$BP$6:$BP$505,1,Journal!$AM$6:$AM$505,">0")/ABS(SUMIFS(Journal!$AM$6:$AM$505,Journal!$F$6:$F$505,$B7,Journal!$BP$6:$BP$505,1,Journal!$AM$6:$AM$505,"<0")),"-")) -> - | M7: Pair
B8: =IF(Lists!$F$7="","",Lists!$F$7) -> London | C8: =IF($B8="","",D8+E8+F8) -> 1 | D8: =IF($B8="","",COUNTIFS(Journal!$F$6:$F$505,$B8,Journal!$AL$6:$AL$505,"Win",Journal!$BP$6:$BP$505,1)) -> 1 | E8: =IF($B8="","",COUNTIFS(Journal!$F$6:$F$505,$B8,Journal!$AL$6:$AL$505,"Loss",Journal!$BP$6:$BP$505,1)) -> 0 | F8: =IF($B8="","",COUNTIFS(Journal!$F$6:$F$505,$B8,Journal!$AL$6:$AL$505,"BE",Journal!$BP$6:$BP$505,1)) -> 0 | G8: =IF($B8="","",IFERROR(D8/C8,0)) -> 1 | H8: =IF($B8="","",SUMIFS(Journal!$AK$6:$AK$505,Journal!$F$6:$F$505,$B8,Journal!$BP$6:$BP$505,1)) -> 2.33 | I8: =IF($B8="","",IFERROR(H8/C8,0)) -> 2.33 | J8: =IF($B8="","",SUMIFS(Journal!$AM$6:$AM$505,Journal!$F$6:$F$505,$B8,Journal!$BP$6:$BP$505,1)) -> 229.5 | K8: =IF($B8="","",IFERROR(SUMIFS(Journal!$AM$6:$AM$505,Journal!$F$6:$F$505,$B8,Journal!$BP$6:$BP$505,1,Journal!$AM$6:$AM$505,">0")/ABS(SUMIFS(Journal!$AM$6:$AM$505,Journal!$F$6:$F$505,$B8,Journal!$BP$6:$BP$505,1,Journal!$AM$6:$AM$505,"<0")),"-")) -> - | M8: Setup / Model
B9: =IF(Lists!$F$8="","",Lists!$F$8) -> New York | C9: =IF($B9="","",D9+E9+F9) -> 0 | D9: =IF($B9="","",COUNTIFS(Journal!$F$6:$F$505,$B9,Journal!$AL$6:$AL$505,"Win",Journal!$BP$6:$BP$505,1)) -> 0 | E9: =IF($B9="","",COUNTIFS(Journal!$F$6:$F$505,$B9,Journal!$AL$6:$AL$505,"Loss",Journal!$BP$6:$BP$505,1)) -> 0 | F9: =IF($B9="","",COUNTIFS(Journal!$F$6:$F$505,$B9,Journal!$AL$6:$AL$505,"BE",Journal!$BP$6:$BP$505,1)) -> 0 | G9: =IF($B9="","",IFERROR(D9/C9,0)) -> 0 | H9: =IF($B9="","",SUMIFS(Journal!$AK$6:$AK$505,Journal!$F$6:$F$505,$B9,Journal!$BP$6:$BP$505,1)) -> 0 | I9: =IF($B9="","",IFERROR(H9/C9,0)) -> 0 | J9: =IF($B9="","",SUMIFS(Journal!$AM$6:$AM$505,Journal!$F$6:$F$505,$B9,Journal!$BP$6:$BP$505,1)) -> 0 | K9: =IF($B9="","",IFERROR(SUMIFS(Journal!$AM$6:$AM$505,Journal!$F$6:$F$505,$B9,Journal!$BP$6:$BP$505,1,Journal!$AM$6:$AM$505,">0")/ABS(SUMIFS(Journal!$AM$6:$AM$505,Journal!$F$6:$F$505,$B9,Journal!$BP$6:$BP$505,1,Journal!$AM$6:$AM$505,"<0")),"-")) -> - | M9: Zone Type
B10: =IF(Lists!$F$9="","",Lists!$F$9) -> London-NY Overlap | C10: =IF($B10="","",D10+E10+F10) -> 0 | D10: =IF($B10="","",COUNTIFS(Journal!$F$6:$F$505,$B10,Journal!$AL$6:$AL$505,"Win",Journal!$BP$6:$BP$505,1)) -> 0 | E10: =IF($B10="","",COUNTIFS(Journal!$F$6:$F$505,$B10,Journal!$AL$6:$AL$505,"Loss",Journal!$BP$6:$BP$505,1)) -> 0 | F10: =IF($B10="","",COUNTIFS(Journal!$F$6:$F$505,$B10,Journal!$AL$6:$AL$505,"BE",Journal!$BP$6:$BP$505,1)) -> 0 | G10: =IF($B10="","",IFERROR(D10/C10,0)) -> 0 | H10: =IF($B10="","",SUMIFS(Journal!$AK$6:$AK$505,Journal!$F$6:$F$505,$B10,Journal!$BP$6:$BP$505,1)) -> 0 | I10: =IF($B10="","",IFERROR(H10/C10,0)) -> 0 | J10: =IF($B10="","",SUMIFS(Journal!$AM$6:$AM$505,Journal!$F$6:$F$505,$B10,Journal!$BP$6:$BP$505,1)) -> 0 | K10: =IF($B10="","",IFERROR(SUMIFS(Journal!$AM$6:$AM$505,Journal!$F$6:$F$505,$B10,Journal!$BP$6:$BP$505,1,Journal!$AM$6:$AM$505,">0")/ABS(SUMIFS(Journal!$AM$6:$AM$505,Journal!$F$6:$F$505,$B10,Journal!$BP$6:$BP$505,1,Journal!$AM$6:$AM$505,"<0")),"-")) -> - | M10: Sweep Type
B11: =IF(Lists!$F$10="","",Lists!$F$10) | C11: =IF($B11="","",D11+E11+F11) | D11: =IF($B11="","",COUNTIFS(Journal!$F$6:$F$505,$B11,Journal!$AL$6:$AL$505,"Win",Journal!$BP$6:$BP$505,1)) | E11: =IF($B11="","",COUNTIFS(Journal!$F$6:$F$505,$B11,Journal!$AL$6:$AL$505,"Loss",Journal!$BP$6:$BP$505,1)) | F11: =IF($B11="","",COUNTIFS(Journal!$F$6:$F$505,$B11,Journal!$AL$6:$AL$505,"BE",Journal!$BP$6:$BP$505,1)) | G11: =IF($B11="","",IFERROR(D11/C11,0)) | H11: =IF($B11="","",SUMIFS(Journal!$AK$6:$AK$505,Journal!$F$6:$F$505,$B11,Journal!$BP$6:$BP$505,1)) | I11: =IF($B11="","",IFERROR(H11/C11,0)) | J11: =IF($B11="","",SUMIFS(Journal!$AM$6:$AM$505,Journal!$F$6:$F$505,$B11,Journal!$BP$6:$BP$505,1)) | K11: =IF($B11="","",IFERROR(SUMIFS(Journal!$AM$6:$AM$505,Journal!$F$6:$F$505,$B11,Journal!$BP$6:$BP$505,1,Journal!$AM$6:$AM$505,">0")/ABS(SUMIFS(Journal!$AM$6:$AM$505,Journal!$F$6:$F$505,$B11,Journal!$BP$6:$BP$505,1,Journal!$AM$6:$AM$505,"<0")),"-")) | M11: Sweep vs No Sweep
B12: =IF(Lists!$F$11="","",Lists!$F$11) | C12: =IF($B12="","",D12+E12+F12) | D12: =IF($B12="","",COUNTIFS(Journal!$F$6:$F$505,$B12,Journal!$AL$6:$AL$505,"Win",Journal!$BP$6:$BP$505,1)) | E12: =IF($B12="","",COUNTIFS(Journal!$F$6:$F$505,$B12,Journal!$AL$6:$AL$505,"Loss",Journal!$BP$6:$BP$505,1)) | F12: =IF($B12="","",COUNTIFS(Journal!$F$6:$F$505,$B12,Journal!$AL$6:$AL$505,"BE",Journal!$BP$6:$BP$505,1)) | G12: =IF($B12="","",IFERROR(D12/C12,0)) | H12: =IF($B12="","",SUMIFS(Journal!$AK$6:$AK$505,Journal!$F$6:$F$505,$B12,Journal!$BP$6:$BP$505,1)) | I12: =IF($B12="","",IFERROR(H12/C12,0)) | J12: =IF($B12="","",SUMIFS(Journal!$AM$6:$AM$505,Journal!$F$6:$F$505,$B12,Journal!$BP$6:$BP$505,1)) | K12: =IF($B12="","",IFERROR(SUMIFS(Journal!$AM$6:$AM$505,Journal!$F$6:$F$505,$B12,Journal!$BP$6:$BP$505,1,Journal!$AM$6:$AM$505,">0")/ABS(SUMIFS(Journal!$AM$6:$AM$505,Journal!$F$6:$F$505,$B12,Journal!$BP$6:$BP$505,1,Journal!$AM$6:$AM$505,"<0")),"-")) | M12: HTF Bias
M13: Setup Grade
M14: Direction
B15: Pair - performance by instrument | M15: Weekday
B16: Pair | C16: Trades | D16: Wins | E16: Losses | F16: BE | G16: Win % | H16: Total R | I16: Avg R | J16: Net P&L ($) | K16: Profit Factor | M16: Entry Hour
B17: =IF(Lists!$B$6="","",Lists!$B$6) -> XAUUSD | C17: =IF($B17="","",D17+E17+F17) -> 1 | D17: =IF($B17="","",COUNTIFS(Journal!$I$6:$I$505,$B17,Journal!$AL$6:$AL$505,"Win",Journal!$BP$6:$BP$505,1)) -> 1 | E17: =IF($B17="","",COUNTIFS(Journal!$I$6:$I$505,$B17,Journal!$AL$6:$AL$505,"Loss",Journal!$BP$6:$BP$505,1)) -> 0 | F17: =IF($B17="","",COUNTIFS(Journal!$I$6:$I$505,$B17,Journal!$AL$6:$AL$505,"BE",Journal!$BP$6:$BP$505,1)) -> 0 | G17: =IF($B17="","",IFERROR(D17/C17,0)) -> 1 | H17: =IF($B17="","",SUMIFS(Journal!$AK$6:$AK$505,Journal!$I$6:$I$505,$B17,Journal!$BP$6:$BP$505,1)) -> 2.33 | I17: =IF($B17="","",IFERROR(H17/C17,0)) -> 2.33 | J17: =IF($B17="","",SUMIFS(Journal!$AM$6:$AM$505,Journal!$I$6:$I$505,$B17,Journal!$BP$6:$BP$505,1)) -> 229.5 | K17: =IF($B17="","",IFERROR(SUMIFS(Journal!$AM$6:$AM$505,Journal!$I$6:$I$505,$B17,Journal!$BP$6:$BP$505,1,Journal!$AM$6:$AM$505,">0")/ABS(SUMIFS(Journal!$AM$6:$AM$505,Journal!$I$6:$I$505,$B17,Journal!$BP$6:$BP$505,1,Journal!$AM$6:$AM$505,"<0")),"-")) -> - | M17: Hold Time
B18: =IF(Lists!$B$7="","",Lists!$B$7) -> EURUSD | C18: =IF($B18="","",D18+E18+F18) -> 0 | D18: =IF($B18="","",COUNTIFS(Journal!$I$6:$I$505,$B18,Journal!$AL$6:$AL$505,"Win",Journal!$BP$6:$BP$505,1)) -> 0 | E18: =IF($B18="","",COUNTIFS(Journal!$I$6:$I$505,$B18,Journal!$AL$6:$AL$505,"Loss",Journal!$BP$6:$BP$505,1)) -> 0 | F18: =IF($B18="","",COUNTIFS(Journal!$I$6:$I$505,$B18,Journal!$AL$6:$AL$505,"BE",Journal!$BP$6:$BP$505,1)) -> 0 | G18: =IF($B18="","",IFERROR(D18/C18,0)) -> 0 | H18: =IF($B18="","",SUMIFS(Journal!$AK$6:$AK$505,Journal!$I$6:$I$505,$B18,Journal!$BP$6:$BP$505,1)) -> 0 | I18: =IF($B18="","",IFERROR(H18/C18,0)) -> 0 | J18: =IF($B18="","",SUMIFS(Journal!$AM$6:$AM$505,Journal!$I$6:$I$505,$B18,Journal!$BP$6:$BP$505,1)) -> 0 | K18: =IF($B18="","",IFERROR(SUMIFS(Journal!$AM$6:$AM$505,Journal!$I$6:$I$505,$B18,Journal!$BP$6:$BP$505,1,Journal!$AM$6:$AM$505,">0")/ABS(SUMIFS(Journal!$AM$6:$AM$505,Journal!$I$6:$I$505,$B18,Journal!$BP$6:$BP$505,1,Journal!$AM$6:$AM$505,"<0")),"-")) -> - | M18: Emotion
B19: =IF(Lists!$B$8="","",Lists!$B$8) -> GBPUSD | C19: =IF($B19="","",D19+E19+F19) -> 0 | D19: =IF($B19="","",COUNTIFS(Journal!$I$6:$I$505,$B19,Journal!$AL$6:$AL$505,"Win",Journal!$BP$6:$BP$505,1)) -> 0 | E19: =IF($B19="","",COUNTIFS(Journal!$I$6:$I$505,$B19,Journal!$AL$6:$AL$505,"Loss",Journal!$BP$6:$BP$505,1)) -> 0 | F19: =IF($B19="","",COUNTIFS(Journal!$I$6:$I$505,$B19,Journal!$AL$6:$AL$505,"BE",Journal!$BP$6:$BP$505,1)) -> 0 | G19: =IF($B19="","",IFERROR(D19/C19,0)) -> 0 | H19: =IF($B19="","",SUMIFS(Journal!$AK$6:$AK$505,Journal!$I$6:$I$505,$B19,Journal!$BP$6:$BP$505,1)) -> 0 | I19: =IF($B19="","",IFERROR(H19/C19,0)) -> 0 | J19: =IF($B19="","",SUMIFS(Journal!$AM$6:$AM$505,Journal!$I$6:$I$505,$B19,Journal!$BP$6:$BP$505,1)) -> 0 | K19: =IF($B19="","",IFERROR(SUMIFS(Journal!$AM$6:$AM$505,Journal!$I$6:$I$505,$B19,Journal!$BP$6:$BP$505,1,Journal!$AM$6:$AM$505,">0")/ABS(SUMIFS(Journal!$AM$6:$AM$505,Journal!$I$6:$I$505,$B19,Journal!$BP$6:$BP$505,1,Journal!$AM$6:$AM$505,"<0")),"-")) -> - | M19: Mistake Tag
B20: =IF(Lists!$B$9="","",Lists!$B$9) -> USDJPY | C20: =IF($B20="","",D20+E20+F20) -> 0 | D20: =IF($B20="","",COUNTIFS(Journal!$I$6:$I$505,$B20,Journal!$AL$6:$AL$505,"Win",Journal!$BP$6:$BP$505,1)) -> 0 | E20: =IF($B20="","",COUNTIFS(Journal!$I$6:$I$505,$B20,Journal!$AL$6:$AL$505,"Loss",Journal!$BP$6:$BP$505,1)) -> 0 | F20: =IF($B20="","",COUNTIFS(Journal!$I$6:$I$505,$B20,Journal!$AL$6:$AL$505,"BE",Journal!$BP$6:$BP$505,1)) -> 0 | G20: =IF($B20="","",IFERROR(D20/C20,0)) -> 0 | H20: =IF($B20="","",SUMIFS(Journal!$AK$6:$AK$505,Journal!$I$6:$I$505,$B20,Journal!$BP$6:$BP$505,1)) -> 0 | I20: =IF($B20="","",IFERROR(H20/C20,0)) -> 0 | J20: =IF($B20="","",SUMIFS(Journal!$AM$6:$AM$505,Journal!$I$6:$I$505,$B20,Journal!$BP$6:$BP$505,1)) -> 0 | K20: =IF($B20="","",IFERROR(SUMIFS(Journal!$AM$6:$AM$505,Journal!$I$6:$I$505,$B20,Journal!$BP$6:$BP$505,1,Journal!$AM$6:$AM$505,">0")/ABS(SUMIFS(Journal!$AM$6:$AM$505,Journal!$I$6:$I$505,$B20,Journal!$BP$6:$BP$505,1,Journal!$AM$6:$AM$505,"<0")),"-")) -> - | M20: Rule Check
B21: =IF(Lists!$B$10="","",Lists!$B$10) -> GBPJPY | C21: =IF($B21="","",D21+E21+F21) -> 0 | D21: =IF($B21="","",COUNTIFS(Journal!$I$6:$I$505,$B21,Journal!$AL$6:$AL$505,"Win",Journal!$BP$6:$BP$505,1)) -> 0 | E21: =IF($B21="","",COUNTIFS(Journal!$I$6:$I$505,$B21,Journal!$AL$6:$AL$505,"Loss",Journal!$BP$6:$BP$505,1)) -> 0 | F21: =IF($B21="","",COUNTIFS(Journal!$I$6:$I$505,$B21,Journal!$AL$6:$AL$505,"BE",Journal!$BP$6:$BP$505,1)) -> 0 | G21: =IF($B21="","",IFERROR(D21/C21,0)) -> 0 | H21: =IF($B21="","",SUMIFS(Journal!$AK$6:$AK$505,Journal!$I$6:$I$505,$B21,Journal!$BP$6:$BP$505,1)) -> 0 | I21: =IF($B21="","",IFERROR(H21/C21,0)) -> 0 | J21: =IF($B21="","",SUMIFS(Journal!$AM$6:$AM$505,Journal!$I$6:$I$505,$B21,Journal!$BP$6:$BP$505,1)) -> 0 | K21: =IF($B21="","",IFERROR(SUMIFS(Journal!$AM$6:$AM$505,Journal!$I$6:$I$505,$B21,Journal!$BP$6:$BP$505,1,Journal!$AM$6:$AM$505,">0")/ABS(SUMIFS(Journal!$AM$6:$AM$505,Journal!$I$6:$I$505,$B21,Journal!$BP$6:$BP$505,1,Journal!$AM$6:$AM$505,"<0")),"-")) -> - | M21: Account
B22: =IF(Lists!$B$11="","",Lists!$B$11) -> AUDUSD | C22: =IF($B22="","",D22+E22+F22) -> 0 | D22: =IF($B22="","",COUNTIFS(Journal!$I$6:$I$505,$B22,Journal!$AL$6:$AL$505,"Win",Journal!$BP$6:$BP$505,1)) -> 0 | E22: =IF($B22="","",COUNTIFS(Journal!$I$6:$I$505,$B22,Journal!$AL$6:$AL$505,"Loss",Journal!$BP$6:$BP$505,1)) -> 0 | F22: =IF($B22="","",COUNTIFS(Journal!$I$6:$I$505,$B22,Journal!$AL$6:$AL$505,"BE",Journal!$BP$6:$BP$505,1)) -> 0 | G22: =IF($B22="","",IFERROR(D22/C22,0)) -> 0 | H22: =IF($B22="","",SUMIFS(Journal!$AK$6:$AK$505,Journal!$I$6:$I$505,$B22,Journal!$BP$6:$BP$505,1)) -> 0 | I22: =IF($B22="","",IFERROR(H22/C22,0)) -> 0 | J22: =IF($B22="","",SUMIFS(Journal!$AM$6:$AM$505,Journal!$I$6:$I$505,$B22,Journal!$BP$6:$BP$505,1)) -> 0 | K22: =IF($B22="","",IFERROR(SUMIFS(Journal!$AM$6:$AM$505,Journal!$I$6:$I$505,$B22,Journal!$BP$6:$BP$505,1,Journal!$AM$6:$AM$505,">0")/ABS(SUMIFS(Journal!$AM$6:$AM$505,Journal!$I$6:$I$505,$B22,Journal!$BP$6:$BP$505,1,Journal!$AM$6:$AM$505,"<0")),"-")) -> - | M22: Monthly
B23: =IF(Lists!$B$12="","",Lists!$B$12) -> USDCAD | C23: =IF($B23="","",D23+E23+F23) -> 0 | D23: =IF($B23="","",COUNTIFS(Journal!$I$6:$I$505,$B23,Journal!$AL$6:$AL$505,"Win",Journal!$BP$6:$BP$505,1)) -> 0 | E23: =IF($B23="","",COUNTIFS(Journal!$I$6:$I$505,$B23,Journal!$AL$6:$AL$505,"Loss",Journal!$BP$6:$BP$505,1)) -> 0 | F23: =IF($B23="","",COUNTIFS(Journal!$I$6:$I$505,$B23,Journal!$AL$6:$AL$505,"BE",Journal!$BP$6:$BP$505,1)) -> 0 | G23: =IF($B23="","",IFERROR(D23/C23,0)) -> 0 | H23: =IF($B23="","",SUMIFS(Journal!$AK$6:$AK$505,Journal!$I$6:$I$505,$B23,Journal!$BP$6:$BP$505,1)) -> 0 | I23: =IF($B23="","",IFERROR(H23/C23,0)) -> 0 | J23: =IF($B23="","",SUMIFS(Journal!$AM$6:$AM$505,Journal!$I$6:$I$505,$B23,Journal!$BP$6:$BP$505,1)) -> 0 | K23: =IF($B23="","",IFERROR(SUMIFS(Journal!$AM$6:$AM$505,Journal!$I$6:$I$505,$B23,Journal!$BP$6:$BP$505,1,Journal!$AM$6:$AM$505,">0")/ABS(SUMIFS(Journal!$AM$6:$AM$505,Journal!$I$6:$I$505,$B23,Journal!$BP$6:$BP$505,1,Journal!$AM$6:$AM$505,"<0")),"-")) -> - | M23: Mood and Sleep
B24: =IF(Lists!$B$13="","",Lists!$B$13) -> NZDUSD | C24: =IF($B24="","",D24+E24+F24) -> 0 | D24: =IF($B24="","",COUNTIFS(Journal!$I$6:$I$505,$B24,Journal!$AL$6:$AL$505,"Win",Journal!$BP$6:$BP$505,1)) -> 0 | E24: =IF($B24="","",COUNTIFS(Journal!$I$6:$I$505,$B24,Journal!$AL$6:$AL$505,"Loss",Journal!$BP$6:$BP$505,1)) -> 0 | F24: =IF($B24="","",COUNTIFS(Journal!$I$6:$I$505,$B24,Journal!$AL$6:$AL$505,"BE",Journal!$BP$6:$BP$505,1)) -> 0 | G24: =IF($B24="","",IFERROR(D24/C24,0)) -> 0 | H24: =IF($B24="","",SUMIFS(Journal!$AK$6:$AK$505,Journal!$I$6:$I$505,$B24,Journal!$BP$6:$BP$505,1)) -> 0 | I24: =IF($B24="","",IFERROR(H24/C24,0)) -> 0 | J24: =IF($B24="","",SUMIFS(Journal!$AM$6:$AM$505,Journal!$I$6:$I$505,$B24,Journal!$BP$6:$BP$505,1)) -> 0 | K24: =IF($B24="","",IFERROR(SUMIFS(Journal!$AM$6:$AM$505,Journal!$I$6:$I$505,$B24,Journal!$BP$6:$BP$505,1,Journal!$AM$6:$AM$505,">0")/ABS(SUMIFS(Journal!$AM$6:$AM$505,Journal!$I$6:$I$505,$B24,Journal!$BP$6:$BP$505,1,Journal!$AM$6:$AM$505,"<0")),"-")) -> -
B25: =IF(Lists!$B$14="","",Lists!$B$14) -> USDCHF | C25: =IF($B25="","",D25+E25+F25) -> 0 | D25: =IF($B25="","",COUNTIFS(Journal!$I$6:$I$505,$B25,Journal!$AL$6:$AL$505,"Win",Journal!$BP$6:$BP$505,1)) -> 0 | E25: =IF($B25="","",COUNTIFS(Journal!$I$6:$I$505,$B25,Journal!$AL$6:$AL$505,"Loss",Journal!$BP$6:$BP$505,1)) -> 0 | F25: =IF($B25="","",COUNTIFS(Journal!$I$6:$I$505,$B25,Journal!$AL$6:$AL$505,"BE",Journal!$BP$6:$BP$505,1)) -> 0 | G25: =IF($B25="","",IFERROR(D25/C25,0)) -> 0 | H25: =IF($B25="","",SUMIFS(Journal!$AK$6:$AK$505,Journal!$I$6:$I$505,$B25,Journal!$BP$6:$BP$505,1)) -> 0 | I25: =IF($B25="","",IFERROR(H25/C25,0)) -> 0 | J25: =IF($B25="","",SUMIFS(Journal!$AM$6:$AM$505,Journal!$I$6:$I$505,$B25,Journal!$BP$6:$BP$505,1)) -> 0 | K25: =IF($B25="","",IFERROR(SUMIFS(Journal!$AM$6:$AM$505,Journal!$I$6:$I$505,$B25,Journal!$BP$6:$BP$505,1,Journal!$AM$6:$AM$505,">0")/ABS(SUMIFS(Journal!$AM$6:$AM$505,Journal!$I$6:$I$505,$B25,Journal!$BP$6:$BP$505,1,Journal!$AM$6:$AM$505,"<0")),"-")) -> -
B26: =IF(Lists!$B$15="","",Lists!$B$15) -> EURJPY | C26: =IF($B26="","",D26+E26+F26) -> 0 | D26: =IF($B26="","",COUNTIFS(Journal!$I$6:$I$505,$B26,Journal!$AL$6:$AL$505,"Win",Journal!$BP$6:$BP$505,1)) -> 0 | E26: =IF($B26="","",COUNTIFS(Journal!$I$6:$I$505,$B26,Journal!$AL$6:$AL$505,"Loss",Journal!$BP$6:$BP$505,1)) -> 0 | F26: =IF($B26="","",COUNTIFS(Journal!$I$6:$I$505,$B26,Journal!$AL$6:$AL$505,"BE",Journal!$BP$6:$BP$505,1)) -> 0 | G26: =IF($B26="","",IFERROR(D26/C26,0)) -> 0 | H26: =IF($B26="","",SUMIFS(Journal!$AK$6:$AK$505,Journal!$I$6:$I$505,$B26,Journal!$BP$6:$BP$505,1)) -> 0 | I26: =IF($B26="","",IFERROR(H26/C26,0)) -> 0 | J26: =IF($B26="","",SUMIFS(Journal!$AM$6:$AM$505,Journal!$I$6:$I$505,$B26,Journal!$BP$6:$BP$505,1)) -> 0 | K26: =IF($B26="","",IFERROR(SUMIFS(Journal!$AM$6:$AM$505,Journal!$I$6:$I$505,$B26,Journal!$BP$6:$BP$505,1,Journal!$AM$6:$AM$505,">0")/ABS(SUMIFS(Journal!$AM$6:$AM$505,Journal!$I$6:$I$505,$B26,Journal!$BP$6:$BP$505,1,Journal!$AM$6:$AM$505,"<0")),"-")) -> -
B27: =IF(Lists!$B$16="","",Lists!$B$16) | C27: =IF($B27="","",D27+E27+F27) | D27: =IF($B27="","",COUNTIFS(Journal!$I$6:$I$505,$B27,Journal!$AL$6:$AL$505,"Win",Journal!$BP$6:$BP$505,1)) | E27: =IF($B27="","",COUNTIFS(Journal!$I$6:$I$505,$B27,Journal!$AL$6:$AL$505,"Loss",Journal!$BP$6:$BP$505,1)) | F27: =IF($B27="","",COUNTIFS(Journal!$I$6:$I$505,$B27,Journal!$AL$6:$AL$505,"BE",Journal!$BP$6:$BP$505,1)) | G27: =IF($B27="","",IFERROR(D27/C27,0)) | H27: =IF($B27="","",SUMIFS(Journal!$AK$6:$AK$505,Journal!$I$6:$I$505,$B27,Journal!$BP$6:$BP$505,1)) | I27: =IF($B27="","",IFERROR(H27/C27,0)) | J27: =IF($B27="","",SUMIFS(Journal!$AM$6:$AM$505,Journal!$I$6:$I$505,$B27,Journal!$BP$6:$BP$505,1)) | K27: =IF($B27="","",IFERROR(SUMIFS(Journal!$AM$6:$AM$505,Journal!$I$6:$I$505,$B27,Journal!$BP$6:$BP$505,1,Journal!$AM$6:$AM$505,">0")/ABS(SUMIFS(Journal!$AM$6:$AM$505,Journal!$I$6:$I$505,$B27,Journal!$BP$6:$BP$505,1,Journal!$AM$6:$AM$505,"<0")),"-"))
B28: =IF(Lists!$B$17="","",Lists!$B$17) | C28: =IF($B28="","",D28+E28+F28) | D28: =IF($B28="","",COUNTIFS(Journal!$I$6:$I$505,$B28,Journal!$AL$6:$AL$505,"Win",Journal!$BP$6:$BP$505,1)) | E28: =IF($B28="","",COUNTIFS(Journal!$I$6:$I$505,$B28,Journal!$AL$6:$AL$505,"Loss",Journal!$BP$6:$BP$505,1)) | F28: =IF($B28="","",COUNTIFS(Journal!$I$6:$I$505,$B28,Journal!$AL$6:$AL$505,"BE",Journal!$BP$6:$BP$505,1)) | G28: =IF($B28="","",IFERROR(D28/C28,0)) | H28: =IF($B28="","",SUMIFS(Journal!$AK$6:$AK$505,Journal!$I$6:$I$505,$B28,Journal!$BP$6:$BP$505,1)) | I28: =IF($B28="","",IFERROR(H28/C28,0)) | J28: =IF($B28="","",SUMIFS(Journal!$AM$6:$AM$505,Journal!$I$6:$I$505,$B28,Journal!$BP$6:$BP$505,1)) | K28: =IF($B28="","",IFERROR(SUMIFS(Journal!$AM$6:$AM$505,Journal!$I$6:$I$505,$B28,Journal!$BP$6:$BP$505,1,Journal!$AM$6:$AM$505,">0")/ABS(SUMIFS(Journal!$AM$6:$AM$505,Journal!$I$6:$I$505,$B28,Journal!$BP$6:$BP$505,1,Journal!$AM$6:$AM$505,"<0")),"-"))
B31: Setup / Model - performance by strategy
B32: Setup / Model | C32: Trades | D32: Wins | E32: Losses | F32: BE | G32: Win % | H32: Total R | I32: Avg R | J32: Net P&L ($) | K32: Profit Factor
B33: =IF(Lists!$G$6="","",Lists!$G$6) -> Liquidity Sweep Reversal | C33: =IF($B33="","",D33+E33+F33) -> 1 | D33: =IF($B33="","",COUNTIFS(Journal!$L$6:$L$505,$B33,Journal!$AL$6:$AL$505,"Win",Journal!$BP$6:$BP$505,1)) -> 1 | E33: =IF($B33="","",COUNTIFS(Journal!$L$6:$L$505,$B33,Journal!$AL$6:$AL$505,"Loss",Journal!$BP$6:$BP$505,1)) -> 0 | F33: =IF($B33="","",COUNTIFS(Journal!$L$6:$L$505,$B33,Journal!$AL$6:$AL$505,"BE",Journal!$BP$6:$BP$505,1)) -> 0 | G33: =IF($B33="","",IFERROR(D33/C33,0)) -> 1 | H33: =IF($B33="","",SUMIFS(Journal!$AK$6:$AK$505,Journal!$L$6:$L$505,$B33,Journal!$BP$6:$BP$505,1)) -> 2.33 | I33: =IF($B33="","",IFERROR(H33/C33,0)) -> 2.33 | J33: =IF($B33="","",SUMIFS(Journal!$AM$6:$AM$505,Journal!$L$6:$L$505,$B33,Journal!$BP$6:$BP$505,1)) -> 229.5 | K33: =IF($B33="","",IFERROR(SUMIFS(Journal!$AM$6:$AM$505,Journal!$L$6:$L$505,$B33,Journal!$BP$6:$BP$505,1,Journal!$AM$6:$AM$505,">0")/ABS(SUMIFS(Journal!$AM$6:$AM$505,Journal!$L$6:$L$505,$B33,Journal!$BP$6:$BP$505,1,Journal!$AM$6:$AM$505,"<0")),"-")) -> -
B34: =IF(Lists!$G$7="","",Lists!$G$7) -> Order Block Retest | C34: =IF($B34="","",D34+E34+F34) -> 0 | D34: =IF($B34="","",COUNTIFS(Journal!$L$6:$L$505,$B34,Journal!$AL$6:$AL$505,"Win",Journal!$BP$6:$BP$505,1)) -> 0 | E34: =IF($B34="","",COUNTIFS(Journal!$L$6:$L$505,$B34,Journal!$AL$6:$AL$505,"Loss",Journal!$BP$6:$BP$505,1)) -> 0 | F34: =IF($B34="","",COUNTIFS(Journal!$L$6:$L$505,$B34,Journal!$AL$6:$AL$505,"BE",Journal!$BP$6:$BP$505,1)) -> 0 | G34: =IF($B34="","",IFERROR(D34/C34,0)) -> 0 | H34: =IF($B34="","",SUMIFS(Journal!$AK$6:$AK$505,Journal!$L$6:$L$505,$B34,Journal!$BP$6:$BP$505,1)) -> 0 | I34: =IF($B34="","",IFERROR(H34/C34,0)) -> 0 | J34: =IF($B34="","",SUMIFS(Journal!$AM$6:$AM$505,Journal!$L$6:$L$505,$B34,Journal!$BP$6:$BP$505,1)) -> 0 | K34: =IF($B34="","",IFERROR(SUMIFS(Journal!$AM$6:$AM$505,Journal!$L$6:$L$505,$B34,Journal!$BP$6:$BP$505,1,Journal!$AM$6:$AM$505,">0")/ABS(SUMIFS(Journal!$AM$6:$AM$505,Journal!$L$6:$L$505,$B34,Journal!$BP$6:$BP$505,1,Journal!$AM$6:$AM$505,"<0")),"-")) -> -
B35: =IF(Lists!$G$8="","",Lists!$G$8) -> Break & Retest | C35: =IF($B35="","",D35+E35+F35) -> 0 | D35: =IF($B35="","",COUNTIFS(Journal!$L$6:$L$505,$B35,Journal!$AL$6:$AL$505,"Win",Journal!$BP$6:$BP$505,1)) -> 0 | E35: =IF($B35="","",COUNTIFS(Journal!$L$6:$L$505,$B35,Journal!$AL$6:$AL$505,"Loss",Journal!$BP$6:$BP$505,1)) -> 0 | F35: =IF($B35="","",COUNTIFS(Journal!$L$6:$L$505,$B35,Journal!$AL$6:$AL$505,"BE",Journal!$BP$6:$BP$505,1)) -> 0 | G35: =IF($B35="","",IFERROR(D35/C35,0)) -> 0 | H35: =IF($B35="","",SUMIFS(Journal!$AK$6:$AK$505,Journal!$L$6:$L$505,$B35,Journal!$BP$6:$BP$505,1)) -> 0 | I35: =IF($B35="","",IFERROR(H35/C35,0)) -> 0 | J35: =IF($B35="","",SUMIFS(Journal!$AM$6:$AM$505,Journal!$L$6:$L$505,$B35,Journal!$BP$6:$BP$505,1)) -> 0 | K35: =IF($B35="","",IFERROR(SUMIFS(Journal!$AM$6:$AM$505,Journal!$L$6:$L$505,$B35,Journal!$BP$6:$BP$505,1,Journal!$AM$6:$AM$505,">0")/ABS(SUMIFS(Journal!$AM$6:$AM$505,Journal!$L$6:$L$505,$B35,Journal!$BP$6:$BP$505,1,Journal!$AM$6:$AM$505,"<0")),"-")) -> -
B36: =IF(Lists!$G$9="","",Lists!$G$9) -> FVG Entry | C36: =IF($B36="","",D36+E36+F36) -> 0 | D36: =IF($B36="","",COUNTIFS(Journal!$L$6:$L$505,$B36,Journal!$AL$6:$AL$505,"Win",Journal!$BP$6:$BP$505,1)) -> 0 | E36: =IF($B36="","",COUNTIFS(Journal!$L$6:$L$505,$B36,Journal!$AL$6:$AL$505,"Loss",Journal!$BP$6:$BP$505,1)) -> 0 | F36: =IF($B36="","",COUNTIFS(Journal!$L$6:$L$505,$B36,Journal!$AL$6:$AL$505,"BE",Journal!$BP$6:$BP$505,1)) -> 0 | G36: =IF($B36="","",IFERROR(D36/C36,0)) -> 0 | H36: =IF($B36="","",SUMIFS(Journal!$AK$6:$AK$505,Journal!$L$6:$L$505,$B36,Journal!$BP$6:$BP$505,1)) -> 0 | I36: =IF($B36="","",IFERROR(H36/C36,0)) -> 0 | J36: =IF($B36="","",SUMIFS(Journal!$AM$6:$AM$505,Journal!$L$6:$L$505,$B36,Journal!$BP$6:$BP$505,1)) -> 0 | K36: =IF($B36="","",IFERROR(SUMIFS(Journal!$AM$6:$AM$505,Journal!$L$6:$L$505,$B36,Journal!$BP$6:$BP$505,1,Journal!$AM$6:$AM$505,">0")/ABS(SUMIFS(Journal!$AM$6:$AM$505,Journal!$L$6:$L$505,$B36,Journal!$BP$6:$BP$505,1,Journal!$AM$6:$AM$505,"<0")),"-")) -> -
B37: =IF(Lists!$G$10="","",Lists!$G$10) -> Breaker Block | C37: =IF($B37="","",D37+E37+F37) -> 0 | D37: =IF($B37="","",COUNTIFS(Journal!$L$6:$L$505,$B37,Journal!$AL$6:$AL$505,"Win",Journal!$BP$6:$BP$505,1)) -> 0 | E37: =IF($B37="","",COUNTIFS(Journal!$L$6:$L$505,$B37,Journal!$AL$6:$AL$505,"Loss",Journal!$BP$6:$BP$505,1)) -> 0 | F37: =IF($B37="","",COUNTIFS(Journal!$L$6:$L$505,$B37,Journal!$AL$6:$AL$505,"BE",Journal!$BP$6:$BP$505,1)) -> 0 | G37: =IF($B37="","",IFERROR(D37/C37,0)) -> 0 | H37: =IF($B37="","",SUMIFS(Journal!$AK$6:$AK$505,Journal!$L$6:$L$505,$B37,Journal!$BP$6:$BP$505,1)) -> 0 | I37: =IF($B37="","",IFERROR(H37/C37,0)) -> 0 | J37: =IF($B37="","",SUMIFS(Journal!$AM$6:$AM$505,Journal!$L$6:$L$505,$B37,Journal!$BP$6:$BP$505,1)) -> 0 | K37: =IF($B37="","",IFERROR(SUMIFS(Journal!$AM$6:$AM$505,Journal!$L$6:$L$505,$B37,Journal!$BP$6:$BP$505,1,Journal!$AM$6:$AM$505,">0")/ABS(SUMIFS(Journal!$AM$6:$AM$505,Journal!$L$6:$L$505,$B37,Journal!$BP$6:$BP$505,1,Journal!$AM$6:$AM$505,"<0")),"-")) -> -
B38: =IF(Lists!$G$11="","",Lists!$G$11) -> Supply/Demand Zone Reaction | C38: =IF($B38="","",D38+E38+F38) -> 0 | D38: =IF($B38="","",COUNTIFS(Journal!$L$6:$L$505,$B38,Journal!$AL$6:$AL$505,"Win",Journal!$BP$6:$BP$505,1)) -> 0 | E38: =IF($B38="","",COUNTIFS(Journal!$L$6:$L$505,$B38,Journal!$AL$6:$AL$505,"Loss",Journal!$BP$6:$BP$505,1)) -> 0 | F38: =IF($B38="","",COUNTIFS(Journal!$L$6:$L$505,$B38,Journal!$AL$6:$AL$505,"BE",Journal!$BP$6:$BP$505,1)) -> 0 | G38: =IF($B38="","",IFERROR(D38/C38,0)) -> 0 | H38: =IF($B38="","",SUMIFS(Journal!$AK$6:$AK$505,Journal!$L$6:$L$505,$B38,Journal!$BP$6:$BP$505,1)) -> 0 | I38: =IF($B38="","",IFERROR(H38/C38,0)) -> 0 | J38: =IF($B38="","",SUMIFS(Journal!$AM$6:$AM$505,Journal!$L$6:$L$505,$B38,Journal!$BP$6:$BP$505,1)) -> 0 | K38: =IF($B38="","",IFERROR(SUMIFS(Journal!$AM$6:$AM$505,Journal!$L$6:$L$505,$B38,Journal!$BP$6:$BP$505,1,Journal!$AM$6:$AM$505,">0")/ABS(SUMIFS(Journal!$AM$6:$AM$505,Journal!$L$6:$L$505,$B38,Journal!$BP$6:$BP$505,1,Journal!$AM$6:$AM$505,"<0")),"-")) -> -
B39: =IF(Lists!$G$12="","",Lists!$G$12) -> Trend Pullback | C39: =IF($B39="","",D39+E39+F39) -> 0 | D39: =IF($B39="","",COUNTIFS(Journal!$L$6:$L$505,$B39,Journal!$AL$6:$AL$505,"Win",Journal!$BP$6:$BP$505,1)) -> 0 | E39: =IF($B39="","",COUNTIFS(Journal!$L$6:$L$505,$B39,Journal!$AL$6:$AL$505,"Loss",Journal!$BP$6:$BP$505,1)) -> 0 | F39: =IF($B39="","",COUNTIFS(Journal!$L$6:$L$505,$B39,Journal!$AL$6:$AL$505,"BE",Journal!$BP$6:$BP$505,1)) -> 0 | G39: =IF($B39="","",IFERROR(D39/C39,0)) -> 0 | H39: =IF($B39="","",SUMIFS(Journal!$AK$6:$AK$505,Journal!$L$6:$L$505,$B39,Journal!$BP$6:$BP$505,1)) -> 0 | I39: =IF($B39="","",IFERROR(H39/C39,0)) -> 0 | J39: =IF($B39="","",SUMIFS(Journal!$AM$6:$AM$505,Journal!$L$6:$L$505,$B39,Journal!$BP$6:$BP$505,1)) -> 0 | K39: =IF($B39="","",IFERROR(SUMIFS(Journal!$AM$6:$AM$505,Journal!$L$6:$L$505,$B39,Journal!$BP$6:$BP$505,1,Journal!$AM$6:$AM$505,">0")/ABS(SUMIFS(Journal!$AM$6:$AM$505,Journal!$L$6:$L$505,$B39,Journal!$BP$6:$BP$505,1,Journal!$AM$6:$AM$505,"<0")),"-")) -> -
B40: =IF(Lists!$G$13="","",Lists!$G$13) -> Range Edge Fade | C40: =IF($B40="","",D40+E40+F40) -> 0 | D40: =IF($B40="","",COUNTIFS(Journal!$L$6:$L$505,$B40,Journal!$AL$6:$AL$505,"Win",Journal!$BP$6:$BP$505,1)) -> 0 | E40: =IF($B40="","",COUNTIFS(Journal!$L$6:$L$505,$B40,Journal!$AL$6:$AL$505,"Loss",Journal!$BP$6:$BP$505,1)) -> 0 | F40: =IF($B40="","",COUNTIFS(Journal!$L$6:$L$505,$B40,Journal!$AL$6:$AL$505,"BE",Journal!$BP$6:$BP$505,1)) -> 0 | G40: =IF($B40="","",IFERROR(D40/C40,0)) -> 0 | H40: =IF($B40="","",SUMIFS(Journal!$AK$6:$AK$505,Journal!$L$6:$L$505,$B40,Journal!$BP$6:$BP$505,1)) -> 0 | I40: =IF($B40="","",IFERROR(H40/C40,0)) -> 0 | J40: =IF($B40="","",SUMIFS(Journal!$AM$6:$AM$505,Journal!$L$6:$L$505,$B40,Journal!$BP$6:$BP$505,1)) -> 0 | K40: =IF($B40="","",IFERROR(SUMIFS(Journal!$AM$6:$AM$505,Journal!$L$6:$L$505,$B40,Journal!$BP$6:$BP$505,1,Journal!$AM$6:$AM$505,">0")/ABS(SUMIFS(Journal!$AM$6:$AM$505,Journal!$L$6:$L$505,$B40,Journal!$BP$6:$BP$505,1,Journal!$AM$6:$AM$505,"<0")),"-")) -> -
B41: =IF(Lists!$G$14="","",Lists!$G$14) -> Asia Range Sweep | C41: =IF($B41="","",D41+E41+F41) -> 0 | D41: =IF($B41="","",COUNTIFS(Journal!$L$6:$L$505,$B41,Journal!$AL$6:$AL$505,"Win",Journal!$BP$6:$BP$505,1)) -> 0 | E41: =IF($B41="","",COUNTIFS(Journal!$L$6:$L$505,$B41,Journal!$AL$6:$AL$505,"Loss",Journal!$BP$6:$BP$505,1)) -> 0 | F41: =IF($B41="","",COUNTIFS(Journal!$L$6:$L$505,$B41,Journal!$AL$6:$AL$505,"BE",Journal!$BP$6:$BP$505,1)) -> 0 | G41: =IF($B41="","",IFERROR(D41/C41,0)) -> 0 | H41: =IF($B41="","",SUMIFS(Journal!$AK$6:$AK$505,Journal!$L$6:$L$505,$B41,Journal!$BP$6:$BP$505,1)) -> 0 | I41: =IF($B41="","",IFERROR(H41/C41,0)) -> 0 | J41: =IF($B41="","",SUMIFS(Journal!$AM$6:$AM$505,Journal!$L$6:$L$505,$B41,Journal!$BP$6:$BP$505,1)) -> 0 | K41: =IF($B41="","",IFERROR(SUMIFS(Journal!$AM$6:$AM$505,Journal!$L$6:$L$505,$B41,Journal!$BP$6:$BP$505,1,Journal!$AM$6:$AM$505,">0")/ABS(SUMIFS(Journal!$AM$6:$AM$505,Journal!$L$6:$L$505,$B41,Journal!$BP$6:$BP$505,1,Journal!$AM$6:$AM$505,"<0")),"-")) -> -
B42: =IF(Lists!$G$15="","",Lists!$G$15) -> Other | C42: =IF($B42="","",D42+E42+F42) -> 0 | D42: =IF($B42="","",COUNTIFS(Journal!$L$6:$L$505,$B42,Journal!$AL$6:$AL$505,"Win",Journal!$BP$6:$BP$505,1)) -> 0 | E42: =IF($B42="","",COUNTIFS(Journal!$L$6:$L$505,$B42,Journal!$AL$6:$AL$505,"Loss",Journal!$BP$6:$BP$505,1)) -> 0 | F42: =IF($B42="","",COUNTIFS(Journal!$L$6:$L$505,$B42,Journal!$AL$6:$AL$505,"BE",Journal!$BP$6:$BP$505,1)) -> 0 | G42: =IF($B42="","",IFERROR(D42/C42,0)) -> 0 | H42: =IF($B42="","",SUMIFS(Journal!$AK$6:$AK$505,Journal!$L$6:$L$505,$B42,Journal!$BP$6:$BP$505,1)) -> 0 | I42: =IF($B42="","",IFERROR(H42/C42,0)) -> 0 | J42: =IF($B42="","",SUMIFS(Journal!$AM$6:$AM$505,Journal!$L$6:$L$505,$B42,Journal!$BP$6:$BP$505,1)) -> 0 | K42: =IF($B42="","",IFERROR(SUMIFS(Journal!$AM$6:$AM$505,Journal!$L$6:$L$505,$B42,Journal!$BP$6:$BP$505,1,Journal!$AM$6:$AM$505,">0")/ABS(SUMIFS(Journal!$AM$6:$AM$505,Journal!$L$6:$L$505,$B42,Journal!$BP$6:$BP$505,1,Journal!$AM$6:$AM$505,"<0")),"-")) -> -
B43: =IF(Lists!$G$16="","",Lists!$G$16) | C43: =IF($B43="","",D43+E43+F43) | D43: =IF($B43="","",COUNTIFS(Journal!$L$6:$L$505,$B43,Journal!$AL$6:$AL$505,"Win",Journal!$BP$6:$BP$505,1)) | E43: =IF($B43="","",COUNTIFS(Journal!$L$6:$L$505,$B43,Journal!$AL$6:$AL$505,"Loss",Journal!$BP$6:$BP$505,1)) | F43: =IF($B43="","",COUNTIFS(Journal!$L$6:$L$505,$B43,Journal!$AL$6:$AL$505,"BE",Journal!$BP$6:$BP$505,1)) | G43: =IF($B43="","",IFERROR(D43/C43,0)) | H43: =IF($B43="","",SUMIFS(Journal!$AK$6:$AK$505,Journal!$L$6:$L$505,$B43,Journal!$BP$6:$BP$505,1)) | I43: =IF($B43="","",IFERROR(H43/C43,0)) | J43: =IF($B43="","",SUMIFS(Journal!$AM$6:$AM$505,Journal!$L$6:$L$505,$B43,Journal!$BP$6:$BP$505,1)) | K43: =IF($B43="","",IFERROR(SUMIFS(Journal!$AM$6:$AM$505,Journal!$L$6:$L$505,$B43,Journal!$BP$6:$BP$505,1,Journal!$AM$6:$AM$505,">0")/ABS(SUMIFS(Journal!$AM$6:$AM$505,Journal!$L$6:$L$505,$B43,Journal!$BP$6:$BP$505,1,Journal!$AM$6:$AM$505,"<0")),"-"))
B44: =IF(Lists!$G$17="","",Lists!$G$17) | C44: =IF($B44="","",D44+E44+F44) | D44: =IF($B44="","",COUNTIFS(Journal!$L$6:$L$505,$B44,Journal!$AL$6:$AL$505,"Win",Journal!$BP$6:$BP$505,1)) | E44: =IF($B44="","",COUNTIFS(Journal!$L$6:$L$505,$B44,Journal!$AL$6:$AL$505,"Loss",Journal!$BP$6:$BP$505,1)) | F44: =IF($B44="","",COUNTIFS(Journal!$L$6:$L$505,$B44,Journal!$AL$6:$AL$505,"BE",Journal!$BP$6:$BP$505,1)) | G44: =IF($B44="","",IFERROR(D44/C44,0)) | H44: =IF($B44="","",SUMIFS(Journal!$AK$6:$AK$505,Journal!$L$6:$L$505,$B44,Journal!$BP$6:$BP$505,1)) | I44: =IF($B44="","",IFERROR(H44/C44,0)) | J44: =IF($B44="","",SUMIFS(Journal!$AM$6:$AM$505,Journal!$L$6:$L$505,$B44,Journal!$BP$6:$BP$505,1)) | K44: =IF($B44="","",IFERROR(SUMIFS(Journal!$AM$6:$AM$505,Journal!$L$6:$L$505,$B44,Journal!$BP$6:$BP$505,1,Journal!$AM$6:$AM$505,">0")/ABS(SUMIFS(Journal!$AM$6:$AM$505,Journal!$L$6:$L$505,$B44,Journal!$BP$6:$BP$505,1,Journal!$AM$6:$AM$505,"<0")),"-"))
B47: Zone Type - where entries were taken
B48: Zone Type | C48: Trades | D48: Wins | E48: Losses | F48: BE | G48: Win % | H48: Total R | I48: Avg R | J48: Net P&L ($) | K48: Profit Factor
B49: =IF(Lists!$H$6="","",Lists!$H$6) -> Order Block | C49: =IF($B49="","",D49+E49+F49) -> 1 | D49: =IF($B49="","",COUNTIFS(Journal!$M$6:$M$505,$B49,Journal!$AL$6:$AL$505,"Win",Journal!$BP$6:$BP$505,1)) -> 1 | E49: =IF($B49="","",COUNTIFS(Journal!$M$6:$M$505,$B49,Journal!$AL$6:$AL$505,"Loss",Journal!$BP$6:$BP$505,1)) -> 0 | F49: =IF($B49="","",COUNTIFS(Journal!$M$6:$M$505,$B49,Journal!$AL$6:$AL$505,"BE",Journal!$BP$6:$BP$505,1)) -> 0 | G49: =IF($B49="","",IFERROR(D49/C49,0)) -> 1 | H49: =IF($B49="","",SUMIFS(Journal!$AK$6:$AK$505,Journal!$M$6:$M$505,$B49,Journal!$BP$6:$BP$505,1)) -> 2.33 | I49: =IF($B49="","",IFERROR(H49/C49,0)) -> 2.33 | J49: =IF($B49="","",SUMIFS(Journal!$AM$6:$AM$505,Journal!$M$6:$M$505,$B49,Journal!$BP$6:$BP$505,1)) -> 229.5 | K49: =IF($B49="","",IFERROR(SUMIFS(Journal!$AM$6:$AM$505,Journal!$M$6:$M$505,$B49,Journal!$BP$6:$BP$505,1,Journal!$AM$6:$AM$505,">0")/ABS(SUMIFS(Journal!$AM$6:$AM$505,Journal!$M$6:$M$505,$B49,Journal!$BP$6:$BP$505,1,Journal!$AM$6:$AM$505,"<0")),"-")) -> -
B50: =IF(Lists!$H$7="","",Lists!$H$7) -> Demand Zone | C50: =IF($B50="","",D50+E50+F50) -> 0 | D50: =IF($B50="","",COUNTIFS(Journal!$M$6:$M$505,$B50,Journal!$AL$6:$AL$505,"Win",Journal!$BP$6:$BP$505,1)) -> 0 | E50: =IF($B50="","",COUNTIFS(Journal!$M$6:$M$505,$B50,Journal!$AL$6:$AL$505,"Loss",Journal!$BP$6:$BP$505,1)) -> 0 | F50: =IF($B50="","",COUNTIFS(Journal!$M$6:$M$505,$B50,Journal!$AL$6:$AL$505,"BE",Journal!$BP$6:$BP$505,1)) -> 0 | G50: =IF($B50="","",IFERROR(D50/C50,0)) -> 0 | H50: =IF($B50="","",SUMIFS(Journal!$AK$6:$AK$505,Journal!$M$6:$M$505,$B50,Journal!$BP$6:$BP$505,1)) -> 0 | I50: =IF($B50="","",IFERROR(H50/C50,0)) -> 0 | J50: =IF($B50="","",SUMIFS(Journal!$AM$6:$AM$505,Journal!$M$6:$M$505,$B50,Journal!$BP$6:$BP$505,1)) -> 0 | K50: =IF($B50="","",IFERROR(SUMIFS(Journal!$AM$6:$AM$505,Journal!$M$6:$M$505,$B50,Journal!$BP$6:$BP$505,1,Journal!$AM$6:$AM$505,">0")/ABS(SUMIFS(Journal!$AM$6:$AM$505,Journal!$M$6:$M$505,$B50,Journal!$BP$6:$BP$505,1,Journal!$AM$6:$AM$505,"<0")),"-")) -> -
B51: =IF(Lists!$H$8="","",Lists!$H$8) -> Supply Zone | C51: =IF($B51="","",D51+E51+F51) -> 0 | D51: =IF($B51="","",COUNTIFS(Journal!$M$6:$M$505,$B51,Journal!$AL$6:$AL$505,"Win",Journal!$BP$6:$BP$505,1)) -> 0 | E51: =IF($B51="","",COUNTIFS(Journal!$M$6:$M$505,$B51,Journal!$AL$6:$AL$505,"Loss",Journal!$BP$6:$BP$505,1)) -> 0 | F51: =IF($B51="","",COUNTIFS(Journal!$M$6:$M$505,$B51,Journal!$AL$6:$AL$505,"BE",Journal!$BP$6:$BP$505,1)) -> 0 | G51: =IF($B51="","",IFERROR(D51/C51,0)) -> 0 | H51: =IF($B51="","",SUMIFS(Journal!$AK$6:$AK$505,Journal!$M$6:$M$505,$B51,Journal!$BP$6:$BP$505,1)) -> 0 | I51: =IF($B51="","",IFERROR(H51/C51,0)) -> 0 | J51: =IF($B51="","",SUMIFS(Journal!$AM$6:$AM$505,Journal!$M$6:$M$505,$B51,Journal!$BP$6:$BP$505,1)) -> 0 | K51: =IF($B51="","",IFERROR(SUMIFS(Journal!$AM$6:$AM$505,Journal!$M$6:$M$505,$B51,Journal!$BP$6:$BP$505,1,Journal!$AM$6:$AM$505,">0")/ABS(SUMIFS(Journal!$AM$6:$AM$505,Journal!$M$6:$M$505,$B51,Journal!$BP$6:$BP$505,1,Journal!$AM$6:$AM$505,"<0")),"-")) -> -
B52: =IF(Lists!$H$9="","",Lists!$H$9) -> FVG / Imbalance | C52: =IF($B52="","",D52+E52+F52) -> 0 | D52: =IF($B52="","",COUNTIFS(Journal!$M$6:$M$505,$B52,Journal!$AL$6:$AL$505,"Win",Journal!$BP$6:$BP$505,1)) -> 0 | E52: =IF($B52="","",COUNTIFS(Journal!$M$6:$M$505,$B52,Journal!$AL$6:$AL$505,"Loss",Journal!$BP$6:$BP$505,1)) -> 0 | F52: =IF($B52="","",COUNTIFS(Journal!$M$6:$M$505,$B52,Journal!$AL$6:$AL$505,"BE",Journal!$BP$6:$BP$505,1)) -> 0 | G52: =IF($B52="","",IFERROR(D52/C52,0)) -> 0 | H52: =IF($B52="","",SUMIFS(Journal!$AK$6:$AK$505,Journal!$M$6:$M$505,$B52,Journal!$BP$6:$BP$505,1)) -> 0 | I52: =IF($B52="","",IFERROR(H52/C52,0)) -> 0 | J52: =IF($B52="","",SUMIFS(Journal!$AM$6:$AM$505,Journal!$M$6:$M$505,$B52,Journal!$BP$6:$BP$505,1)) -> 0 | K52: =IF($B52="","",IFERROR(SUMIFS(Journal!$AM$6:$AM$505,Journal!$M$6:$M$505,$B52,Journal!$BP$6:$BP$505,1,Journal!$AM$6:$AM$505,">0")/ABS(SUMIFS(Journal!$AM$6:$AM$505,Journal!$M$6:$M$505,$B52,Journal!$BP$6:$BP$505,1,Journal!$AM$6:$AM$505,"<0")),"-")) -> -
B53: =IF(Lists!$H$10="","",Lists!$H$10) -> Breaker Block | C53: =IF($B53="","",D53+E53+F53) -> 0 | D53: =IF($B53="","",COUNTIFS(Journal!$M$6:$M$505,$B53,Journal!$AL$6:$AL$505,"Win",Journal!$BP$6:$BP$505,1)) -> 0 | E53: =IF($B53="","",COUNTIFS(Journal!$M$6:$M$505,$B53,Journal!$AL$6:$AL$505,"Loss",Journal!$BP$6:$BP$505,1)) -> 0 | F53: =IF($B53="","",COUNTIFS(Journal!$M$6:$M$505,$B53,Journal!$AL$6:$AL$505,"BE",Journal!$BP$6:$BP$505,1)) -> 0 | G53: =IF($B53="","",IFERROR(D53/C53,0)) -> 0 | H53: =IF($B53="","",SUMIFS(Journal!$AK$6:$AK$505,Journal!$M$6:$M$505,$B53,Journal!$BP$6:$BP$505,1)) -> 0 | I53: =IF($B53="","",IFERROR(H53/C53,0)) -> 0 | J53: =IF($B53="","",SUMIFS(Journal!$AM$6:$AM$505,Journal!$M$6:$M$505,$B53,Journal!$BP$6:$BP$505,1)) -> 0 | K53: =IF($B53="","",IFERROR(SUMIFS(Journal!$AM$6:$AM$505,Journal!$M$6:$M$505,$B53,Journal!$BP$6:$BP$505,1,Journal!$AM$6:$AM$505,">0")/ABS(SUMIFS(Journal!$AM$6:$AM$505,Journal!$M$6:$M$505,$B53,Journal!$BP$6:$BP$505,1,Journal!$AM$6:$AM$505,"<0")),"-")) -> -
B54: =IF(Lists!$H$11="","",Lists!$H$11) -> Mitigation Block | C54: =IF($B54="","",D54+E54+F54) -> 0 | D54: =IF($B54="","",COUNTIFS(Journal!$M$6:$M$505,$B54,Journal!$AL$6:$AL$505,"Win",Journal!$BP$6:$BP$505,1)) -> 0 | E54: =IF($B54="","",COUNTIFS(Journal!$M$6:$M$505,$B54,Journal!$AL$6:$AL$505,"Loss",Journal!$BP$6:$BP$505,1)) -> 0 | F54: =IF($B54="","",COUNTIFS(Journal!$M$6:$M$505,$B54,Journal!$AL$6:$AL$505,"BE",Journal!$BP$6:$BP$505,1)) -> 0 | G54: =IF($B54="","",IFERROR(D54/C54,0)) -> 0 | H54: =IF($B54="","",SUMIFS(Journal!$AK$6:$AK$505,Journal!$M$6:$M$505,$B54,Journal!$BP$6:$BP$505,1)) -> 0 | I54: =IF($B54="","",IFERROR(H54/C54,0)) -> 0 | J54: =IF($B54="","",SUMIFS(Journal!$AM$6:$AM$505,Journal!$M$6:$M$505,$B54,Journal!$BP$6:$BP$505,1)) -> 0 | K54: =IF($B54="","",IFERROR(SUMIFS(Journal!$AM$6:$AM$505,Journal!$M$6:$M$505,$B54,Journal!$BP$6:$BP$505,1,Journal!$AM$6:$AM$505,">0")/ABS(SUMIFS(Journal!$AM$6:$AM$505,Journal!$M$6:$M$505,$B54,Journal!$BP$6:$BP$505,1,Journal!$AM$6:$AM$505,"<0")),"-")) -> -
B55: =IF(Lists!$H$12="","",Lists!$H$12) -> Key Level (S/R) | C55: =IF($B55="","",D55+E55+F55) -> 0 | D55: =IF($B55="","",COUNTIFS(Journal!$M$6:$M$505,$B55,Journal!$AL$6:$AL$505,"Win",Journal!$BP$6:$BP$505,1)) -> 0 | E55: =IF($B55="","",COUNTIFS(Journal!$M$6:$M$505,$B55,Journal!$AL$6:$AL$505,"Loss",Journal!$BP$6:$BP$505,1)) -> 0 | F55: =IF($B55="","",COUNTIFS(Journal!$M$6:$M$505,$B55,Journal!$AL$6:$AL$505,"BE",Journal!$BP$6:$BP$505,1)) -> 0 | G55: =IF($B55="","",IFERROR(D55/C55,0)) -> 0 | H55: =IF($B55="","",SUMIFS(Journal!$AK$6:$AK$505,Journal!$M$6:$M$505,$B55,Journal!$BP$6:$BP$505,1)) -> 0 | I55: =IF($B55="","",IFERROR(H55/C55,0)) -> 0 | J55: =IF($B55="","",SUMIFS(Journal!$AM$6:$AM$505,Journal!$M$6:$M$505,$B55,Journal!$BP$6:$BP$505,1)) -> 0 | K55: =IF($B55="","",IFERROR(SUMIFS(Journal!$AM$6:$AM$505,Journal!$M$6:$M$505,$B55,Journal!$BP$6:$BP$505,1,Journal!$AM$6:$AM$505,">0")/ABS(SUMIFS(Journal!$AM$6:$AM$505,Journal!$M$6:$M$505,$B55,Journal!$BP$6:$BP$505,1,Journal!$AM$6:$AM$505,"<0")),"-")) -> -
B56: =IF(Lists!$H$13="","",Lists!$H$13) -> Trendline | C56: =IF($B56="","",D56+E56+F56) -> 0 | D56: =IF($B56="","",COUNTIFS(Journal!$M$6:$M$505,$B56,Journal!$AL$6:$AL$505,"Win",Journal!$BP$6:$BP$505,1)) -> 0 | E56: =IF($B56="","",COUNTIFS(Journal!$M$6:$M$505,$B56,Journal!$AL$6:$AL$505,"Loss",Journal!$BP$6:$BP$505,1)) -> 0 | F56: =IF($B56="","",COUNTIFS(Journal!$M$6:$M$505,$B56,Journal!$AL$6:$AL$505,"BE",Journal!$BP$6:$BP$505,1)) -> 0 | G56: =IF($B56="","",IFERROR(D56/C56,0)) -> 0 | H56: =IF($B56="","",SUMIFS(Journal!$AK$6:$AK$505,Journal!$M$6:$M$505,$B56,Journal!$BP$6:$BP$505,1)) -> 0 | I56: =IF($B56="","",IFERROR(H56/C56,0)) -> 0 | J56: =IF($B56="","",SUMIFS(Journal!$AM$6:$AM$505,Journal!$M$6:$M$505,$B56,Journal!$BP$6:$BP$505,1)) -> 0 | K56: =IF($B56="","",IFERROR(SUMIFS(Journal!$AM$6:$AM$505,Journal!$M$6:$M$505,$B56,Journal!$BP$6:$BP$505,1,Journal!$AM$6:$AM$505,">0")/ABS(SUMIFS(Journal!$AM$6:$AM$505,Journal!$M$6:$M$505,$B56,Journal!$BP$6:$BP$505,1,Journal!$AM$6:$AM$505,"<0")),"-")) -> -
B59: Sweep Type - liquidity taken before entry
B60: Sweep Type | C60: Trades | D60: Wins | E60: Losses | F60: BE | G60: Win % | H60: Total R | I60: Avg R | J60: Net P&L ($) | K60: Profit Factor
B61: =IF(Lists!$I$6="","",Lists!$I$6) -> None | C61: =IF($B61="","",D61+E61+F61) -> 0 | D61: =IF($B61="","",COUNTIFS(Journal!$O$6:$O$505,$B61,Journal!$AL$6:$AL$505,"Win",Journal!$BP$6:$BP$505,1)) -> 0 | E61: =IF($B61="","",COUNTIFS(Journal!$O$6:$O$505,$B61,Journal!$AL$6:$AL$505,"Loss",Journal!$BP$6:$BP$505,1)) -> 0 | F61: =IF($B61="","",COUNTIFS(Journal!$O$6:$O$505,$B61,Journal!$AL$6:$AL$505,"BE",Journal!$BP$6:$BP$505,1)) -> 0 | G61: =IF($B61="","",IFERROR(D61/C61,0)) -> 0 | H61: =IF($B61="","",SUMIFS(Journal!$AK$6:$AK$505,Journal!$O$6:$O$505,$B61,Journal!$BP$6:$BP$505,1)) -> 0 | I61: =IF($B61="","",IFERROR(H61/C61,0)) -> 0 | J61: =IF($B61="","",SUMIFS(Journal!$AM$6:$AM$505,Journal!$O$6:$O$505,$B61,Journal!$BP$6:$BP$505,1)) -> 0 | K61: =IF($B61="","",IFERROR(SUMIFS(Journal!$AM$6:$AM$505,Journal!$O$6:$O$505,$B61,Journal!$BP$6:$BP$505,1,Journal!$AM$6:$AM$505,">0")/ABS(SUMIFS(Journal!$AM$6:$AM$505,Journal!$O$6:$O$505,$B61,Journal!$BP$6:$BP$505,1,Journal!$AM$6:$AM$505,"<0")),"-")) -> -
B62: =IF(Lists!$I$7="","",Lists!$I$7) -> Asia High | C62: =IF($B62="","",D62+E62+F62) -> 1 | D62: =IF($B62="","",COUNTIFS(Journal!$O$6:$O$505,$B62,Journal!$AL$6:$AL$505,"Win",Journal!$BP$6:$BP$505,1)) -> 1 | E62: =IF($B62="","",COUNTIFS(Journal!$O$6:$O$505,$B62,Journal!$AL$6:$AL$505,"Loss",Journal!$BP$6:$BP$505,1)) -> 0 | F62: =IF($B62="","",COUNTIFS(Journal!$O$6:$O$505,$B62,Journal!$AL$6:$AL$505,"BE",Journal!$BP$6:$BP$505,1)) -> 0 | G62: =IF($B62="","",IFERROR(D62/C62,0)) -> 1 | H62: =IF($B62="","",SUMIFS(Journal!$AK$6:$AK$505,Journal!$O$6:$O$505,$B62,Journal!$BP$6:$BP$505,1)) -> 2.33 | I62: =IF($B62="","",IFERROR(H62/C62,0)) -> 2.33 | J62: =IF($B62="","",SUMIFS(Journal!$AM$6:$AM$505,Journal!$O$6:$O$505,$B62,Journal!$BP$6:$BP$505,1)) -> 229.5 | K62: =IF($B62="","",IFERROR(SUMIFS(Journal!$AM$6:$AM$505,Journal!$O$6:$O$505,$B62,Journal!$BP$6:$BP$505,1,Journal!$AM$6:$AM$505,">0")/ABS(SUMIFS(Journal!$AM$6:$AM$505,Journal!$O$6:$O$505,$B62,Journal!$BP$6:$BP$505,1,Journal!$AM$6:$AM$505,"<0")),"-")) -> -
B63: =IF(Lists!$I$8="","",Lists!$I$8) -> Asia Low | C63: =IF($B63="","",D63+E63+F63) -> 0 | D63: =IF($B63="","",COUNTIFS(Journal!$O$6:$O$505,$B63,Journal!$AL$6:$AL$505,"Win",Journal!$BP$6:$BP$505,1)) -> 0 | E63: =IF($B63="","",COUNTIFS(Journal!$O$6:$O$505,$B63,Journal!$AL$6:$AL$505,"Loss",Journal!$BP$6:$BP$505,1)) -> 0 | F63: =IF($B63="","",COUNTIFS(Journal!$O$6:$O$505,$B63,Journal!$AL$6:$AL$505,"BE",Journal!$BP$6:$BP$505,1)) -> 0 | G63: =IF($B63="","",IFERROR(D63/C63,0)) -> 0 | H63: =IF($B63="","",SUMIFS(Journal!$AK$6:$AK$505,Journal!$O$6:$O$505,$B63,Journal!$BP$6:$BP$505,1)) -> 0 | I63: =IF($B63="","",IFERROR(H63/C63,0)) -> 0 | J63: =IF($B63="","",SUMIFS(Journal!$AM$6:$AM$505,Journal!$O$6:$O$505,$B63,Journal!$BP$6:$BP$505,1)) -> 0 | K63: =IF($B63="","",IFERROR(SUMIFS(Journal!$AM$6:$AM$505,Journal!$O$6:$O$505,$B63,Journal!$BP$6:$BP$505,1,Journal!$AM$6:$AM$505,">0")/ABS(SUMIFS(Journal!$AM$6:$AM$505,Journal!$O$6:$O$505,$B63,Journal!$BP$6:$BP$505,1,Journal!$AM$6:$AM$505,"<0")),"-")) -> -
B64: =IF(Lists!$I$9="","",Lists!$I$9) -> Prev Day High | C64: =IF($B64="","",D64+E64+F64) -> 0 | D64: =IF($B64="","",COUNTIFS(Journal!$O$6:$O$505,$B64,Journal!$AL$6:$AL$505,"Win",Journal!$BP$6:$BP$505,1)) -> 0 | E64: =IF($B64="","",COUNTIFS(Journal!$O$6:$O$505,$B64,Journal!$AL$6:$AL$505,"Loss",Journal!$BP$6:$BP$505,1)) -> 0 | F64: =IF($B64="","",COUNTIFS(Journal!$O$6:$O$505,$B64,Journal!$AL$6:$AL$505,"BE",Journal!$BP$6:$BP$505,1)) -> 0 | G64: =IF($B64="","",IFERROR(D64/C64,0)) -> 0 | H64: =IF($B64="","",SUMIFS(Journal!$AK$6:$AK$505,Journal!$O$6:$O$505,$B64,Journal!$BP$6:$BP$505,1)) -> 0 | I64: =IF($B64="","",IFERROR(H64/C64,0)) -> 0 | J64: =IF($B64="","",SUMIFS(Journal!$AM$6:$AM$505,Journal!$O$6:$O$505,$B64,Journal!$BP$6:$BP$505,1)) -> 0 | K64: =IF($B64="","",IFERROR(SUMIFS(Journal!$AM$6:$AM$505,Journal!$O$6:$O$505,$B64,Journal!$BP$6:$BP$505,1,Journal!$AM$6:$AM$505,">0")/ABS(SUMIFS(Journal!$AM$6:$AM$505,Journal!$O$6:$O$505,$B64,Journal!$BP$6:$BP$505,1,Journal!$AM$6:$AM$505,"<0")),"-")) -> -
B65: =IF(Lists!$I$10="","",Lists!$I$10) -> Prev Day Low | C65: =IF($B65="","",D65+E65+F65) -> 0 | D65: =IF($B65="","",COUNTIFS(Journal!$O$6:$O$505,$B65,Journal!$AL$6:$AL$505,"Win",Journal!$BP$6:$BP$505,1)) -> 0 | E65: =IF($B65="","",COUNTIFS(Journal!$O$6:$O$505,$B65,Journal!$AL$6:$AL$505,"Loss",Journal!$BP$6:$BP$505,1)) -> 0 | F65: =IF($B65="","",COUNTIFS(Journal!$O$6:$O$505,$B65,Journal!$AL$6:$AL$505,"BE",Journal!$BP$6:$BP$505,1)) -> 0 | G65: =IF($B65="","",IFERROR(D65/C65,0)) -> 0 | H65: =IF($B65="","",SUMIFS(Journal!$AK$6:$AK$505,Journal!$O$6:$O$505,$B65,Journal!$BP$6:$BP$505,1)) -> 0 | I65: =IF($B65="","",IFERROR(H65/C65,0)) -> 0 | J65: =IF($B65="","",SUMIFS(Journal!$AM$6:$AM$505,Journal!$O$6:$O$505,$B65,Journal!$BP$6:$BP$505,1)) -> 0 | K65: =IF($B65="","",IFERROR(SUMIFS(Journal!$AM$6:$AM$505,Journal!$O$6:$O$505,$B65,Journal!$BP$6:$BP$505,1,Journal!$AM$6:$AM$505,">0")/ABS(SUMIFS(Journal!$AM$6:$AM$505,Journal!$O$6:$O$505,$B65,Journal!$BP$6:$BP$505,1,Journal!$AM$6:$AM$505,"<0")),"-")) -> -
B66: =IF(Lists!$I$11="","",Lists!$I$11) -> Equal Highs | C66: =IF($B66="","",D66+E66+F66) -> 0 | D66: =IF($B66="","",COUNTIFS(Journal!$O$6:$O$505,$B66,Journal!$AL$6:$AL$505,"Win",Journal!$BP$6:$BP$505,1)) -> 0 | E66: =IF($B66="","",COUNTIFS(Journal!$O$6:$O$505,$B66,Journal!$AL$6:$AL$505,"Loss",Journal!$BP$6:$BP$505,1)) -> 0 | F66: =IF($B66="","",COUNTIFS(Journal!$O$6:$O$505,$B66,Journal!$AL$6:$AL$505,"BE",Journal!$BP$6:$BP$505,1)) -> 0 | G66: =IF($B66="","",IFERROR(D66/C66,0)) -> 0 | H66: =IF($B66="","",SUMIFS(Journal!$AK$6:$AK$505,Journal!$O$6:$O$505,$B66,Journal!$BP$6:$BP$505,1)) -> 0 | I66: =IF($B66="","",IFERROR(H66/C66,0)) -> 0 | J66: =IF($B66="","",SUMIFS(Journal!$AM$6:$AM$505,Journal!$O$6:$O$505,$B66,Journal!$BP$6:$BP$505,1)) -> 0 | K66: =IF($B66="","",IFERROR(SUMIFS(Journal!$AM$6:$AM$505,Journal!$O$6:$O$505,$B66,Journal!$BP$6:$BP$505,1,Journal!$AM$6:$AM$505,">0")/ABS(SUMIFS(Journal!$AM$6:$AM$505,Journal!$O$6:$O$505,$B66,Journal!$BP$6:$BP$505,1,Journal!$AM$6:$AM$505,"<0")),"-")) -> -
B67: =IF(Lists!$I$12="","",Lists!$I$12) -> Equal Lows | C67: =IF($B67="","",D67+E67+F67) -> 0 | D67: =IF($B67="","",COUNTIFS(Journal!$O$6:$O$505,$B67,Journal!$AL$6:$AL$505,"Win",Journal!$BP$6:$BP$505,1)) -> 0 | E67: =IF($B67="","",COUNTIFS(Journal!$O$6:$O$505,$B67,Journal!$AL$6:$AL$505,"Loss",Journal!$BP$6:$BP$505,1)) -> 0 | F67: =IF($B67="","",COUNTIFS(Journal!$O$6:$O$505,$B67,Journal!$AL$6:$AL$505,"BE",Journal!$BP$6:$BP$505,1)) -> 0 | G67: =IF($B67="","",IFERROR(D67/C67,0)) -> 0 | H67: =IF($B67="","",SUMIFS(Journal!$AK$6:$AK$505,Journal!$O$6:$O$505,$B67,Journal!$BP$6:$BP$505,1)) -> 0 | I67: =IF($B67="","",IFERROR(H67/C67,0)) -> 0 | J67: =IF($B67="","",SUMIFS(Journal!$AM$6:$AM$505,Journal!$O$6:$O$505,$B67,Journal!$BP$6:$BP$505,1)) -> 0 | K67: =IF($B67="","",IFERROR(SUMIFS(Journal!$AM$6:$AM$505,Journal!$O$6:$O$505,$B67,Journal!$BP$6:$BP$505,1,Journal!$AM$6:$AM$505,">0")/ABS(SUMIFS(Journal!$AM$6:$AM$505,Journal!$O$6:$O$505,$B67,Journal!$BP$6:$BP$505,1,Journal!$AM$6:$AM$505,"<0")),"-")) -> -
B68: =IF(Lists!$I$13="","",Lists!$I$13) -> Swing High/Low | C68: =IF($B68="","",D68+E68+F68) -> 0 | D68: =IF($B68="","",COUNTIFS(Journal!$O$6:$O$505,$B68,Journal!$AL$6:$AL$505,"Win",Journal!$BP$6:$BP$505,1)) -> 0 | E68: =IF($B68="","",COUNTIFS(Journal!$O$6:$O$505,$B68,Journal!$AL$6:$AL$505,"Loss",Journal!$BP$6:$BP$505,1)) -> 0 | F68: =IF($B68="","",COUNTIFS(Journal!$O$6:$O$505,$B68,Journal!$AL$6:$AL$505,"BE",Journal!$BP$6:$BP$505,1)) -> 0 | G68: =IF($B68="","",IFERROR(D68/C68,0)) -> 0 | H68: =IF($B68="","",SUMIFS(Journal!$AK$6:$AK$505,Journal!$O$6:$O$505,$B68,Journal!$BP$6:$BP$505,1)) -> 0 | I68: =IF($B68="","",IFERROR(H68/C68,0)) -> 0 | J68: =IF($B68="","",SUMIFS(Journal!$AM$6:$AM$505,Journal!$O$6:$O$505,$B68,Journal!$BP$6:$BP$505,1)) -> 0 | K68: =IF($B68="","",IFERROR(SUMIFS(Journal!$AM$6:$AM$505,Journal!$O$6:$O$505,$B68,Journal!$BP$6:$BP$505,1,Journal!$AM$6:$AM$505,">0")/ABS(SUMIFS(Journal!$AM$6:$AM$505,Journal!$O$6:$O$505,$B68,Journal!$BP$6:$BP$505,1,Journal!$AM$6:$AM$505,"<0")),"-")) -> -
B71: Liquidity Sweep? - sweep vs no sweep
B72: Liquidity Sweep? | C72: Trades | D72: Wins | E72: Losses | F72: BE | G72: Win % | H72: Total R | I72: Avg R | J72: Net P&L ($) | K72: Profit Factor
B73: Yes | C73: =IF($B73="","",D73+E73+F73) -> 1 | D73: =IF($B73="","",COUNTIFS(Journal!$N$6:$N$505,$B73,Journal!$AL$6:$AL$505,"Win",Journal!$BP$6:$BP$505,1)) -> 1 | E73: =IF($B73="","",COUNTIFS(Journal!$N$6:$N$505,$B73,Journal!$AL$6:$AL$505,"Loss",Journal!$BP$6:$BP$505,1)) -> 0 | F73: =IF($B73="","",COUNTIFS(Journal!$N$6:$N$505,$B73,Journal!$AL$6:$AL$505,"BE",Journal!$BP$6:$BP$505,1)) -> 0 | G73: =IF($B73="","",IFERROR(D73/C73,0)) -> 1 | H73: =IF($B73="","",SUMIFS(Journal!$AK$6:$AK$505,Journal!$N$6:$N$505,$B73,Journal!$BP$6:$BP$505,1)) -> 2.33 | I73: =IF($B73="","",IFERROR(H73/C73,0)) -> 2.33 | J73: =IF($B73="","",SUMIFS(Journal!$AM$6:$AM$505,Journal!$N$6:$N$505,$B73,Journal!$BP$6:$BP$505,1)) -> 229.5 | K73: =IF($B73="","",IFERROR(SUMIFS(Journal!$AM$6:$AM$505,Journal!$N$6:$N$505,$B73,Journal!$BP$6:$BP$505,1,Journal!$AM$6:$AM$505,">0")/ABS(SUMIFS(Journal!$AM$6:$AM$505,Journal!$N$6:$N$505,$B73,Journal!$BP$6:$BP$505,1,Journal!$AM$6:$AM$505,"<0")),"-")) -> -
B74: No | C74: =IF($B74="","",D74+E74+F74) -> 0 | D74: =IF($B74="","",COUNTIFS(Journal!$N$6:$N$505,$B74,Journal!$AL$6:$AL$505,"Win",Journal!$BP$6:$BP$505,1)) -> 0 | E74: =IF($B74="","",COUNTIFS(Journal!$N$6:$N$505,$B74,Journal!$AL$6:$AL$505,"Loss",Journal!$BP$6:$BP$505,1)) -> 0 | F74: =IF($B74="","",COUNTIFS(Journal!$N$6:$N$505,$B74,Journal!$AL$6:$AL$505,"BE",Journal!$BP$6:$BP$505,1)) -> 0 | G74: =IF($B74="","",IFERROR(D74/C74,0)) -> 0 | H74: =IF($B74="","",SUMIFS(Journal!$AK$6:$AK$505,Journal!$N$6:$N$505,$B74,Journal!$BP$6:$BP$505,1)) -> 0 | I74: =IF($B74="","",IFERROR(H74/C74,0)) -> 0 | J74: =IF($B74="","",SUMIFS(Journal!$AM$6:$AM$505,Journal!$N$6:$N$505,$B74,Journal!$BP$6:$BP$505,1)) -> 0 | K74: =IF($B74="","",IFERROR(SUMIFS(Journal!$AM$6:$AM$505,Journal!$N$6:$N$505,$B74,Journal!$BP$6:$BP$505,1,Journal!$AM$6:$AM$505,">0")/ABS(SUMIFS(Journal!$AM$6:$AM$505,Journal!$N$6:$N$505,$B74,Journal!$BP$6:$BP$505,1,Journal!$AM$6:$AM$505,"<0")),"-")) -> -
B77: HTF Bias - higher-timeframe bias
B78: HTF Bias | C78: Trades | D78: Wins | E78: Losses | F78: BE | G78: Win % | H78: Total R | I78: Avg R | J78: Net P&L ($) | K78: Profit Factor
B79: =IF(Lists!$J$6="","",Lists!$J$6) -> Bullish | C79: =IF($B79="","",D79+E79+F79) -> 0 | D79: =IF($B79="","",COUNTIFS(Journal!$K$6:$K$505,$B79,Journal!$AL$6:$AL$505,"Win",Journal!$BP$6:$BP$505,1)) -> 0 | E79: =IF($B79="","",COUNTIFS(Journal!$K$6:$K$505,$B79,Journal!$AL$6:$AL$505,"Loss",Journal!$BP$6:$BP$505,1)) -> 0 | F79: =IF($B79="","",COUNTIFS(Journal!$K$6:$K$505,$B79,Journal!$AL$6:$AL$505,"BE",Journal!$BP$6:$BP$505,1)) -> 0 | G79: =IF($B79="","",IFERROR(D79/C79,0)) -> 0 | H79: =IF($B79="","",SUMIFS(Journal!$AK$6:$AK$505,Journal!$K$6:$K$505,$B79,Journal!$BP$6:$BP$505,1)) -> 0 | I79: =IF($B79="","",IFERROR(H79/C79,0)) -> 0 | J79: =IF($B79="","",SUMIFS(Journal!$AM$6:$AM$505,Journal!$K$6:$K$505,$B79,Journal!$BP$6:$BP$505,1)) -> 0 | K79: =IF($B79="","",IFERROR(SUMIFS(Journal!$AM$6:$AM$505,Journal!$K$6:$K$505,$B79,Journal!$BP$6:$BP$505,1,Journal!$AM$6:$AM$505,">0")/ABS(SUMIFS(Journal!$AM$6:$AM$505,Journal!$K$6:$K$505,$B79,Journal!$BP$6:$BP$505,1,Journal!$AM$6:$AM$505,"<0")),"-")) -> -
B80: =IF(Lists!$J$7="","",Lists!$J$7) -> Bearish | C80: =IF($B80="","",D80+E80+F80) -> 1 | D80: =IF($B80="","",COUNTIFS(Journal!$K$6:$K$505,$B80,Journal!$AL$6:$AL$505,"Win",Journal!$BP$6:$BP$505,1)) -> 1 | E80: =IF($B80="","",COUNTIFS(Journal!$K$6:$K$505,$B80,Journal!$AL$6:$AL$505,"Loss",Journal!$BP$6:$BP$505,1)) -> 0 | F80: =IF($B80="","",COUNTIFS(Journal!$K$6:$K$505,$B80,Journal!$AL$6:$AL$505,"BE",Journal!$BP$6:$BP$505,1)) -> 0 | G80: =IF($B80="","",IFERROR(D80/C80,0)) -> 1 | H80: =IF($B80="","",SUMIFS(Journal!$AK$6:$AK$505,Journal!$K$6:$K$505,$B80,Journal!$BP$6:$BP$505,1)) -> 2.33 | I80: =IF($B80="","",IFERROR(H80/C80,0)) -> 2.33 | J80: =IF($B80="","",SUMIFS(Journal!$AM$6:$AM$505,Journal!$K$6:$K$505,$B80,Journal!$BP$6:$BP$505,1)) -> 229.5 | K80: =IF($B80="","",IFERROR(SUMIFS(Journal!$AM$6:$AM$505,Journal!$K$6:$K$505,$B80,Journal!$BP$6:$BP$505,1,Journal!$AM$6:$AM$505,">0")/ABS(SUMIFS(Journal!$AM$6:$AM$505,Journal!$K$6:$K$505,$B80,Journal!$BP$6:$BP$505,1,Journal!$AM$6:$AM$505,"<0")),"-")) -> -
B81: =IF(Lists!$J$8="","",Lists!$J$8) -> Range / Unclear | C81: =IF($B81="","",D81+E81+F81) -> 0 | D81: =IF($B81="","",COUNTIFS(Journal!$K$6:$K$505,$B81,Journal!$AL$6:$AL$505,"Win",Journal!$BP$6:$BP$505,1)) -> 0 | E81: =IF($B81="","",COUNTIFS(Journal!$K$6:$K$505,$B81,Journal!$AL$6:$AL$505,"Loss",Journal!$BP$6:$BP$505,1)) -> 0 | F81: =IF($B81="","",COUNTIFS(Journal!$K$6:$K$505,$B81,Journal!$AL$6:$AL$505,"BE",Journal!$BP$6:$BP$505,1)) -> 0 | G81: =IF($B81="","",IFERROR(D81/C81,0)) -> 0 | H81: =IF($B81="","",SUMIFS(Journal!$AK$6:$AK$505,Journal!$K$6:$K$505,$B81,Journal!$BP$6:$BP$505,1)) -> 0 | I81: =IF($B81="","",IFERROR(H81/C81,0)) -> 0 | J81: =IF($B81="","",SUMIFS(Journal!$AM$6:$AM$505,Journal!$K$6:$K$505,$B81,Journal!$BP$6:$BP$505,1)) -> 0 | K81: =IF($B81="","",IFERROR(SUMIFS(Journal!$AM$6:$AM$505,Journal!$K$6:$K$505,$B81,Journal!$BP$6:$BP$505,1,Journal!$AM$6:$AM$505,">0")/ABS(SUMIFS(Journal!$AM$6:$AM$505,Journal!$K$6:$K$505,$B81,Journal!$BP$6:$BP$505,1,Journal!$AM$6:$AM$505,"<0")),"-")) -> -
B82: =IF(Lists!$J$9="","",Lists!$J$9) | C82: =IF($B82="","",D82+E82+F82) | D82: =IF($B82="","",COUNTIFS(Journal!$K$6:$K$505,$B82,Journal!$AL$6:$AL$505,"Win",Journal!$BP$6:$BP$505,1)) | E82: =IF($B82="","",COUNTIFS(Journal!$K$6:$K$505,$B82,Journal!$AL$6:$AL$505,"Loss",Journal!$BP$6:$BP$505,1)) | F82: =IF($B82="","",COUNTIFS(Journal!$K$6:$K$505,$B82,Journal!$AL$6:$AL$505,"BE",Journal!$BP$6:$BP$505,1)) | G82: =IF($B82="","",IFERROR(D82/C82,0)) | H82: =IF($B82="","",SUMIFS(Journal!$AK$6:$AK$505,Journal!$K$6:$K$505,$B82,Journal!$BP$6:$BP$505,1)) | I82: =IF($B82="","",IFERROR(H82/C82,0)) | J82: =IF($B82="","",SUMIFS(Journal!$AM$6:$AM$505,Journal!$K$6:$K$505,$B82,Journal!$BP$6:$BP$505,1)) | K82: =IF($B82="","",IFERROR(SUMIFS(Journal!$AM$6:$AM$505,Journal!$K$6:$K$505,$B82,Journal!$BP$6:$BP$505,1,Journal!$AM$6:$AM$505,">0")/ABS(SUMIFS(Journal!$AM$6:$AM$505,Journal!$K$6:$K$505,$B82,Journal!$BP$6:$BP$505,1,Journal!$AM$6:$AM$505,"<0")),"-"))
B85: Setup Grade - A+ to C
B86: Setup Grade | C86: Trades | D86: Wins | E86: Losses | F86: BE | G86: Win % | H86: Total R | I86: Avg R | J86: Net P&L ($) | K86: Profit Factor
B87: A+ | C87: =IF($B87="","",D87+E87+F87) -> 1 | D87: =IF($B87="","",COUNTIFS(Journal!$Y$6:$Y$505,$B87,Journal!$AL$6:$AL$505,"Win",Journal!$BP$6:$BP$505,1)) -> 1 | E87: =IF($B87="","",COUNTIFS(Journal!$Y$6:$Y$505,$B87,Journal!$AL$6:$AL$505,"Loss",Journal!$BP$6:$BP$505,1)) -> 0 | F87: =IF($B87="","",COUNTIFS(Journal!$Y$6:$Y$505,$B87,Journal!$AL$6:$AL$505,"BE",Journal!$BP$6:$BP$505,1)) -> 0 | G87: =IF($B87="","",IFERROR(D87/C87,0)) -> 1 | H87: =IF($B87="","",SUMIFS(Journal!$AK$6:$AK$505,Journal!$Y$6:$Y$505,$B87,Journal!$BP$6:$BP$505,1)) -> 2.33 | I87: =IF($B87="","",IFERROR(H87/C87,0)) -> 2.33 | J87: =IF($B87="","",SUMIFS(Journal!$AM$6:$AM$505,Journal!$Y$6:$Y$505,$B87,Journal!$BP$6:$BP$505,1)) -> 229.5 | K87: =IF($B87="","",IFERROR(SUMIFS(Journal!$AM$6:$AM$505,Journal!$Y$6:$Y$505,$B87,Journal!$BP$6:$BP$505,1,Journal!$AM$6:$AM$505,">0")/ABS(SUMIFS(Journal!$AM$6:$AM$505,Journal!$Y$6:$Y$505,$B87,Journal!$BP$6:$BP$505,1,Journal!$AM$6:$AM$505,"<0")),"-")) -> -
B88: A | C88: =IF($B88="","",D88+E88+F88) -> 0 | D88: =IF($B88="","",COUNTIFS(Journal!$Y$6:$Y$505,$B88,Journal!$AL$6:$AL$505,"Win",Journal!$BP$6:$BP$505,1)) -> 0 | E88: =IF($B88="","",COUNTIFS(Journal!$Y$6:$Y$505,$B88,Journal!$AL$6:$AL$505,"Loss",Journal!$BP$6:$BP$505,1)) -> 0 | F88: =IF($B88="","",COUNTIFS(Journal!$Y$6:$Y$505,$B88,Journal!$AL$6:$AL$505,"BE",Journal!$BP$6:$BP$505,1)) -> 0 | G88: =IF($B88="","",IFERROR(D88/C88,0)) -> 0 | H88: =IF($B88="","",SUMIFS(Journal!$AK$6:$AK$505,Journal!$Y$6:$Y$505,$B88,Journal!$BP$6:$BP$505,1)) -> 0 | I88: =IF($B88="","",IFERROR(H88/C88,0)) -> 0 | J88: =IF($B88="","",SUMIFS(Journal!$AM$6:$AM$505,Journal!$Y$6:$Y$505,$B88,Journal!$BP$6:$BP$505,1)) -> 0 | K88: =IF($B88="","",IFERROR(SUMIFS(Journal!$AM$6:$AM$505,Journal!$Y$6:$Y$505,$B88,Journal!$BP$6:$BP$505,1,Journal!$AM$6:$AM$505,">0")/ABS(SUMIFS(Journal!$AM$6:$AM$505,Journal!$Y$6:$Y$505,$B88,Journal!$BP$6:$BP$505,1,Journal!$AM$6:$AM$505,"<0")),"-")) -> -
B89: B | C89: =IF($B89="","",D89+E89+F89) -> 0 | D89: =IF($B89="","",COUNTIFS(Journal!$Y$6:$Y$505,$B89,Journal!$AL$6:$AL$505,"Win",Journal!$BP$6:$BP$505,1)) -> 0 | E89: =IF($B89="","",COUNTIFS(Journal!$Y$6:$Y$505,$B89,Journal!$AL$6:$AL$505,"Loss",Journal!$BP$6:$BP$505,1)) -> 0 | F89: =IF($B89="","",COUNTIFS(Journal!$Y$6:$Y$505,$B89,Journal!$AL$6:$AL$505,"BE",Journal!$BP$6:$BP$505,1)) -> 0 | G89: =IF($B89="","",IFERROR(D89/C89,0)) -> 0 | H89: =IF($B89="","",SUMIFS(Journal!$AK$6:$AK$505,Journal!$Y$6:$Y$505,$B89,Journal!$BP$6:$BP$505,1)) -> 0 | I89: =IF($B89="","",IFERROR(H89/C89,0)) -> 0 | J89: =IF($B89="","",SUMIFS(Journal!$AM$6:$AM$505,Journal!$Y$6:$Y$505,$B89,Journal!$BP$6:$BP$505,1)) -> 0 | K89: =IF($B89="","",IFERROR(SUMIFS(Journal!$AM$6:$AM$505,Journal!$Y$6:$Y$505,$B89,Journal!$BP$6:$BP$505,1,Journal!$AM$6:$AM$505,">0")/ABS(SUMIFS(Journal!$AM$6:$AM$505,Journal!$Y$6:$Y$505,$B89,Journal!$BP$6:$BP$505,1,Journal!$AM$6:$AM$505,"<0")),"-")) -> -
B90: C | C90: =IF($B90="","",D90+E90+F90) -> 0 | D90: =IF($B90="","",COUNTIFS(Journal!$Y$6:$Y$505,$B90,Journal!$AL$6:$AL$505,"Win",Journal!$BP$6:$BP$505,1)) -> 0 | E90: =IF($B90="","",COUNTIFS(Journal!$Y$6:$Y$505,$B90,Journal!$AL$6:$AL$505,"Loss",Journal!$BP$6:$BP$505,1)) -> 0 | F90: =IF($B90="","",COUNTIFS(Journal!$Y$6:$Y$505,$B90,Journal!$AL$6:$AL$505,"BE",Journal!$BP$6:$BP$505,1)) -> 0 | G90: =IF($B90="","",IFERROR(D90/C90,0)) -> 0 | H90: =IF($B90="","",SUMIFS(Journal!$AK$6:$AK$505,Journal!$Y$6:$Y$505,$B90,Journal!$BP$6:$BP$505,1)) -> 0 | I90: =IF($B90="","",IFERROR(H90/C90,0)) -> 0 | J90: =IF($B90="","",SUMIFS(Journal!$AM$6:$AM$505,Journal!$Y$6:$Y$505,$B90,Journal!$BP$6:$BP$505,1)) -> 0 | K90: =IF($B90="","",IFERROR(SUMIFS(Journal!$AM$6:$AM$505,Journal!$Y$6:$Y$505,$B90,Journal!$BP$6:$BP$505,1,Journal!$AM$6:$AM$505,">0")/ABS(SUMIFS(Journal!$AM$6:$AM$505,Journal!$Y$6:$Y$505,$B90,Journal!$BP$6:$BP$505,1,Journal!$AM$6:$AM$505,"<0")),"-")) -> -
B93: Direction - long vs short
B94: Direction | C94: Trades | D94: Wins | E94: Losses | F94: BE | G94: Win % | H94: Total R | I94: Avg R | J94: Net P&L ($) | K94: Profit Factor
B95: Long | C95: =IF($B95="","",D95+E95+F95) -> 0 | D95: =IF($B95="","",COUNTIFS(Journal!$J$6:$J$505,$B95,Journal!$AL$6:$AL$505,"Win",Journal!$BP$6:$BP$505,1)) -> 0 | E95: =IF($B95="","",COUNTIFS(Journal!$J$6:$J$505,$B95,Journal!$AL$6:$AL$505,"Loss",Journal!$BP$6:$BP$505,1)) -> 0 | F95: =IF($B95="","",COUNTIFS(Journal!$J$6:$J$505,$B95,Journal!$AL$6:$AL$505,"BE",Journal!$BP$6:$BP$505,1)) -> 0 | G95: =IF($B95="","",IFERROR(D95/C95,0)) -> 0 | H95: =IF($B95="","",SUMIFS(Journal!$AK$6:$AK$505,Journal!$J$6:$J$505,$B95,Journal!$BP$6:$BP$505,1)) -> 0 | I95: =IF($B95="","",IFERROR(H95/C95,0)) -> 0 | J95: =IF($B95="","",SUMIFS(Journal!$AM$6:$AM$505,Journal!$J$6:$J$505,$B95,Journal!$BP$6:$BP$505,1)) -> 0 | K95: =IF($B95="","",IFERROR(SUMIFS(Journal!$AM$6:$AM$505,Journal!$J$6:$J$505,$B95,Journal!$BP$6:$BP$505,1,Journal!$AM$6:$AM$505,">0")/ABS(SUMIFS(Journal!$AM$6:$AM$505,Journal!$J$6:$J$505,$B95,Journal!$BP$6:$BP$505,1,Journal!$AM$6:$AM$505,"<0")),"-")) -> -
B96: Short | C96: =IF($B96="","",D96+E96+F96) -> 1 | D96: =IF($B96="","",COUNTIFS(Journal!$J$6:$J$505,$B96,Journal!$AL$6:$AL$505,"Win",Journal!$BP$6:$BP$505,1)) -> 1 | E96: =IF($B96="","",COUNTIFS(Journal!$J$6:$J$505,$B96,Journal!$AL$6:$AL$505,"Loss",Journal!$BP$6:$BP$505,1)) -> 0 | F96: =IF($B96="","",COUNTIFS(Journal!$J$6:$J$505,$B96,Journal!$AL$6:$AL$505,"BE",Journal!$BP$6:$BP$505,1)) -> 0 | G96: =IF($B96="","",IFERROR(D96/C96,0)) -> 1 | H96: =IF($B96="","",SUMIFS(Journal!$AK$6:$AK$505,Journal!$J$6:$J$505,$B96,Journal!$BP$6:$BP$505,1)) -> 2.33 | I96: =IF($B96="","",IFERROR(H96/C96,0)) -> 2.33 | J96: =IF($B96="","",SUMIFS(Journal!$AM$6:$AM$505,Journal!$J$6:$J$505,$B96,Journal!$BP$6:$BP$505,1)) -> 229.5 | K96: =IF($B96="","",IFERROR(SUMIFS(Journal!$AM$6:$AM$505,Journal!$J$6:$J$505,$B96,Journal!$BP$6:$BP$505,1,Journal!$AM$6:$AM$505,">0")/ABS(SUMIFS(Journal!$AM$6:$AM$505,Journal!$J$6:$J$505,$B96,Journal!$BP$6:$BP$505,1,Journal!$AM$6:$AM$505,"<0")),"-")) -> -
B99: Weekday - performance by day of week
B100: Weekday | C100: Trades | D100: Wins | E100: Losses | F100: BE | G100: Win % | H100: Total R | I100: Avg R | J100: Net P&L ($) | K100: Profit Factor
B101: Mon | C101: =IF($B101="","",D101+E101+F101) -> 1 | D101: =IF($B101="","",COUNTIFS(Journal!$C$6:$C$505,$B101,Journal!$AL$6:$AL$505,"Win",Journal!$BP$6:$BP$505,1)) -> 1 | E101: =IF($B101="","",COUNTIFS(Journal!$C$6:$C$505,$B101,Journal!$AL$6:$AL$505,"Loss",Journal!$BP$6:$BP$505,1)) -> 0 | F101: =IF($B101="","",COUNTIFS(Journal!$C$6:$C$505,$B101,Journal!$AL$6:$AL$505,"BE",Journal!$BP$6:$BP$505,1)) -> 0 | G101: =IF($B101="","",IFERROR(D101/C101,0)) -> 1 | H101: =IF($B101="","",SUMIFS(Journal!$AK$6:$AK$505,Journal!$C$6:$C$505,$B101,Journal!$BP$6:$BP$505,1)) -> 2.33 | I101: =IF($B101="","",IFERROR(H101/C101,0)) -> 2.33 | J101: =IF($B101="","",SUMIFS(Journal!$AM$6:$AM$505,Journal!$C$6:$C$505,$B101,Journal!$BP$6:$BP$505,1)) -> 229.5 | K101: =IF($B101="","",IFERROR(SUMIFS(Journal!$AM$6:$AM$505,Journal!$C$6:$C$505,$B101,Journal!$BP$6:$BP$505,1,Journal!$AM$6:$AM$505,">0")/ABS(SUMIFS(Journal!$AM$6:$AM$505,Journal!$C$6:$C$505,$B101,Journal!$BP$6:$BP$505,1,Journal!$AM$6:$AM$505,"<0")),"-")) -> -
B102: Tue | C102: =IF($B102="","",D102+E102+F102) -> 0 | D102: =IF($B102="","",COUNTIFS(Journal!$C$6:$C$505,$B102,Journal!$AL$6:$AL$505,"Win",Journal!$BP$6:$BP$505,1)) -> 0 | E102: =IF($B102="","",COUNTIFS(Journal!$C$6:$C$505,$B102,Journal!$AL$6:$AL$505,"Loss",Journal!$BP$6:$BP$505,1)) -> 0 | F102: =IF($B102="","",COUNTIFS(Journal!$C$6:$C$505,$B102,Journal!$AL$6:$AL$505,"BE",Journal!$BP$6:$BP$505,1)) -> 0 | G102: =IF($B102="","",IFERROR(D102/C102,0)) -> 0 | H102: =IF($B102="","",SUMIFS(Journal!$AK$6:$AK$505,Journal!$C$6:$C$505,$B102,Journal!$BP$6:$BP$505,1)) -> 0 | I102: =IF($B102="","",IFERROR(H102/C102,0)) -> 0 | J102: =IF($B102="","",SUMIFS(Journal!$AM$6:$AM$505,Journal!$C$6:$C$505,$B102,Journal!$BP$6:$BP$505,1)) -> 0 | K102: =IF($B102="","",IFERROR(SUMIFS(Journal!$AM$6:$AM$505,Journal!$C$6:$C$505,$B102,Journal!$BP$6:$BP$505,1,Journal!$AM$6:$AM$505,">0")/ABS(SUMIFS(Journal!$AM$6:$AM$505,Journal!$C$6:$C$505,$B102,Journal!$BP$6:$BP$505,1,Journal!$AM$6:$AM$505,"<0")),"-")) -> -
B103: Wed | C103: =IF($B103="","",D103+E103+F103) -> 0 | D103: =IF($B103="","",COUNTIFS(Journal!$C$6:$C$505,$B103,Journal!$AL$6:$AL$505,"Win",Journal!$BP$6:$BP$505,1)) -> 0 | E103: =IF($B103="","",COUNTIFS(Journal!$C$6:$C$505,$B103,Journal!$AL$6:$AL$505,"Loss",Journal!$BP$6:$BP$505,1)) -> 0 | F103: =IF($B103="","",COUNTIFS(Journal!$C$6:$C$505,$B103,Journal!$AL$6:$AL$505,"BE",Journal!$BP$6:$BP$505,1)) -> 0 | G103: =IF($B103="","",IFERROR(D103/C103,0)) -> 0 | H103: =IF($B103="","",SUMIFS(Journal!$AK$6:$AK$505,Journal!$C$6:$C$505,$B103,Journal!$BP$6:$BP$505,1)) -> 0 | I103: =IF($B103="","",IFERROR(H103/C103,0)) -> 0 | J103: =IF($B103="","",SUMIFS(Journal!$AM$6:$AM$505,Journal!$C$6:$C$505,$B103,Journal!$BP$6:$BP$505,1)) -> 0 | K103: =IF($B103="","",IFERROR(SUMIFS(Journal!$AM$6:$AM$505,Journal!$C$6:$C$505,$B103,Journal!$BP$6:$BP$505,1,Journal!$AM$6:$AM$505,">0")/ABS(SUMIFS(Journal!$AM$6:$AM$505,Journal!$C$6:$C$505,$B103,Journal!$BP$6:$BP$505,1,Journal!$AM$6:$AM$505,"<0")),"-")) -> -
B104: Thu | C104: =IF($B104="","",D104+E104+F104) -> 0 | D104: =IF($B104="","",COUNTIFS(Journal!$C$6:$C$505,$B104,Journal!$AL$6:$AL$505,"Win",Journal!$BP$6:$BP$505,1)) -> 0 | E104: =IF($B104="","",COUNTIFS(Journal!$C$6:$C$505,$B104,Journal!$AL$6:$AL$505,"Loss",Journal!$BP$6:$BP$505,1)) -> 0 | F104: =IF($B104="","",COUNTIFS(Journal!$C$6:$C$505,$B104,Journal!$AL$6:$AL$505,"BE",Journal!$BP$6:$BP$505,1)) -> 0 | G104: =IF($B104="","",IFERROR(D104/C104,0)) -> 0 | H104: =IF($B104="","",SUMIFS(Journal!$AK$6:$AK$505,Journal!$C$6:$C$505,$B104,Journal!$BP$6:$BP$505,1)) -> 0 | I104: =IF($B104="","",IFERROR(H104/C104,0)) -> 0 | J104: =IF($B104="","",SUMIFS(Journal!$AM$6:$AM$505,Journal!$C$6:$C$505,$B104,Journal!$BP$6:$BP$505,1)) -> 0 | K104: =IF($B104="","",IFERROR(SUMIFS(Journal!$AM$6:$AM$505,Journal!$C$6:$C$505,$B104,Journal!$BP$6:$BP$505,1,Journal!$AM$6:$AM$505,">0")/ABS(SUMIFS(Journal!$AM$6:$AM$505,Journal!$C$6:$C$505,$B104,Journal!$BP$6:$BP$505,1,Journal!$AM$6:$AM$505,"<0")),"-")) -> -
B105: Fri | C105: =IF($B105="","",D105+E105+F105) -> 0 | D105: =IF($B105="","",COUNTIFS(Journal!$C$6:$C$505,$B105,Journal!$AL$6:$AL$505,"Win",Journal!$BP$6:$BP$505,1)) -> 0 | E105: =IF($B105="","",COUNTIFS(Journal!$C$6:$C$505,$B105,Journal!$AL$6:$AL$505,"Loss",Journal!$BP$6:$BP$505,1)) -> 0 | F105: =IF($B105="","",COUNTIFS(Journal!$C$6:$C$505,$B105,Journal!$AL$6:$AL$505,"BE",Journal!$BP$6:$BP$505,1)) -> 0 | G105: =IF($B105="","",IFERROR(D105/C105,0)) -> 0 | H105: =IF($B105="","",SUMIFS(Journal!$AK$6:$AK$505,Journal!$C$6:$C$505,$B105,Journal!$BP$6:$BP$505,1)) -> 0 | I105: =IF($B105="","",IFERROR(H105/C105,0)) -> 0 | J105: =IF($B105="","",SUMIFS(Journal!$AM$6:$AM$505,Journal!$C$6:$C$505,$B105,Journal!$BP$6:$BP$505,1)) -> 0 | K105: =IF($B105="","",IFERROR(SUMIFS(Journal!$AM$6:$AM$505,Journal!$C$6:$C$505,$B105,Journal!$BP$6:$BP$505,1,Journal!$AM$6:$AM$505,">0")/ABS(SUMIFS(Journal!$AM$6:$AM$505,Journal!$C$6:$C$505,$B105,Journal!$BP$6:$BP$505,1,Journal!$AM$6:$AM$505,"<0")),"-")) -> -
B106: Sat | C106: =IF($B106="","",D106+E106+F106) -> 0 | D106: =IF($B106="","",COUNTIFS(Journal!$C$6:$C$505,$B106,Journal!$AL$6:$AL$505,"Win",Journal!$BP$6:$BP$505,1)) -> 0 | E106: =IF($B106="","",COUNTIFS(Journal!$C$6:$C$505,$B106,Journal!$AL$6:$AL$505,"Loss",Journal!$BP$6:$BP$505,1)) -> 0 | F106: =IF($B106="","",COUNTIFS(Journal!$C$6:$C$505,$B106,Journal!$AL$6:$AL$505,"BE",Journal!$BP$6:$BP$505,1)) -> 0 | G106: =IF($B106="","",IFERROR(D106/C106,0)) -> 0 | H106: =IF($B106="","",SUMIFS(Journal!$AK$6:$AK$505,Journal!$C$6:$C$505,$B106,Journal!$BP$6:$BP$505,1)) -> 0 | I106: =IF($B106="","",IFERROR(H106/C106,0)) -> 0 | J106: =IF($B106="","",SUMIFS(Journal!$AM$6:$AM$505,Journal!$C$6:$C$505,$B106,Journal!$BP$6:$BP$505,1)) -> 0 | K106: =IF($B106="","",IFERROR(SUMIFS(Journal!$AM$6:$AM$505,Journal!$C$6:$C$505,$B106,Journal!$BP$6:$BP$505,1,Journal!$AM$6:$AM$505,">0")/ABS(SUMIFS(Journal!$AM$6:$AM$505,Journal!$C$6:$C$505,$B106,Journal!$BP$6:$BP$505,1,Journal!$AM$6:$AM$505,"<0")),"-")) -> -
B107: Sun | C107: =IF($B107="","",D107+E107+F107) -> 0 | D107: =IF($B107="","",COUNTIFS(Journal!$C$6:$C$505,$B107,Journal!$AL$6:$AL$505,"Win",Journal!$BP$6:$BP$505,1)) -> 0 | E107: =IF($B107="","",COUNTIFS(Journal!$C$6:$C$505,$B107,Journal!$AL$6:$AL$505,"Loss",Journal!$BP$6:$BP$505,1)) -> 0 | F107: =IF($B107="","",COUNTIFS(Journal!$C$6:$C$505,$B107,Journal!$AL$6:$AL$505,"BE",Journal!$BP$6:$BP$505,1)) -> 0 | G107: =IF($B107="","",IFERROR(D107/C107,0)) -> 0 | H107: =IF($B107="","",SUMIFS(Journal!$AK$6:$AK$505,Journal!$C$6:$C$505,$B107,Journal!$BP$6:$BP$505,1)) -> 0 | I107: =IF($B107="","",IFERROR(H107/C107,0)) -> 0 | J107: =IF($B107="","",SUMIFS(Journal!$AM$6:$AM$505,Journal!$C$6:$C$505,$B107,Journal!$BP$6:$BP$505,1)) -> 0 | K107: =IF($B107="","",IFERROR(SUMIFS(Journal!$AM$6:$AM$505,Journal!$C$6:$C$505,$B107,Journal!$BP$6:$BP$505,1,Journal!$AM$6:$AM$505,">0")/ABS(SUMIFS(Journal!$AM$6:$AM$505,Journal!$C$6:$C$505,$B107,Journal!$BP$6:$BP$505,1,Journal!$AM$6:$AM$505,"<0")),"-")) -> -
B110: Entry Hour (24h clock, your journal's time)
B111: Entry Hour (24h clock, your journal's time) | C111: Trades | D111: Wins | E111: Losses | F111: BE | G111: Win % | H111: Total R | I111: Avg R | J111: Net P&L ($) | K111: Profit Factor
B112: 0 | C112: =IF($B112="","",D112+E112+F112) -> 0 | D112: =IF($B112="","",COUNTIFS(Journal!$AS$6:$AS$505,$B112,Journal!$AL$6:$AL$505,"Win",Journal!$BP$6:$BP$505,1)) -> 0 | E112: =IF($B112="","",COUNTIFS(Journal!$AS$6:$AS$505,$B112,Journal!$AL$6:$AL$505,"Loss",Journal!$BP$6:$BP$505,1)) -> 0 | F112: =IF($B112="","",COUNTIFS(Journal!$AS$6:$AS$505,$B112,Journal!$AL$6:$AL$505,"BE",Journal!$BP$6:$BP$505,1)) -> 0 | G112: =IF($B112="","",IFERROR(D112/C112,0)) -> 0 | H112: =IF($B112="","",SUMIFS(Journal!$AK$6:$AK$505,Journal!$AS$6:$AS$505,$B112,Journal!$BP$6:$BP$505,1)) -> 0 | I112: =IF($B112="","",IFERROR(H112/C112,0)) -> 0 | J112: =IF($B112="","",SUMIFS(Journal!$AM$6:$AM$505,Journal!$AS$6:$AS$505,$B112,Journal!$BP$6:$BP$505,1)) -> 0 | K112: =IF($B112="","",IFERROR(SUMIFS(Journal!$AM$6:$AM$505,Journal!$AS$6:$AS$505,$B112,Journal!$BP$6:$BP$505,1,Journal!$AM$6:$AM$505,">0")/ABS(SUMIFS(Journal!$AM$6:$AM$505,Journal!$AS$6:$AS$505,$B112,Journal!$BP$6:$BP$505,1,Journal!$AM$6:$AM$505,"<0")),"-")) -> -
B113: 1 | C113: =IF($B113="","",D113+E113+F113) -> 0 | D113: =IF($B113="","",COUNTIFS(Journal!$AS$6:$AS$505,$B113,Journal!$AL$6:$AL$505,"Win",Journal!$BP$6:$BP$505,1)) -> 0 | E113: =IF($B113="","",COUNTIFS(Journal!$AS$6:$AS$505,$B113,Journal!$AL$6:$AL$505,"Loss",Journal!$BP$6:$BP$505,1)) -> 0 | F113: =IF($B113="","",COUNTIFS(Journal!$AS$6:$AS$505,$B113,Journal!$AL$6:$AL$505,"BE",Journal!$BP$6:$BP$505,1)) -> 0 | G113: =IF($B113="","",IFERROR(D113/C113,0)) -> 0 | H113: =IF($B113="","",SUMIFS(Journal!$AK$6:$AK$505,Journal!$AS$6:$AS$505,$B113,Journal!$BP$6:$BP$505,1)) -> 0 | I113: =IF($B113="","",IFERROR(H113/C113,0)) -> 0 | J113: =IF($B113="","",SUMIFS(Journal!$AM$6:$AM$505,Journal!$AS$6:$AS$505,$B113,Journal!$BP$6:$BP$505,1)) -> 0 | K113: =IF($B113="","",IFERROR(SUMIFS(Journal!$AM$6:$AM$505,Journal!$AS$6:$AS$505,$B113,Journal!$BP$6:$BP$505,1,Journal!$AM$6:$AM$505,">0")/ABS(SUMIFS(Journal!$AM$6:$AM$505,Journal!$AS$6:$AS$505,$B113,Journal!$BP$6:$BP$505,1,Journal!$AM$6:$AM$505,"<0")),"-")) -> -
B114: 2 | C114: =IF($B114="","",D114+E114+F114) -> 0 | D114: =IF($B114="","",COUNTIFS(Journal!$AS$6:$AS$505,$B114,Journal!$AL$6:$AL$505,"Win",Journal!$BP$6:$BP$505,1)) -> 0 | E114: =IF($B114="","",COUNTIFS(Journal!$AS$6:$AS$505,$B114,Journal!$AL$6:$AL$505,"Loss",Journal!$BP$6:$BP$505,1)) -> 0 | F114: =IF($B114="","",COUNTIFS(Journal!$AS$6:$AS$505,$B114,Journal!$AL$6:$AL$505,"BE",Journal!$BP$6:$BP$505,1)) -> 0 | G114: =IF($B114="","",IFERROR(D114/C114,0)) -> 0 | H114: =IF($B114="","",SUMIFS(Journal!$AK$6:$AK$505,Journal!$AS$6:$AS$505,$B114,Journal!$BP$6:$BP$505,1)) -> 0 | I114: =IF($B114="","",IFERROR(H114/C114,0)) -> 0 | J114: =IF($B114="","",SUMIFS(Journal!$AM$6:$AM$505,Journal!$AS$6:$AS$505,$B114,Journal!$BP$6:$BP$505,1)) -> 0 | K114: =IF($B114="","",IFERROR(SUMIFS(Journal!$AM$6:$AM$505,Journal!$AS$6:$AS$505,$B114,Journal!$BP$6:$BP$505,1,Journal!$AM$6:$AM$505,">0")/ABS(SUMIFS(Journal!$AM$6:$AM$505,Journal!$AS$6:$AS$505,$B114,Journal!$BP$6:$BP$505,1,Journal!$AM$6:$AM$505,"<0")),"-")) -> -
B115: 3 | C115: =IF($B115="","",D115+E115+F115) -> 0 | D115: =IF($B115="","",COUNTIFS(Journal!$AS$6:$AS$505,$B115,Journal!$AL$6:$AL$505,"Win",Journal!$BP$6:$BP$505,1)) -> 0 | E115: =IF($B115="","",COUNTIFS(Journal!$AS$6:$AS$505,$B115,Journal!$AL$6:$AL$505,"Loss",Journal!$BP$6:$BP$505,1)) -> 0 | F115: =IF($B115="","",COUNTIFS(Journal!$AS$6:$AS$505,$B115,Journal!$AL$6:$AL$505,"BE",Journal!$BP$6:$BP$505,1)) -> 0 | G115: =IF($B115="","",IFERROR(D115/C115,0)) -> 0 | H115: =IF($B115="","",SUMIFS(Journal!$AK$6:$AK$505,Journal!$AS$6:$AS$505,$B115,Journal!$BP$6:$BP$505,1)) -> 0 | I115: =IF($B115="","",IFERROR(H115/C115,0)) -> 0 | J115: =IF($B115="","",SUMIFS(Journal!$AM$6:$AM$505,Journal!$AS$6:$AS$505,$B115,Journal!$BP$6:$BP$505,1)) -> 0 | K115: =IF($B115="","",IFERROR(SUMIFS(Journal!$AM$6:$AM$505,Journal!$AS$6:$AS$505,$B115,Journal!$BP$6:$BP$505,1,Journal!$AM$6:$AM$505,">0")/ABS(SUMIFS(Journal!$AM$6:$AM$505,Journal!$AS$6:$AS$505,$B115,Journal!$BP$6:$BP$505,1,Journal!$AM$6:$AM$505,"<0")),"-")) -> -
B116: 4 | C116: =IF($B116="","",D116+E116+F116) -> 0 | D116: =IF($B116="","",COUNTIFS(Journal!$AS$6:$AS$505,$B116,Journal!$AL$6:$AL$505,"Win",Journal!$BP$6:$BP$505,1)) -> 0 | E116: =IF($B116="","",COUNTIFS(Journal!$AS$6:$AS$505,$B116,Journal!$AL$6:$AL$505,"Loss",Journal!$BP$6:$BP$505,1)) -> 0 | F116: =IF($B116="","",COUNTIFS(Journal!$AS$6:$AS$505,$B116,Journal!$AL$6:$AL$505,"BE",Journal!$BP$6:$BP$505,1)) -> 0 | G116: =IF($B116="","",IFERROR(D116/C116,0)) -> 0 | H116: =IF($B116="","",SUMIFS(Journal!$AK$6:$AK$505,Journal!$AS$6:$AS$505,$B116,Journal!$BP$6:$BP$505,1)) -> 0 | I116: =IF($B116="","",IFERROR(H116/C116,0)) -> 0 | J116: =IF($B116="","",SUMIFS(Journal!$AM$6:$AM$505,Journal!$AS$6:$AS$505,$B116,Journal!$BP$6:$BP$505,1)) -> 0 | K116: =IF($B116="","",IFERROR(SUMIFS(Journal!$AM$6:$AM$505,Journal!$AS$6:$AS$505,$B116,Journal!$BP$6:$BP$505,1,Journal!$AM$6:$AM$505,">0")/ABS(SUMIFS(Journal!$AM$6:$AM$505,Journal!$AS$6:$AS$505,$B116,Journal!$BP$6:$BP$505,1,Journal!$AM$6:$AM$505,"<0")),"-")) -> -
B117: 5 | C117: =IF($B117="","",D117+E117+F117) -> 0 | D117: =IF($B117="","",COUNTIFS(Journal!$AS$6:$AS$505,$B117,Journal!$AL$6:$AL$505,"Win",Journal!$BP$6:$BP$505,1)) -> 0 | E117: =IF($B117="","",COUNTIFS(Journal!$AS$6:$AS$505,$B117,Journal!$AL$6:$AL$505,"Loss",Journal!$BP$6:$BP$505,1)) -> 0 | F117: =IF($B117="","",COUNTIFS(Journal!$AS$6:$AS$505,$B117,Journal!$AL$6:$AL$505,"BE",Journal!$BP$6:$BP$505,1)) -> 0 | G117: =IF($B117="","",IFERROR(D117/C117,0)) -> 0 | H117: =IF($B117="","",SUMIFS(Journal!$AK$6:$AK$505,Journal!$AS$6:$AS$505,$B117,Journal!$BP$6:$BP$505,1)) -> 0 | I117: =IF($B117="","",IFERROR(H117/C117,0)) -> 0 | J117: =IF($B117="","",SUMIFS(Journal!$AM$6:$AM$505,Journal!$AS$6:$AS$505,$B117,Journal!$BP$6:$BP$505,1)) -> 0 | K117: =IF($B117="","",IFERROR(SUMIFS(Journal!$AM$6:$AM$505,Journal!$AS$6:$AS$505,$B117,Journal!$BP$6:$BP$505,1,Journal!$AM$6:$AM$505,">0")/ABS(SUMIFS(Journal!$AM$6:$AM$505,Journal!$AS$6:$AS$505,$B117,Journal!$BP$6:$BP$505,1,Journal!$AM$6:$AM$505,"<0")),"-")) -> -
B118: 6 | C118: =IF($B118="","",D118+E118+F118) -> 0 | D118: =IF($B118="","",COUNTIFS(Journal!$AS$6:$AS$505,$B118,Journal!$AL$6:$AL$505,"Win",Journal!$BP$6:$BP$505,1)) -> 0 | E118: =IF($B118="","",COUNTIFS(Journal!$AS$6:$AS$505,$B118,Journal!$AL$6:$AL$505,"Loss",Journal!$BP$6:$BP$505,1)) -> 0 | F118: =IF($B118="","",COUNTIFS(Journal!$AS$6:$AS$505,$B118,Journal!$AL$6:$AL$505,"BE",Journal!$BP$6:$BP$505,1)) -> 0 | G118: =IF($B118="","",IFERROR(D118/C118,0)) -> 0 | H118: =IF($B118="","",SUMIFS(Journal!$AK$6:$AK$505,Journal!$AS$6:$AS$505,$B118,Journal!$BP$6:$BP$505,1)) -> 0 | I118: =IF($B118="","",IFERROR(H118/C118,0)) -> 0 | J118: =IF($B118="","",SUMIFS(Journal!$AM$6:$AM$505,Journal!$AS$6:$AS$505,$B118,Journal!$BP$6:$BP$505,1)) -> 0 | K118: =IF($B118="","",IFERROR(SUMIFS(Journal!$AM$6:$AM$505,Journal!$AS$6:$AS$505,$B118,Journal!$BP$6:$BP$505,1,Journal!$AM$6:$AM$505,">0")/ABS(SUMIFS(Journal!$AM$6:$AM$505,Journal!$AS$6:$AS$505,$B118,Journal!$BP$6:$BP$505,1,Journal!$AM$6:$AM$505,"<0")),"-")) -> -
B119: 7 | C119: =IF($B119="","",D119+E119+F119) -> 0 | D119: =IF($B119="","",COUNTIFS(Journal!$AS$6:$AS$505,$B119,Journal!$AL$6:$AL$505,"Win",Journal!$BP$6:$BP$505,1)) -> 0 | E119: =IF($B119="","",COUNTIFS(Journal!$AS$6:$AS$505,$B119,Journal!$AL$6:$AL$505,"Loss",Journal!$BP$6:$BP$505,1)) -> 0 | F119: =IF($B119="","",COUNTIFS(Journal!$AS$6:$AS$505,$B119,Journal!$AL$6:$AL$505,"BE",Journal!$BP$6:$BP$505,1)) -> 0 | G119: =IF($B119="","",IFERROR(D119/C119,0)) -> 0 | H119: =IF($B119="","",SUMIFS(Journal!$AK$6:$AK$505,Journal!$AS$6:$AS$505,$B119,Journal!$BP$6:$BP$505,1)) -> 0 | I119: =IF($B119="","",IFERROR(H119/C119,0)) -> 0 | J119: =IF($B119="","",SUMIFS(Journal!$AM$6:$AM$505,Journal!$AS$6:$AS$505,$B119,Journal!$BP$6:$BP$505,1)) -> 0 | K119: =IF($B119="","",IFERROR(SUMIFS(Journal!$AM$6:$AM$505,Journal!$AS$6:$AS$505,$B119,Journal!$BP$6:$BP$505,1,Journal!$AM$6:$AM$505,">0")/ABS(SUMIFS(Journal!$AM$6:$AM$505,Journal!$AS$6:$AS$505,$B119,Journal!$BP$6:$BP$505,1,Journal!$AM$6:$AM$505,"<0")),"-")) -> -
B120: 8 | C120: =IF($B120="","",D120+E120+F120) -> 1 | D120: =IF($B120="","",COUNTIFS(Journal!$AS$6:$AS$505,$B120,Journal!$AL$6:$AL$505,"Win",Journal!$BP$6:$BP$505,1)) -> 1 | E120: =IF($B120="","",COUNTIFS(Journal!$AS$6:$AS$505,$B120,Journal!$AL$6:$AL$505,"Loss",Journal!$BP$6:$BP$505,1)) -> 0 | F120: =IF($B120="","",COUNTIFS(Journal!$AS$6:$AS$505,$B120,Journal!$AL$6:$AL$505,"BE",Journal!$BP$6:$BP$505,1)) -> 0 | G120: =IF($B120="","",IFERROR(D120/C120,0)) -> 1 | H120: =IF($B120="","",SUMIFS(Journal!$AK$6:$AK$505,Journal!$AS$6:$AS$505,$B120,Journal!$BP$6:$BP$505,1)) -> 2.33 | I120: =IF($B120="","",IFERROR(H120/C120,0)) -> 2.33 | J120: =IF($B120="","",SUMIFS(Journal!$AM$6:$AM$505,Journal!$AS$6:$AS$505,$B120,Journal!$BP$6:$BP$505,1)) -> 229.5 | K120: =IF($B120="","",IFERROR(SUMIFS(Journal!$AM$6:$AM$505,Journal!$AS$6:$AS$505,$B120,Journal!$BP$6:$BP$505,1,Journal!$AM$6:$AM$505,">0")/ABS(SUMIFS(Journal!$AM$6:$AM$505,Journal!$AS$6:$AS$505,$B120,Journal!$BP$6:$BP$505,1,Journal!$AM$6:$AM$505,"<0")),"-")) -> -
...

Sheet Weekly Review
B1: WEEKLY REVIEW
B2: Numbers fill in from the Journal (Account View applies). Write your reflections in the blue cells.
B5: Week # | C5: Week Start (Mon) | D5: Week End | E5: Trades | F5: Wins | G5: Losses | H5: BE | I5: Win % | J5: Net R | K5: Net P&L ($) | L5: Rule Breaches | M5: Plan Adherence | N5: What went well | O5: What to improve | P5: Next week's plan
B6: 1 | C6: =Settings!$C$7-WEEKDAY(Settings!$C$7,2)+1+7*(B6-1) -> 46293 | D6: =C6+6 -> 46299 | E6: =F6+G6+H6 -> 1 | F6: =COUNTIFS(Journal!$B$6:$B$505,">="&$C6,Journal!$B$6:$B$505,"<"&($C6+7),Journal!$BP$6:$BP$505,1,Journal!$AL$6:$AL$505,"Win") -> 1 | G6: =COUNTIFS(Journal!$B$6:$B$505,">="&$C6,Journal!$B$6:$B$505,"<"&($C6+7),Journal!$BP$6:$BP$505,1,Journal!$AL$6:$AL$505,"Loss") -> 0 | H6: =COUNTIFS(Journal!$B$6:$B$505,">="&$C6,Journal!$B$6:$B$505,"<"&($C6+7),Journal!$BP$6:$BP$505,1,Journal!$AL$6:$AL$505,"BE") -> 0 | I6: =IF(E6=0,"",F6/E6) -> 1 | J6: =IF(E6=0,"",SUMIFS(Journal!$AK$6:$AK$505,Journal!$B$6:$B$505,">="&$C6,Journal!$B$6:$B$505,"<"&($C6+7),Journal!$BP$6:$BP$505,1)) -> 2.33 | K6: =IF(E6=0,"",SUMIFS(Journal!$AM$6:$AM$505,Journal!$B$6:$B$505,">="&$C6,Journal!$B$6:$B$505,"<"&($C6+7),Journal!$BP$6:$BP$505,1)) -> 229.5 | L6: =COUNTIFS(Journal!$B$6:$B$505,">="&$C6,Journal!$B$6:$B$505,"<"&($C6+7),Journal!$BP$6:$BP$505,1,Journal!$BB$6:$BB$505,"Oversized")+COUNTIFS(Journal!$B$6:$B$505,">="&$C6,Journal!$B$6:$B$505,"<"&($C6+7),Journal!$BP$6:$BP$505,1,Journal!$BB$6:$BB$505,"Overtraded")+COUNTIFS(Journal!$B$6:$B$505,">="&$C6,Journal!$B$6:$B$505,"<"&($C6+7),Journal!$BP$6:$BP$505,1,Journal!$BB$6:$BB$505,"Daily loss hit")+COUNTIFS(Journal!$B$6:$B$505,">="&$C6,Journal!$B$6:$B$505,"<"&($C6+7),Journal!$BP$6:$BP$505,1,Journal!$BB$6:$BB$505,"Weekly loss hit") -> 0 | M6: =IFERROR(COUNTIFS(Journal!$B$6:$B$505,">="&$C6,Journal!$B$6:$B$505,"<"&($C6+7),Journal!$BP$6:$BP$505,1,Journal!$BD$6:$BD$505,"Yes")/(COUNTIFS(Journal!$B$6:$B$505,">="&$C6,Journal!$B$6:$B$505,"<"&($C6+7),Journal!$BP$6:$BP$505,1,Journal!$BD$6:$BD$505,"Yes")+COUNTIFS(Journal!$B$6:$B$505,">="&$C6,Journal!$B$6:$B$505,"<"&($C6+7),Journal!$BP$6:$BP$505,1,Journal!$BD$6:$BD$505,"No")),"") -> 1
B7: 2 | C7: =Settings!$C$7-WEEKDAY(Settings!$C$7,2)+1+7*(B7-1) -> 46300 | D7: =C7+6 -> 46306 | E7: =F7+G7+H7 -> 0 | F7: =COUNTIFS(Journal!$B$6:$B$505,">="&$C7,Journal!$B$6:$B$505,"<"&($C7+7),Journal!$BP$6:$BP$505,1,Journal!$AL$6:$AL$505,"Win") -> 0 | G7: =COUNTIFS(Journal!$B$6:$B$505,">="&$C7,Journal!$B$6:$B$505,"<"&($C7+7),Journal!$BP$6:$BP$505,1,Journal!$AL$6:$AL$505,"Loss") -> 0 | H7: =COUNTIFS(Journal!$B$6:$B$505,">="&$C7,Journal!$B$6:$B$505,"<"&($C7+7),Journal!$BP$6:$BP$505,1,Journal!$AL$6:$AL$505,"BE") -> 0 | I7: =IF(E7=0,"",F7/E7) | J7: =IF(E7=0,"",SUMIFS(Journal!$AK$6:$AK$505,Journal!$B$6:$B$505,">="&$C7,Journal!$B$6:$B$505,"<"&($C7+7),Journal!$BP$6:$BP$505,1)) | K7: =IF(E7=0,"",SUMIFS(Journal!$AM$6:$AM$505,Journal!$B$6:$B$505,">="&$C7,Journal!$B$6:$B$505,"<"&($C7+7),Journal!$BP$6:$BP$505,1)) | L7: =COUNTIFS(Journal!$B$6:$B$505,">="&$C7,Journal!$B$6:$B$505,"<"&($C7+7),Journal!$BP$6:$BP$505,1,Journal!$BB$6:$BB$505,"Oversized")+COUNTIFS(Journal!$B$6:$B$505,">="&$C7,Journal!$B$6:$B$505,"<"&($C7+7),Journal!$BP$6:$BP$505,1,Journal!$BB$6:$BB$505,"Overtraded")+COUNTIFS(Journal!$B$6:$B$505,">="&$C7,Journal!$B$6:$B$505,"<"&($C7+7),Journal!$BP$6:$BP$505,1,Journal!$BB$6:$BB$505,"Daily loss hit")+COUNTIFS(Journal!$B$6:$B$505,">="&$C7,Journal!$B$6:$B$505,"<"&($C7+7),Journal!$BP$6:$BP$505,1,Journal!$BB$6:$BB$505,"Weekly loss hit") -> 0 | M7: =IFERROR(COUNTIFS(Journal!$B$6:$B$505,">="&$C7,Journal!$B$6:$B$505,"<"&($C7+7),Journal!$BP$6:$BP$505,1,Journal!$BD$6:$BD$505,"Yes")/(COUNTIFS(Journal!$B$6:$B$505,">="&$C7,Journal!$B$6:$B$505,"<"&($C7+7),Journal!$BP$6:$BP$505,1,Journal!$BD$6:$BD$505,"Yes")+COUNTIFS(Journal!$B$6:$B$505,">="&$C7,Journal!$B$6:$B$505,"<"&($C7+7),Journal!$BP$6:$BP$505,1,Journal!$BD$6:$BD$505,"No")),"")
B8: 3 | C8: =Settings!$C$7-WEEKDAY(Settings!$C$7,2)+1+7*(B8-1) -> 46307 | D8: =C8+6 -> 46313 | E8: =F8+G8+H8 -> 0 | F8: =COUNTIFS(Journal!$B$6:$B$505,">="&$C8,Journal!$B$6:$B$505,"<"&($C8+7),Journal!$BP$6:$BP$505,1,Journal!$AL$6:$AL$505,"Win") -> 0 | G8: =COUNTIFS(Journal!$B$6:$B$505,">="&$C8,Journal!$B$6:$B$505,"<"&($C8+7),Journal!$BP$6:$BP$505,1,Journal!$AL$6:$AL$505,"Loss") -> 0 | H8: =COUNTIFS(Journal!$B$6:$B$505,">="&$C8,Journal!$B$6:$B$505,"<"&($C8+7),Journal!$BP$6:$BP$505,1,Journal!$AL$6:$AL$505,"BE") -> 0 | I8: =IF(E8=0,"",F8/E8) | J8: =IF(E8=0,"",SUMIFS(Journal!$AK$6:$AK$505,Journal!$B$6:$B$505,">="&$C8,Journal!$B$6:$B$505,"<"&($C8+7),Journal!$BP$6:$BP$505,1)) | K8: =IF(E8=0,"",SUMIFS(Journal!$AM$6:$AM$505,Journal!$B$6:$B$505,">="&$C8,Journal!$B$6:$B$505,"<"&($C8+7),Journal!$BP$6:$BP$505,1)) | L8: =COUNTIFS(Journal!$B$6:$B$505,">="&$C8,Journal!$B$6:$B$505,"<"&($C8+7),Journal!$BP$6:$BP$505,1,Journal!$BB$6:$BB$505,"Oversized")+COUNTIFS(Journal!$B$6:$B$505,">="&$C8,Journal!$B$6:$B$505,"<"&($C8+7),Journal!$BP$6:$BP$505,1,Journal!$BB$6:$BB$505,"Overtraded")+COUNTIFS(Journal!$B$6:$B$505,">="&$C8,Journal!$B$6:$B$505,"<"&($C8+7),Journal!$BP$6:$BP$505,1,Journal!$BB$6:$BB$505,"Daily loss hit")+COUNTIFS(Journal!$B$6:$B$505,">="&$C8,Journal!$B$6:$B$505,"<"&($C8+7),Journal!$BP$6:$BP$505,1,Journal!$BB$6:$BB$505,"Weekly loss hit") -> 0 | M8: =IFERROR(COUNTIFS(Journal!$B$6:$B$505,">="&$C8,Journal!$B$6:$B$505,"<"&($C8+7),Journal!$BP$6:$BP$505,1,Journal!$BD$6:$BD$505,"Yes")/(COUNTIFS(Journal!$B$6:$B$505,">="&$C8,Journal!$B$6:$B$505,"<"&($C8+7),Journal!$BP$6:$BP$505,1,Journal!$BD$6:$BD$505,"Yes")+COUNTIFS(Journal!$B$6:$B$505,">="&$C8,Journal!$B$6:$B$505,"<"&($C8+7),Journal!$BP$6:$BP$505,1,Journal!$BD$6:$BD$505,"No")),"")
B9: 4 | C9: =Settings!$C$7-WEEKDAY(Settings!$C$7,2)+1+7*(B9-1) -> 46314 | D9: =C9+6 -> 46320 | E9: =F9+G9+H9 -> 0 | F9: =COUNTIFS(Journal!$B$6:$B$505,">="&$C9,Journal!$B$6:$B$505,"<"&($C9+7),Journal!$BP$6:$BP$505,1,Journal!$AL$6:$AL$505,"Win") -> 0 | G9: =COUNTIFS(Journal!$B$6:$B$505,">="&$C9,Journal!$B$6:$B$505,"<"&($C9+7),Journal!$BP$6:$BP$505,1,Journal!$AL$6:$AL$505,"Loss") -> 0 | H9: =COUNTIFS(Journal!$B$6:$B$505,">="&$C9,Journal!$B$6:$B$505,"<"&($C9+7),Journal!$BP$6:$BP$505,1,Journal!$AL$6:$AL$505,"BE") -> 0 | I9: =IF(E9=0,"",F9/E9) | J9: =IF(E9=0,"",SUMIFS(Journal!$AK$6:$AK$505,Journal!$B$6:$B$505,">="&$C9,Journal!$B$6:$B$505,"<"&($C9+7),Journal!$BP$6:$BP$505,1)) | K9: =IF(E9=0,"",SUMIFS(Journal!$AM$6:$AM$505,Journal!$B$6:$B$505,">="&$C9,Journal!$B$6:$B$505,"<"&($C9+7),Journal!$BP$6:$BP$505,1)) | L9: =COUNTIFS(Journal!$B$6:$B$505,">="&$C9,Journal!$B$6:$B$505,"<"&($C9+7),Journal!$BP$6:$BP$505,1,Journal!$BB$6:$BB$505,"Oversized")+COUNTIFS(Journal!$B$6:$B$505,">="&$C9,Journal!$B$6:$B$505,"<"&($C9+7),Journal!$BP$6:$BP$505,1,Journal!$BB$6:$BB$505,"Overtraded")+COUNTIFS(Journal!$B$6:$B$505,">="&$C9,Journal!$B$6:$B$505,"<"&($C9+7),Journal!$BP$6:$BP$505,1,Journal!$BB$6:$BB$505,"Daily loss hit")+COUNTIFS(Journal!$B$6:$B$505,">="&$C9,Journal!$B$6:$B$505,"<"&($C9+7),Journal!$BP$6:$BP$505,1,Journal!$BB$6:$BB$505,"Weekly loss hit") -> 0 | M9: =IFERROR(COUNTIFS(Journal!$B$6:$B$505,">="&$C9,Journal!$B$6:$B$505,"<"&($C9+7),Journal!$BP$6:$BP$505,1,Journal!$BD$6:$BD$505,"Yes")/(COUNTIFS(Journal!$B$6:$B$505,">="&$C9,Journal!$B$6:$B$505,"<"&($C9+7),Journal!$BP$6:$BP$505,1,Journal!$BD$6:$BD$505,"Yes")+COUNTIFS(Journal!$B$6:$B$505,">="&$C9,Journal!$B$6:$B$505,"<"&($C9+7),Journal!$BP$6:$BP$505,1,Journal!$BD$6:$BD$505,"No")),"")
B10: 5 | C10: =Settings!$C$7-WEEKDAY(Settings!$C$7,2)+1+7*(B10-1) -> 46321 | D10: =C10+6 -> 46327 | E10: =F10+G10+H10 -> 0 | F10: =COUNTIFS(Journal!$B$6:$B$505,">="&$C10,Journal!$B$6:$B$505,"<"&($C10+7),Journal!$BP$6:$BP$505,1,Journal!$AL$6:$AL$505,"Win") -> 0 | G10: =COUNTIFS(Journal!$B$6:$B$505,">="&$C10,Journal!$B$6:$B$505,"<"&($C10+7),Journal!$BP$6:$BP$505,1,Journal!$AL$6:$AL$505,"Loss") -> 0 | H10: =COUNTIFS(Journal!$B$6:$B$505,">="&$C10,Journal!$B$6:$B$505,"<"&($C10+7),Journal!$BP$6:$BP$505,1,Journal!$AL$6:$AL$505,"BE") -> 0 | I10: =IF(E10=0,"",F10/E10) | J10: =IF(E10=0,"",SUMIFS(Journal!$AK$6:$AK$505,Journal!$B$6:$B$505,">="&$C10,Journal!$B$6:$B$505,"<"&($C10+7),Journal!$BP$6:$BP$505,1)) | K10: =IF(E10=0,"",SUMIFS(Journal!$AM$6:$AM$505,Journal!$B$6:$B$505,">="&$C10,Journal!$B$6:$B$505,"<"&($C10+7),Journal!$BP$6:$BP$505,1)) | L10: =COUNTIFS(Journal!$B$6:$B$505,">="&$C10,Journal!$B$6:$B$505,"<"&($C10+7),Journal!$BP$6:$BP$505,1,Journal!$BB$6:$BB$505,"Oversized")+COUNTIFS(Journal!$B$6:$B$505,">="&$C10,Journal!$B$6:$B$505,"<"&($C10+7),Journal!$BP$6:$BP$505,1,Journal!$BB$6:$BB$505,"Overtraded")+COUNTIFS(Journal!$B$6:$B$505,">="&$C10,Journal!$B$6:$B$505,"<"&($C10+7),Journal!$BP$6:$BP$505,1,Journal!$BB$6:$BB$505,"Daily loss hit")+COUNTIFS(Journal!$B$6:$B$505,">="&$C10,Journal!$B$6:$B$505,"<"&($C10+7),Journal!$BP$6:$BP$505,1,Journal!$BB$6:$BB$505,"Weekly loss hit") -> 0 | M10: =IFERROR(COUNTIFS(Journal!$B$6:$B$505,">="&$C10,Journal!$B$6:$B$505,"<"&($C10+7),Journal!$BP$6:$BP$505,1,Journal!$BD$6:$BD$505,"Yes")/(COUNTIFS(Journal!$B$6:$B$505,">="&$C10,Journal!$B$6:$B$505,"<"&($C10+7),Journal!$BP$6:$BP$505,1,Journal!$BD$6:$BD$505,"Yes")+COUNTIFS(Journal!$B$6:$B$505,">="&$C10,Journal!$B$6:$B$505,"<"&($C10+7),Journal!$BP$6:$BP$505,1,Journal!$BD$6:$BD$505,"No")),"")
B11: 6 | C11: =Settings!$C$7-WEEKDAY(Settings!$C$7,2)+1+7*(B11-1) -> 46328 | D11: =C11+6 -> 46334 | E11: =F11+G11+H11 -> 0 | F11: =COUNTIFS(Journal!$B$6:$B$505,">="&$C11,Journal!$B$6:$B$505,"<"&($C11+7),Journal!$BP$6:$BP$505,1,Journal!$AL$6:$AL$505,"Win") -> 0 | G11: =COUNTIFS(Journal!$B$6:$B$505,">="&$C11,Journal!$B$6:$B$505,"<"&($C11+7),Journal!$BP$6:$BP$505,1,Journal!$AL$6:$AL$505,"Loss") -> 0 | H11: =COUNTIFS(Journal!$B$6:$B$505,">="&$C11,Journal!$B$6:$B$505,"<"&($C11+7),Journal!$BP$6:$BP$505,1,Journal!$AL$6:$AL$505,"BE") -> 0 | I11: =IF(E11=0,"",F11/E11) | J11: =IF(E11=0,"",SUMIFS(Journal!$AK$6:$AK$505,Journal!$B$6:$B$505,">="&$C11,Journal!$B$6:$B$505,"<"&($C11+7),Journal!$BP$6:$BP$505,1)) | K11: =IF(E11=0,"",SUMIFS(Journal!$AM$6:$AM$505,Journal!$B$6:$B$505,">="&$C11,Journal!$B$6:$B$505,"<"&($C11+7),Journal!$BP$6:$BP$505,1)) | L11: =COUNTIFS(Journal!$B$6:$B$505,">="&$C11,Journal!$B$6:$B$505,"<"&($C11+7),Journal!$BP$6:$BP$505,1,Journal!$BB$6:$BB$505,"Oversized")+COUNTIFS(Journal!$B$6:$B$505,">="&$C11,Journal!$B$6:$B$505,"<"&($C11+7),Journal!$BP$6:$BP$505,1,Journal!$BB$6:$BB$505,"Overtraded")+COUNTIFS(Journal!$B$6:$B$505,">="&$C11,Journal!$B$6:$B$505,"<"&($C11+7),Journal!$BP$6:$BP$505,1,Journal!$BB$6:$BB$505,"Daily loss hit")+COUNTIFS(Journal!$B$6:$B$505,">="&$C11,Journal!$B$6:$B$505,"<"&($C11+7),Journal!$BP$6:$BP$505,1,Journal!$BB$6:$BB$505,"Weekly loss hit") -> 0 | M11: =IFERROR(COUNTIFS(Journal!$B$6:$B$505,">="&$C11,Journal!$B$6:$B$505,"<"&($C11+7),Journal!$BP$6:$BP$505,1,Journal!$BD$6:$BD$505,"Yes")/(COUNTIFS(Journal!$B$6:$B$505,">="&$C11,Journal!$B$6:$B$505,"<"&($C11+7),Journal!$BP$6:$BP$505,1,Journal!$BD$6:$BD$505,"Yes")+COUNTIFS(Journal!$B$6:$B$505,">="&$C11,Journal!$B$6:$B$505,"<"&($C11+7),Journal!$BP$6:$BP$505,1,Journal!$BD$6:$BD$505,"No")),"")
B12: 7 | C12: =Settings!$C$7-WEEKDAY(Settings!$C$7,2)+1+7*(B12-1) -> 46335 | D12: =C12+6 -> 46341 | E12: =F12+G12+H12 -> 0 | F12: =COUNTIFS(Journal!$B$6:$B$505,">="&$C12,Journal!$B$6:$B$505,"<"&($C12+7),Journal!$BP$6:$BP$505,1,Journal!$AL$6:$AL$505,"Win") -> 0 | G12: =COUNTIFS(Journal!$B$6:$B$505,">="&$C12,Journal!$B$6:$B$505,"<"&($C12+7),Journal!$BP$6:$BP$505,1,Journal!$AL$6:$AL$505,"Loss") -> 0 | H12: =COUNTIFS(Journal!$B$6:$B$505,">="&$C12,Journal!$B$6:$B$505,"<"&($C12+7),Journal!$BP$6:$BP$505,1,Journal!$AL$6:$AL$505,"BE") -> 0 | I12: =IF(E12=0,"",F12/E12) | J12: =IF(E12=0,"",SUMIFS(Journal!$AK$6:$AK$505,Journal!$B$6:$B$505,">="&$C12,Journal!$B$6:$B$505,"<"&($C12+7),Journal!$BP$6:$BP$505,1)) | K12: =IF(E12=0,"",SUMIFS(Journal!$AM$6:$AM$505,Journal!$B$6:$B$505,">="&$C12,Journal!$B$6:$B$505,"<"&($C12+7),Journal!$BP$6:$BP$505,1)) | L12: =COUNTIFS(Journal!$B$6:$B$505,">="&$C12,Journal!$B$6:$B$505,"<"&($C12+7),Journal!$BP$6:$BP$505,1,Journal!$BB$6:$BB$505,"Oversized")+COUNTIFS(Journal!$B$6:$B$505,">="&$C12,Journal!$B$6:$B$505,"<"&($C12+7),Journal!$BP$6:$BP$505,1,Journal!$BB$6:$BB$505,"Overtraded")+COUNTIFS(Journal!$B$6:$B$505,">="&$C12,Journal!$B$6:$B$505,"<"&($C12+7),Journal!$BP$6:$BP$505,1,Journal!$BB$6:$BB$505,"Daily loss hit")+COUNTIFS(Journal!$B$6:$B$505,">="&$C12,Journal!$B$6:$B$505,"<"&($C12+7),Journal!$BP$6:$BP$505,1,Journal!$BB$6:$BB$505,"Weekly loss hit") -> 0 | M12: =IFERROR(COUNTIFS(Journal!$B$6:$B$505,">="&$C12,Journal!$B$6:$B$505,"<"&($C12+7),Journal!$BP$6:$BP$505,1,Journal!$BD$6:$BD$505,"Yes")/(COUNTIFS(Journal!$B$6:$B$505,">="&$C12,Journal!$B$6:$B$505,"<"&($C12+7),Journal!$BP$6:$BP$505,1,Journal!$BD$6:$BD$505,"Yes")+COUNTIFS(Journal!$B$6:$B$505,">="&$C12,Journal!$B$6:$B$505,"<"&($C12+7),Journal!$BP$6:$BP$505,1,Journal!$BD$6:$BD$505,"No")),"")
B13: 8 | C13: =Settings!$C$7-WEEKDAY(Settings!$C$7,2)+1+7*(B13-1) -> 46342 | D13: =C13+6 -> 46348 | E13: =F13+G13+H13 -> 0 | F13: =COUNTIFS(Journal!$B$6:$B$505,">="&$C13,Journal!$B$6:$B$505,"<"&($C13+7),Journal!$BP$6:$BP$505,1,Journal!$AL$6:$AL$505,"Win") -> 0 | G13: =COUNTIFS(Journal!$B$6:$B$505,">="&$C13,Journal!$B$6:$B$505,"<"&($C13+7),Journal!$BP$6:$BP$505,1,Journal!$AL$6:$AL$505,"Loss") -> 0 | H13: =COUNTIFS(Journal!$B$6:$B$505,">="&$C13,Journal!$B$6:$B$505,"<"&($C13+7),Journal!$BP$6:$BP$505,1,Journal!$AL$6:$AL$505,"BE") -> 0 | I13: =IF(E13=0,"",F13/E13) | J13: =IF(E13=0,"",SUMIFS(Journal!$AK$6:$AK$505,Journal!$B$6:$B$505,">="&$C13,Journal!$B$6:$B$505,"<"&($C13+7),Journal!$BP$6:$BP$505,1)) | K13: =IF(E13=0,"",SUMIFS(Journal!$AM$6:$AM$505,Journal!$B$6:$B$505,">="&$C13,Journal!$B$6:$B$505,"<"&($C13+7),Journal!$BP$6:$BP$505,1)) | L13: =COUNTIFS(Journal!$B$6:$B$505,">="&$C13,Journal!$B$6:$B$505,"<"&($C13+7),Journal!$BP$6:$BP$505,1,Journal!$BB$6:$BB$505,"Oversized")+COUNTIFS(Journal!$B$6:$B$505,">="&$C13,Journal!$B$6:$B$505,"<"&($C13+7),Journal!$BP$6:$BP$505,1,Journal!$BB$6:$BB$505,"Overtraded")+COUNTIFS(Journal!$B$6:$B$505,">="&$C13,Journal!$B$6:$B$505,"<"&($C13+7),Journal!$BP$6:$BP$505,1,Journal!$BB$6:$BB$505,"Daily loss hit")+COUNTIFS(Journal!$B$6:$B$505,">="&$C13,Journal!$B$6:$B$505,"<"&($C13+7),Journal!$BP$6:$BP$505,1,Journal!$BB$6:$BB$505,"Weekly loss hit") -> 0 | M13: =IFERROR(COUNTIFS(Journal!$B$6:$B$505,">="&$C13,Journal!$B$6:$B$505,"<"&($C13+7),Journal!$BP$6:$BP$505,1,Journal!$BD$6:$BD$505,"Yes")/(COUNTIFS(Journal!$B$6:$B$505,">="&$C13,Journal!$B$6:$B$505,"<"&($C13+7),Journal!$BP$6:$BP$505,1,Journal!$BD$6:$BD$505,"Yes")+COUNTIFS(Journal!$B$6:$B$505,">="&$C13,Journal!$B$6:$B$505,"<"&($C13+7),Journal!$BP$6:$BP$505,1,Journal!$BD$6:$BD$505,"No")),"")
B14: 9 | C14: =Settings!$C$7-WEEKDAY(Settings!$C$7,2)+1+7*(B14-1) -> 46349 | D14: =C14+6 -> 46355 | E14: =F14+G14+H14 -> 0 | F14: =COUNTIFS(Journal!$B$6:$B$505,">="&$C14,Journal!$B$6:$B$505,"<"&($C14+7),Journal!$BP$6:$BP$505,1,Journal!$AL$6:$AL$505,"Win") -> 0 | G14: =COUNTIFS(Journal!$B$6:$B$505,">="&$C14,Journal!$B$6:$B$505,"<"&($C14+7),Journal!$BP$6:$BP$505,1,Journal!$AL$6:$AL$505,"Loss") -> 0 | H14: =COUNTIFS(Journal!$B$6:$B$505,">="&$C14,Journal!$B$6:$B$505,"<"&($C14+7),Journal!$BP$6:$BP$505,1,Journal!$AL$6:$AL$505,"BE") -> 0 | I14: =IF(E14=0,"",F14/E14) | J14: =IF(E14=0,"",SUMIFS(Journal!$AK$6:$AK$505,Journal!$B$6:$B$505,">="&$C14,Journal!$B$6:$B$505,"<"&($C14+7),Journal!$BP$6:$BP$505,1)) | K14: =IF(E14=0,"",SUMIFS(Journal!$AM$6:$AM$505,Journal!$B$6:$B$505,">="&$C14,Journal!$B$6:$B$505,"<"&($C14+7),Journal!$BP$6:$BP$505,1)) | L14: =COUNTIFS(Journal!$B$6:$B$505,">="&$C14,Journal!$B$6:$B$505,"<"&($C14+7),Journal!$BP$6:$BP$505,1,Journal!$BB$6:$BB$505,"Oversized")+COUNTIFS(Journal!$B$6:$B$505,">="&$C14,Journal!$B$6:$B$505,"<"&($C14+7),Journal!$BP$6:$BP$505,1,Journal!$BB$6:$BB$505,"Overtraded")+COUNTIFS(Journal!$B$6:$B$505,">="&$C14,Journal!$B$6:$B$505,"<"&($C14+7),Journal!$BP$6:$BP$505,1,Journal!$BB$6:$BB$505,"Daily loss hit")+COUNTIFS(Journal!$B$6:$B$505,">="&$C14,Journal!$B$6:$B$505,"<"&($C14+7),Journal!$BP$6:$BP$505,1,Journal!$BB$6:$BB$505,"Weekly loss hit") -> 0 | M14: =IFERROR(COUNTIFS(Journal!$B$6:$B$505,">="&$C14,Journal!$B$6:$B$505,"<"&($C14+7),Journal!$BP$6:$BP$505,1,Journal!$BD$6:$BD$505,"Yes")/(COUNTIFS(Journal!$B$6:$B$505,">="&$C14,Journal!$B$6:$B$505,"<"&($C14+7),Journal!$BP$6:$BP$505,1,Journal!$BD$6:$BD$505,"Yes")+COUNTIFS(Journal!$B$6:$B$505,">="&$C14,Journal!$B$6:$B$505,"<"&($C14+7),Journal!$BP$6:$BP$505,1,Journal!$BD$6:$BD$505,"No")),"")
B15: 10 | C15: =Settings!$C$7-WEEKDAY(Settings!$C$7,2)+1+7*(B15-1) -> 46356 | D15: =C15+6 -> 46362 | E15: =F15+G15+H15 -> 0 | F15: =COUNTIFS(Journal!$B$6:$B$505,">="&$C15,Journal!$B$6:$B$505,"<"&($C15+7),Journal!$BP$6:$BP$505,1,Journal!$AL$6:$AL$505,"Win") -> 0 | G15: =COUNTIFS(Journal!$B$6:$B$505,">="&$C15,Journal!$B$6:$B$505,"<"&($C15+7),Journal!$BP$6:$BP$505,1,Journal!$AL$6:$AL$505,"Loss") -> 0 | H15: =COUNTIFS(Journal!$B$6:$B$505,">="&$C15,Journal!$B$6:$B$505,"<"&($C15+7),Journal!$BP$6:$BP$505,1,Journal!$AL$6:$AL$505,"BE") -> 0 | I15: =IF(E15=0,"",F15/E15) | J15: =IF(E15=0,"",SUMIFS(Journal!$AK$6:$AK$505,Journal!$B$6:$B$505,">="&$C15,Journal!$B$6:$B$505,"<"&($C15+7),Journal!$BP$6:$BP$505,1)) | K15: =IF(E15=0,"",SUMIFS(Journal!$AM$6:$AM$505,Journal!$B$6:$B$505,">="&$C15,Journal!$B$6:$B$505,"<"&($C15+7),Journal!$BP$6:$BP$505,1)) | L15: =COUNTIFS(Journal!$B$6:$B$505,">="&$C15,Journal!$B$6:$B$505,"<"&($C15+7),Journal!$BP$6:$BP$505,1,Journal!$BB$6:$BB$505,"Oversized")+COUNTIFS(Journal!$B$6:$B$505,">="&$C15,Journal!$B$6:$B$505,"<"&($C15+7),Journal!$BP$6:$BP$505,1,Journal!$BB$6:$BB$505,"Overtraded")+COUNTIFS(Journal!$B$6:$B$505,">="&$C15,Journal!$B$6:$B$505,"<"&($C15+7),Journal!$BP$6:$BP$505,1,Journal!$BB$6:$BB$505,"Daily loss hit")+COUNTIFS(Journal!$B$6:$B$505,">="&$C15,Journal!$B$6:$B$505,"<"&($C15+7),Journal!$BP$6:$BP$505,1,Journal!$BB$6:$BB$505,"Weekly loss hit") -> 0 | M15: =IFERROR(COUNTIFS(Journal!$B$6:$B$505,">="&$C15,Journal!$B$6:$B$505,"<"&($C15+7),Journal!$BP$6:$BP$505,1,Journal!$BD$6:$BD$505,"Yes")/(COUNTIFS(Journal!$B$6:$B$505,">="&$C15,Journal!$B$6:$B$505,"<"&($C15+7),Journal!$BP$6:$BP$505,1,Journal!$BD$6:$BD$505,"Yes")+COUNTIFS(Journal!$B$6:$B$505,">="&$C15,Journal!$B$6:$B$505,"<"&($C15+7),Journal!$BP$6:$BP$505,1,Journal!$BD$6:$BD$505,"No")),"")
B16: 11 | C16: =Settings!$C$7-WEEKDAY(Settings!$C$7,2)+1+7*(B16-1) -> 46363 | D16: =C16+6 -> 46369 | E16: =F16+G16+H16 -> 0 | F16: =COUNTIFS(Journal!$B$6:$B$505,">="&$C16,Journal!$B$6:$B$505,"<"&($C16+7),Journal!$BP$6:$BP$505,1,Journal!$AL$6:$AL$505,"Win") -> 0 | G16: =COUNTIFS(Journal!$B$6:$B$505,">="&$C16,Journal!$B$6:$B$505,"<"&($C16+7),Journal!$BP$6:$BP$505,1,Journal!$AL$6:$AL$505,"Loss") -> 0 | H16: =COUNTIFS(Journal!$B$6:$B$505,">="&$C16,Journal!$B$6:$B$505,"<"&($C16+7),Journal!$BP$6:$BP$505,1,Journal!$AL$6:$AL$505,"BE") -> 0 | I16: =IF(E16=0,"",F16/E16) | J16: =IF(E16=0,"",SUMIFS(Journal!$AK$6:$AK$505,Journal!$B$6:$B$505,">="&$C16,Journal!$B$6:$B$505,"<"&($C16+7),Journal!$BP$6:$BP$505,1)) | K16: =IF(E16=0,"",SUMIFS(Journal!$AM$6:$AM$505,Journal!$B$6:$B$505,">="&$C16,Journal!$B$6:$B$505,"<"&($C16+7),Journal!$BP$6:$BP$505,1)) | L16: =COUNTIFS(Journal!$B$6:$B$505,">="&$C16,Journal!$B$6:$B$505,"<"&($C16+7),Journal!$BP$6:$BP$505,1,Journal!$BB$6:$BB$505,"Oversized")+COUNTIFS(Journal!$B$6:$B$505,">="&$C16,Journal!$B$6:$B$505,"<"&($C16+7),Journal!$BP$6:$BP$505,1,Journal!$BB$6:$BB$505,"Overtraded")+COUNTIFS(Journal!$B$6:$B$505,">="&$C16,Journal!$B$6:$B$505,"<"&($C16+7),Journal!$BP$6:$BP$505,1,Journal!$BB$6:$BB$505,"Daily loss hit")+COUNTIFS(Journal!$B$6:$B$505,">="&$C16,Journal!$B$6:$B$505,"<"&($C16+7),Journal!$BP$6:$BP$505,1,Journal!$BB$6:$BB$505,"Weekly loss hit") -> 0 | M16: =IFERROR(COUNTIFS(Journal!$B$6:$B$505,">="&$C16,Journal!$B$6:$B$505,"<"&($C16+7),Journal!$BP$6:$BP$505,1,Journal!$BD$6:$BD$505,"Yes")/(COUNTIFS(Journal!$B$6:$B$505,">="&$C16,Journal!$B$6:$B$505,"<"&($C16+7),Journal!$BP$6:$BP$505,1,Journal!$BD$6:$BD$505,"Yes")+COUNTIFS(Journal!$B$6:$B$505,">="&$C16,Journal!$B$6:$B$505,"<"&($C16+7),Journal!$BP$6:$BP$505,1,Journal!$BD$6:$BD$505,"No")),"")
B17: 12 | C17: =Settings!$C$7-WEEKDAY(Settings!$C$7,2)+1+7*(B17-1) -> 46370 | D17: =C17+6 -> 46376 | E17: =F17+G17+H17 -> 0 | F17: =COUNTIFS(Journal!$B$6:$B$505,">="&$C17,Journal!$B$6:$B$505,"<"&($C17+7),Journal!$BP$6:$BP$505,1,Journal!$AL$6:$AL$505,"Win") -> 0 | G17: =COUNTIFS(Journal!$B$6:$B$505,">="&$C17,Journal!$B$6:$B$505,"<"&($C17+7),Journal!$BP$6:$BP$505,1,Journal!$AL$6:$AL$505,"Loss") -> 0 | H17: =COUNTIFS(Journal!$B$6:$B$505,">="&$C17,Journal!$B$6:$B$505,"<"&($C17+7),Journal!$BP$6:$BP$505,1,Journal!$AL$6:$AL$505,"BE") -> 0 | I17: =IF(E17=0,"",F17/E17) | J17: =IF(E17=0,"",SUMIFS(Journal!$AK$6:$AK$505,Journal!$B$6:$B$505,">="&$C17,Journal!$B$6:$B$505,"<"&($C17+7),Journal!$BP$6:$BP$505,1)) | K17: =IF(E17=0,"",SUMIFS(Journal!$AM$6:$AM$505,Journal!$B$6:$B$505,">="&$C17,Journal!$B$6:$B$505,"<"&($C17+7),Journal!$BP$6:$BP$505,1)) | L17: =COUNTIFS(Journal!$B$6:$B$505,">="&$C17,Journal!$B$6:$B$505,"<"&($C17+7),Journal!$BP$6:$BP$505,1,Journal!$BB$6:$BB$505,"Oversized")+COUNTIFS(Journal!$B$6:$B$505,">="&$C17,Journal!$B$6:$B$505,"<"&($C17+7),Journal!$BP$6:$BP$505,1,Journal!$BB$6:$BB$505,"Overtraded")+COUNTIFS(Journal!$B$6:$B$505,">="&$C17,Journal!$B$6:$B$505,"<"&($C17+7),Journal!$BP$6:$BP$505,1,Journal!$BB$6:$BB$505,"Daily loss hit")+COUNTIFS(Journal!$B$6:$B$505,">="&$C17,Journal!$B$6:$B$505,"<"&($C17+7),Journal!$BP$6:$BP$505,1,Journal!$BB$6:$BB$505,"Weekly loss hit") -> 0 | M17: =IFERROR(COUNTIFS(Journal!$B$6:$B$505,">="&$C17,Journal!$B$6:$B$505,"<"&($C17+7),Journal!$BP$6:$BP$505,1,Journal!$BD$6:$BD$505,"Yes")/(COUNTIFS(Journal!$B$6:$B$505,">="&$C17,Journal!$B$6:$B$505,"<"&($C17+7),Journal!$BP$6:$BP$505,1,Journal!$BD$6:$BD$505,"Yes")+COUNTIFS(Journal!$B$6:$B$505,">="&$C17,Journal!$B$6:$B$505,"<"&($C17+7),Journal!$BP$6:$BP$505,1,Journal!$BD$6:$BD$505,"No")),"")
... B31: 26 | C31: =Settings!$C$7-WEEKDAY(Settings!$C$7,2)+1+7*(B31-1) -> 46468 | D31: =C31+6 -> 46474 | E31: =F31+G31+H31 -> 0 | F31: =COUNTIFS(Journal!$B$6:$B$505,">="&$C31,Journal!$B$6:$B$505,"<"&($C31+7),Journal!$BP$6:$BP$505,1,Journal!$AL$6:$AL$505,"Win") -> 0 | G31: =COUNTIFS(Journal!$B$6:$B$505,">="&$C31,Journal!$B$6:$B$505,"<"&($C31+7),Journal!$BP$6:$BP$505,1,Journal!$AL$6:$AL$505,"Loss") -> 0 | H31: =COUNTIFS(Journal!$B$6:$B$505,">="&$C31,Journal!$B$6:$B$505,"<"&($C31+7),Journal!$BP$6:$BP$505,1,Journal!$AL$6:$AL$505,"BE") -> 0 | I31: =IF(E31=0,"",F31/E31) | J31: =IF(E31=0,"",SUMIFS(Journal!$AK$6:$AK$505,Journal!$B$6:$B$505,">="&$C31,Journal!$B$6:$B$505,"<"&($C31+7),Journal!$BP$6:$BP$505,1)) | K31: =IF(E31=0,"",SUMIFS(Journal!$AM$6:$AM$505,Journal!$B$6:$B$505,">="&$C31,Journal!$B$6:$B$505,"<"&($C31+7),Journal!$BP$6:$BP$505,1)) | L31: =COUNTIFS(Journal!$B$6:$B$505,">="&$C31,Journal!$B$6:$B$505,"<"&($C31+7),Journal!$BP$6:$BP$505,1,Journal!$BB$6:$BB$505,"Oversized")+COUNTIFS(Journal!$B$6:$B$505,">="&$C31,Journal!$B$6:$B$505,"<"&($C31+7),Journal!$BP$6:$BP$505,1,Journal!$BB$6:$BB$505,"Overtraded")+COUNTIFS(Journal!$B$6:$B$505,">="&$C31,Journal!$B$6:$B$505,"<"&($C31+7),Journal!$BP$6:$BP$505,1,Journal!$BB$6:$BB$505,"Daily loss hit")+COUNTIFS(Journal!$B$6:$B$505,">="&$C31,Journal!$B$6:$B$505,"<"&($C31+7),Journal!$BP$6:$BP$505,1,Journal!$BB$6:$BB$505,"Weekly loss hit") -> 0 | M31: =IFERROR(COUNTIFS(Journal!$B$6:$B$505,">="&$C31,Journal!$B$6:$B$505,"<"&($C31+7),Journal!$BP$6:$BP$505,1,Journal!$BD$6:$BD$505,"Yes")/(COUNTIFS(Journal!$B$6:$B$505,">="&$C31,Journal!$B$6:$B$505,"<"&($C31+7),Journal!$BP$6:$BP$505,1,Journal!$BD$6:$BD$505,"Yes")+COUNTIFS(Journal!$B$6:$B$505,">="&$C31,Journal!$B$6:$B$505,"<"&($C31+7),Journal!$BP$6:$BP$505,1,Journal!$BD$6:$BD$505,"No")),"")

Sheet Goals & Prop
B1: GOALS & PROP FIRM TRACKER
B2: Prop rules live on Settings (placeholders until you enter your challenge). Monthly targets below are blue inputs.
B5: PROP CHALLENGE TRACKER
B6: Prop account | C6: =Settings!$C$21 -> Prop Challenge
B7: Starting balance ($) | C7: =IFERROR(INDEX(Settings!$G$5:$G$10,MATCH(Settings!$C$21,Settings!$F$5:$F$10,0)),0) -> 50000 | D7: From Settings > Accounts
B8: Current balance ($) | C8: =C7+SUMIFS(Journal!$AM$6:$AM$505,Journal!$BJ$6:$BJ$505,Settings!$C$21) -> 50000
B9: Net P&L ($) | C9: =SUMIFS(Journal!$AM$6:$AM$505,Journal!$BJ$6:$BJ$505,Settings!$C$21) -> 0
B10: Profit (% of start) | C10: =IFERROR(C9/C7,0) -> 0
B11: Profit target (%) | C11: =Settings!$C$22 -> 0.08 | D11: Placeholder on Settings
B12: Target progress | C12: =MAX(0,MIN(1,IFERROR(C10/C11,0))) -> 0 | D12: =REPT("█",ROUND(C12*25,0))&REPT("░",25-ROUND(C12*25,0)) -> ░░░░░░░░░░░░░░░░░░░░░░░░░
B13: Worst day-so-far loss ($) | C13: =MIN(0,_xlfn.MINIFS(Journal!$AZ$6:$AZ$505,Journal!$BJ$6:$BJ$505,Settings!$C$21)) -> 0 | D13: Lowest running day P&L after any trade
B14: Worst day loss (% of start) | C14: =IFERROR(-C13/C7,0) -> 0
B15: Daily loss limit (%) | C15: =Settings!$C$23 -> 0.05 | D15: Placeholder on Settings
B16: Daily loss limit used | C16: =MAX(0,MIN(1,IFERROR(C14/C15,0))) -> 0 | D16: =REPT("█",ROUND(C16*25,0))&REPT("░",25-ROUND(C16*25,0)) -> ░░░░░░░░░░░░░░░░░░░░░░░░░
B17: Max drawdown (%) | C17: =-MIN(0,_xlfn.MINIFS(Journal!$BO$6:$BO$505,Journal!$BJ$6:$BJ$505,Settings!$C$21)) -> 0 | D17: Peak to trough on this account
B18: Max drawdown limit (%) | C18: =Settings!$C$24 -> 0.1 | D18: Placeholder on Settings
B19: Drawdown limit used | C19: =MAX(0,MIN(1,IFERROR(C17/C18,0))) -> 0 | D19: =REPT("█",ROUND(C19*25,0))&REPT("░",25-ROUND(C19*25,0)) -> ░░░░░░░░░░░░░░░░░░░░░░░░░
B20: Trades taken | C20: =SUMPRODUCT((Journal!$BJ$6:$BJ$505=Settings!$C$21)*(Journal!$AL$6:$AL$505<>"")) -> 0
B21: Days left in challenge | C21: =MAX(0,Settings!$C$25-TODAY()) -> 92 | D21: Counts down from today to the end date on Settings
B22: STATUS | C22: =IF(C17>=C18,"BREACHED - max drawdown",IF(C14>=C15,"BREACHED - daily loss",IF(C12>=1,"TARGET HIT",IF(OR(C16>=0.8,C19>=0.8),"CAUTION - near a limit","ON TRACK")))) -> ON TRACK
B25: MONTHLY GOALS (targets are blue placeholders - set your own)
B26: Month | C26: Target P&L ($) | D26: Actual P&L ($) | E26: Progress | F26: Target Win % | G26: Actual Win % | H26: Status
B27: =Analytics!B193 -> 46266 | C27: 300 | D27: =Analytics!J193 -> 229.5 | E27: =REPT("█",ROUND(MAX(0,MIN(1,IFERROR(D27/C27,0)))*15,0))&REPT("░",15-ROUND(MAX(0,MIN(1,IFERROR(D27/C27,0)))*15,0))&" "&TEXT(IFERROR(D27/C27,0),"0%") -> ███████████░░░░ 77% | F27: 0.5 | G27: =IF(Analytics!C193=0,0,Analytics!G193) -> 1 | H27: =IF(Analytics!C193=0,IF(B27>TODAY(),"Upcoming","No trades"),IF(D27>=C27,"Goal met",IF(D27>=0,"In progress","Behind"))) -> In progress
B28: =Analytics!B194 -> 46296 | C28: 300 | D28: =Analytics!J194 -> 0 | E28: =REPT("█",ROUND(MAX(0,MIN(1,IFERROR(D28/C28,0)))*15,0))&REPT("░",15-ROUND(MAX(0,MIN(1,IFERROR(D28/C28,0)))*15,0))&" "&TEXT(IFERROR(D28/C28,0),"0%") -> ░░░░░░░░░░░░░░░ 0% | F28: 0.5 | G28: =IF(Analytics!C194=0,0,Analytics!G194) -> 0 | H28: =IF(Analytics!C194=0,IF(B28>TODAY(),"Upcoming","No trades"),IF(D28>=C28,"Goal met",IF(D28>=0,"In progress","Behind"))) -> Upcoming
B29: =Analytics!B195 -> 46327 | C29: 300 | D29: =Analytics!J195 -> 0 | E29: =REPT("█",ROUND(MAX(0,MIN(1,IFERROR(D29/C29,0)))*15,0))&REPT("░",15-ROUND(MAX(0,MIN(1,IFERROR(D29/C29,0)))*15,0))&" "&TEXT(IFERROR(D29/C29,0),"0%") -> ░░░░░░░░░░░░░░░ 0% | F29: 0.5 | G29: =IF(Analytics!C195=0,0,Analytics!G195) -> 0 | H29: =IF(Analytics!C195=0,IF(B29>TODAY(),"Upcoming","No trades"),IF(D29>=C29,"Goal met",IF(D29>=0,"In progress","Behind"))) -> Upcoming
B30: =Analytics!B196 -> 46357 | C30: 300 | D30: =Analytics!J196 -> 0 | E30: =REPT("█",ROUND(MAX(0,MIN(1,IFERROR(D30/C30,0)))*15,0))&REPT("░",15-ROUND(MAX(0,MIN(1,IFERROR(D30/C30,0)))*15,0))&" "&TEXT(IFERROR(D30/C30,0),"0%") -> ░░░░░░░░░░░░░░░ 0% | F30: 0.5 | G30: =IF(Analytics!C196=0,0,Analytics!G196) -> 0 | H30: =IF(Analytics!C196=0,IF(B30>TODAY(),"Upcoming","No trades"),IF(D30>=C30,"Goal met",IF(D30>=0,"In progress","Behind"))) -> Upcoming
B31: =Analytics!B197 -> 46388 | C31: 300 | D31: =Analytics!J197 -> 0 | E31: =REPT("█",ROUND(MAX(0,MIN(1,IFERROR(D31/C31,0)))*15,0))&REPT("░",15-ROUND(MAX(0,MIN(1,IFERROR(D31/C31,0)))*15,0))&" "&TEXT(IFERROR(D31/C31,0),"0%") -> ░░░░░░░░░░░░░░░ 0% | F31: 0.5 | G31: =IF(Analytics!C197=0,0,Analytics!G197) -> 0 | H31: =IF(Analytics!C197=0,IF(B31>TODAY(),"Upcoming","No trades"),IF(D31>=C31,"Goal met",IF(D31>=0,"In progress","Behind"))) -> Upcoming
B32: =Analytics!B198 -> 46419 | C32: 300 | D32: =Analytics!J198 -> 0 | E32: =REPT("█",ROUND(MAX(0,MIN(1,IFERROR(D32/C32,0)))*15,0))&REPT("░",15-ROUND(MAX(0,MIN(1,IFERROR(D32/C32,0)))*15,0))&" "&TEXT(IFERROR(D32/C32,0),"0%") -> ░░░░░░░░░░░░░░░ 0% | F32: 0.5 | G32: =IF(Analytics!C198=0,0,Analytics!G198) -> 0 | H32: =IF(Analytics!C198=0,IF(B32>TODAY(),"Upcoming","No trades"),IF(D32>=C32,"Goal met",IF(D32>=0,"In progress","Behind"))) -> Upcoming
B33: =Analytics!B199 -> 46447 | C33: 300 | D33: =Analytics!J199 -> 0 | E33: =REPT("█",ROUND(MAX(0,MIN(1,IFERROR(D33/C33,0)))*15,0))&REPT("░",15-ROUND(MAX(0,MIN(1,IFERROR(D33/C33,0)))*15,0))&" "&TEXT(IFERROR(D33/C33,0),"0%") -> ░░░░░░░░░░░░░░░ 0% | F33: 0.5 | G33: =IF(Analytics!C199=0,0,Analytics!G199) -> 0 | H33: =IF(Analytics!C199=0,IF(B33>TODAY(),"Upcoming","No trades"),IF(D33>=C33,"Goal met",IF(D33>=0,"In progress","Behind"))) -> Upcoming
B34: =Analytics!B200 -> 46478 | C34: 300 | D34: =Analytics!J200 -> 0 | E34: =REPT("█",ROUND(MAX(0,MIN(1,IFERROR(D34/C34,0)))*15,0))&REPT("░",15-ROUND(MAX(0,MIN(1,IFERROR(D34/C34,0)))*15,0))&" "&TEXT(IFERROR(D34/C34,0),"0%") -> ░░░░░░░░░░░░░░░ 0% | F34: 0.5 | G34: =IF(Analytics!C200=0,0,Analytics!G200) -> 0 | H34: =IF(Analytics!C200=0,IF(B34>TODAY(),"Upcoming","No trades"),IF(D34>=C34,"Goal met",IF(D34>=0,"In progress","Behind"))) -> Upcoming
B35: =Analytics!B201 -> 46508 | C35: 300 | D35: =Analytics!J201 -> 0 | E35: =REPT("█",ROUND(MAX(0,MIN(1,IFERROR(D35/C35,0)))*15,0))&REPT("░",15-ROUND(MAX(0,MIN(1,IFERROR(D35/C35,0)))*15,0))&" "&TEXT(IFERROR(D35/C35,0),"0%") -> ░░░░░░░░░░░░░░░ 0% | F35: 0.5 | G35: =IF(Analytics!C201=0,0,Analytics!G201) -> 0 | H35: =IF(Analytics!C201=0,IF(B35>TODAY(),"Upcoming","No trades"),IF(D35>=C35,"Goal met",IF(D35>=0,"In progress","Behind"))) -> Upcoming
B36: =Analytics!B202 -> 46539 | C36: 300 | D36: =Analytics!J202 -> 0 | E36: =REPT("█",ROUND(MAX(0,MIN(1,IFERROR(D36/C36,0)))*15,0))&REPT("░",15-ROUND(MAX(0,MIN(1,IFERROR(D36/C36,0)))*15,0))&" "&TEXT(IFERROR(D36/C36,0),"0%") -> ░░░░░░░░░░░░░░░ 0% | F36: 0.5 | G36: =IF(Analytics!C202=0,0,Analytics!G202) -> 0 | H36: =IF(Analytics!C202=0,IF(B36>TODAY(),"Upcoming","No trades"),IF(D36>=C36,"Goal met",IF(D36>=0,"In progress","Behind"))) -> Upcoming
B37: =Analytics!B203 -> 46569 | C37: 300 | D37: =Analytics!J203 -> 0 | E37: =REPT("█",ROUND(MAX(0,MIN(1,IFERROR(D37/C37,0)))*15,0))&REPT("░",15-ROUND(MAX(0,MIN(1,IFERROR(D37/C37,0)))*15,0))&" "&TEXT(IFERROR(D37/C37,0),"0%") -> ░░░░░░░░░░░░░░░ 0% | F37: 0.5 | G37: =IF(Analytics!C203=0,0,Analytics!G203) -> 0 | H37: =IF(Analytics!C203=0,IF(B37>TODAY(),"Upcoming","No trades"),IF(D37>=C37,"Goal met",IF(D37>=0,"In progress","Behind"))) -> Upcoming
B38: =Analytics!B204 -> 46600 | C38: 300 | D38: =Analytics!J204 -> 0 | E38: =REPT("█",ROUND(MAX(0,MIN(1,IFERROR(D38/C38,0)))*15,0))&REPT("░",15-ROUND(MAX(0,MIN(1,IFERROR(D38/C38,0)))*15,0))&" "&TEXT(IFERROR(D38/C38,0),"0%") -> ░░░░░░░░░░░░░░░ 0% | F38: 0.5 | G38: =IF(Analytics!C204=0,0,Analytics!G204) -> 0 | H38: =IF(Analytics!C204=0,IF(B38>TODAY(),"Upcoming","No trades"),IF(D38>=C38,"Goal met",IF(D38>=0,"In progress","Behind"))) -> Upcoming
B40: Monthly targets (300 / 50%) are placeholders, not advice. Status compares each month's P&L with its target.

Sheet Playbook
B1: STRATEGY PLAYBOOK
B2: Your setups with concise rules (editable templates) and a live verdict from your own journal results.
B5: Setup / Model | C5: Entry trigger (edit to your rules) | D5: Stop placement | E5: Target | F5: Trades | G5: Win % | H5: Avg R | I5: Net P&L ($) | J5: Verdict
B6: =Analytics!B33 -> Liquidity Sweep Reversal | C6: Price takes a clear high or low (Asia, prior day, equal highs/lows), closes back inside, then shifts structure with displacement. | D6: Beyond the sweep extreme | E6: Opposite side of the range / next liquidity pool (2R+) | F6: =Analytics!C33 -> 1 | G6: =IF(N(Analytics!C33)=0,"",Analytics!G33) -> 1 | H6: =IF(N(Analytics!C33)=0,"",Analytics!I33) -> 2.33 | I6: =IF(N(Analytics!C33)=0,"",Analytics!J33) -> 229.5 | J6: =IF(B6="","",IF(N(F6)<10,"Need 10+ trades",IF(H6>=0.3,"Keep - proven edge",IF(H6>0,"Refine","Review / pause")))) -> Need 10+ trades
B7: =Analytics!B34 -> Order Block Retest | C7: Price returns to the last opposing candle before a strong move, in line with HTF bias; enter on a rejection. | D7: Beyond the order block | E7: Prior swing / next imbalance | F7: =Analytics!C34 -> 0 | G7: =IF(N(Analytics!C34)=0,"",Analytics!G34) | H7: =IF(N(Analytics!C34)=0,"",Analytics!I34) | I7: =IF(N(Analytics!C34)=0,"",Analytics!J34) | J7: =IF(B7="","",IF(N(F7)<10,"Need 10+ trades",IF(H7>=0.3,"Keep - proven edge",IF(H7>0,"Refine","Review / pause")))) -> Need 10+ trades
B8: =Analytics!B35 -> Break & Retest | C8: A key level breaks with momentum, retests from the other side and holds. | D8: Behind the retest wick | E8: Next key level | F8: =Analytics!C35 -> 0 | G8: =IF(N(Analytics!C35)=0,"",Analytics!G35) | H8: =IF(N(Analytics!C35)=0,"",Analytics!I35) | I8: =IF(N(Analytics!C35)=0,"",Analytics!J35) | J8: =IF(B8="","",IF(N(F8)<10,"Need 10+ trades",IF(H8>=0.3,"Keep - proven edge",IF(H8>0,"Refine","Review / pause")))) -> Need 10+ trades
B9: =Analytics!B36 -> FVG Entry | C9: Displacement leaves an imbalance; enter when price returns into the gap and confirms. | D9: Beyond the candle that formed the gap | E9: Recent swing high / low | F9: =Analytics!C36 -> 0 | G9: =IF(N(Analytics!C36)=0,"",Analytics!G36) | H9: =IF(N(Analytics!C36)=0,"",Analytics!I36) | I9: =IF(N(Analytics!C36)=0,"",Analytics!J36) | J9: =IF(B9="","",IF(N(F9)<10,"Need 10+ trades",IF(H9>=0.3,"Keep - proven edge",IF(H9>0,"Refine","Review / pause")))) -> Need 10+ trades
B10: =Analytics!B37 -> Breaker Block | C10: A failed order block flips role after a structure shift; enter on the retest of the flipped zone. | D10: Beyond the breaker | E10: Opposing liquidity | F10: =Analytics!C37 -> 0 | G10: =IF(N(Analytics!C37)=0,"",Analytics!G37) | H10: =IF(N(Analytics!C37)=0,"",Analytics!I37) | I10: =IF(N(Analytics!C37)=0,"",Analytics!J37) | J10: =IF(B10="","",IF(N(F10)<10,"Need 10+ trades",IF(H10>=0.3,"Keep - proven edge",IF(H10>0,"Refine","Review / pause")))) -> Need 10+ trades
B11: =Analytics!B38 -> Supply/Demand Zone Reaction | C11: Fresh zone left by an impulsive move; enter on a lower-timeframe reaction. | D11: Outside the zone | E11: Next opposing zone | F11: =Analytics!C38 -> 0 | G11: =IF(N(Analytics!C38)=0,"",Analytics!G38) | H11: =IF(N(Analytics!C38)=0,"",Analytics!I38) | I11: =IF(N(Analytics!C38)=0,"",Analytics!J38) | J11: =IF(B11="","",IF(N(F11)<10,"Need 10+ trades",IF(H11>=0.3,"Keep - proven edge",IF(H11>0,"Refine","Review / pause")))) -> Need 10+ trades
B12: =Analytics!B39 -> Trend Pullback | C12: HTF trend intact; buy or sell the pullback into prior structure or a zone. | D12: Beyond the pullback swing | E12: Prior extreme and beyond | F12: =Analytics!C39 -> 0 | G12: =IF(N(Analytics!C39)=0,"",Analytics!G39) | H12: =IF(N(Analytics!C39)=0,"",Analytics!I39) | I12: =IF(N(Analytics!C39)=0,"",Analytics!J39) | J12: =IF(B12="","",IF(N(F12)<10,"Need 10+ trades",IF(H12>=0.3,"Keep - proven edge",IF(H12>0,"Refine","Review / pause")))) -> Need 10+ trades
B13: =Analytics!B40 -> Range Edge Fade | C13: Clear range; fade a rejection at the range high or low. | D13: Outside the range edge | E13: Range midpoint to opposite edge | F13: =Analytics!C40 -> 0 | G13: =IF(N(Analytics!C40)=0,"",Analytics!G40) | H13: =IF(N(Analytics!C40)=0,"",Analytics!I40) | I13: =IF(N(Analytics!C40)=0,"",Analytics!J40) | J13: =IF(B13="","",IF(N(F13)<10,"Need 10+ trades",IF(H13>=0.3,"Keep - proven edge",IF(H13>0,"Refine","Review / pause")))) -> Need 10+ trades
B14: =Analytics!B41 -> Asia Range Sweep | C14: Asian high or low taken during London; enter on the reversal back into the range. | D14: Beyond the sweep | E14: Opposite side of the Asian range | F14: =Analytics!C41 -> 0 | G14: =IF(N(Analytics!C41)=0,"",Analytics!G41) | H14: =IF(N(Analytics!C41)=0,"",Analytics!I41) | I14: =IF(N(Analytics!C41)=0,"",Analytics!J41) | J14: =IF(B14="","",IF(N(F14)<10,"Need 10+ trades",IF(H14>=0.3,"Keep - proven edge",IF(H14>0,"Refine","Review / pause")))) -> Need 10+ trades
B15: =Analytics!B42 -> Other | C15: Describe any other model here. | F15: =Analytics!C42 -> 0 | G15: =IF(N(Analytics!C42)=0,"",Analytics!G42) | H15: =IF(N(Analytics!C42)=0,"",Analytics!I42) | I15: =IF(N(Analytics!C42)=0,"",Analytics!J42) | J15: =IF(B15="","",IF(N(F15)<10,"Need 10+ trades",IF(H15>=0.3,"Keep - proven edge",IF(H15>0,"Refine","Review / pause")))) -> Need 10+ trades
B16: =Analytics!B43 | F16: =Analytics!C43 | G16: =IF(N(Analytics!C43)=0,"",Analytics!G43) | H16: =IF(N(Analytics!C43)=0,"",Analytics!I43) | I16: =IF(N(Analytics!C43)=0,"",Analytics!J43) | J16: =IF(B16="","",IF(N(F16)<10,"Need 10+ trades",IF(H16>=0.3,"Keep - proven edge",IF(H16>0,"Refine","Review / pause"))))
B17: =Analytics!B44 | F17: =Analytics!C44 | G17: =IF(N(Analytics!C44)=0,"",Analytics!G44) | H17: =IF(N(Analytics!C44)=0,"",Analytics!I44) | I17: =IF(N(Analytics!C44)=0,"",Analytics!J44) | J17: =IF(B17="","",IF(N(F17)<10,"Need 10+ trades",IF(H17>=0.3,"Keep - proven edge",IF(H17>0,"Refine","Review / pause"))))
B19: Verdict rule: fewer than 10 trades = not enough data; average R of 0.30 or more = keep; above 0 = refine; otherwise review. Rules shown are generic templates - replace them with your own.

Sheet Backtest
B1: BACKTEST LOG
B2: Log tested trades here to validate a setup before risking money. Results are in R only.
B5: BACKTEST SUMMARY
C6: TRADES | E6: WIN % | G6: TOTAL R | I6: EXPECTANCY (R) | K6: PROFIT FACTOR
C7: =COUNT($J$14:$J$313) -> 0 | E7: =IFERROR(COUNTIF($K$14:$K$313,"Win")/$C$7,0) -> 0 | G7: =SUM($J$14:$J$313) -> 0 | I7: =IFERROR(SUM($J$14:$J$313)/$C$7,0) -> 0 | K7: =IFERROR(SUMIF($J$14:$J$313,">0")/ABS(SUMIF($J$14:$J$313,"<0")),"-") -> -
B13: # | C13: Date | D13: Pair | E13: Setup / Model | F13: Direction | G13: Entry | H13: Stop | I13: Exit | J13: Result (R) | K13: Outcome | L13: Cum. R | M13: Notes | O13: BACKTEST BY SETUP
B14: =IF(C14="","",ROW()-13) | J14: =IF(OR(G14="",H14="",I14=""),"",IFERROR(ROUND(IF(F14="Short",G14-I14,I14-G14)/ABS(G14-H14),2),"")) | K14: =IF(J14="","",IF(ABS(J14)<=Settings!$C$6,"BE",IF(J14>0,"Win","Loss"))) | L14: =IF(J14="","",ROUND(SUM(J$14:J14),2)) | O14: Setup | P14: Trades | Q14: Win % | R14: Total R | S14: Avg R
B15: =IF(C15="","",ROW()-13) | J15: =IF(OR(G15="",H15="",I15=""),"",IFERROR(ROUND(IF(F15="Short",G15-I15,I15-G15)/ABS(G15-H15),2),"")) | K15: =IF(J15="","",IF(ABS(J15)<=Settings!$C$6,"BE",IF(J15>0,"Win","Loss"))) | L15: =IF(J15="","",ROUND(SUM(J$14:J15),2)) | O15: =IF(Lists!$G$6="","",Lists!$G$6) -> Liquidity Sweep Reversal | P15: =IF($O15="","",COUNTIFS($E$14:$E$313,$O15,$K$14:$K$313,"?*")) -> 0 | Q15: =IF($O15="","",IFERROR(COUNTIFS($E$14:$E$313,$O15,$K$14:$K$313,"Win")/P15,0)) -> 0 | R15: =IF($O15="","",SUMIFS($J$14:$J$313,$E$14:$E$313,$O15)) -> 0 | S15: =IF($O15="","",IFERROR(R15/P15,0)) -> 0
B16: =IF(C16="","",ROW()-13) | J16: =IF(OR(G16="",H16="",I16=""),"",IFERROR(ROUND(IF(F16="Short",G16-I16,I16-G16)/ABS(G16-H16),2),"")) | K16: =IF(J16="","",IF(ABS(J16)<=Settings!$C$6,"BE",IF(J16>0,"Win","Loss"))) | L16: =IF(J16="","",ROUND(SUM(J$14:J16),2)) | O16: =IF(Lists!$G$7="","",Lists!$G$7) -> Order Block Retest | P16: =IF($O16="","",COUNTIFS($E$14:$E$313,$O16,$K$14:$K$313,"?*")) -> 0 | Q16: =IF($O16="","",IFERROR(COUNTIFS($E$14:$E$313,$O16,$K$14:$K$313,"Win")/P16,0)) -> 0 | R16: =IF($O16="","",SUMIFS($J$14:$J$313,$E$14:$E$313,$O16)) -> 0 | S16: =IF($O16="","",IFERROR(R16/P16,0)) -> 0
B17: =IF(C17="","",ROW()-13) | J17: =IF(OR(G17="",H17="",I17=""),"",IFERROR(ROUND(IF(F17="Short",G17-I17,I17-G17)/ABS(G17-H17),2),"")) | K17: =IF(J17="","",IF(ABS(J17)<=Settings!$C$6,"BE",IF(J17>0,"Win","Loss"))) | L17: =IF(J17="","",ROUND(SUM(J$14:J17),2)) | O17: =IF(Lists!$G$8="","",Lists!$G$8) -> Break & Retest | P17: =IF($O17="","",COUNTIFS($E$14:$E$313,$O17,$K$14:$K$313,"?*")) -> 0 | Q17: =IF($O17="","",IFERROR(COUNTIFS($E$14:$E$313,$O17,$K$14:$K$313,"Win")/P17,0)) -> 0 | R17: =IF($O17="","",SUMIFS($J$14:$J$313,$E$14:$E$313,$O17)) -> 0 | S17: =IF($O17="","",IFERROR(R17/P17,0)) -> 0
B18: =IF(C18="","",ROW()-13) | J18: =IF(OR(G18="",H18="",I18=""),"",IFERROR(ROUND(IF(F18="Short",G18-I18,I18-G18)/ABS(G18-H18),2),"")) | K18: =IF(J18="","",IF(ABS(J18)<=Settings!$C$6,"BE",IF(J18>0,"Win","Loss"))) | L18: =IF(J18="","",ROUND(SUM(J$14:J18),2)) | O18: =IF(Lists!$G$9="","",Lists!$G$9) -> FVG Entry | P18: =IF($O18="","",COUNTIFS($E$14:$E$313,$O18,$K$14:$K$313,"?*")) -> 0 | Q18: =IF($O18="","",IFERROR(COUNTIFS($E$14:$E$313,$O18,$K$14:$K$313,"Win")/P18,0)) -> 0 | R18: =IF($O18="","",SUMIFS($J$14:$J$313,$E$14:$E$313,$O18)) -> 0 | S18: =IF($O18="","",IFERROR(R18/P18,0)) -> 0
B19: =IF(C19="","",ROW()-13) | J19: =IF(OR(G19="",H19="",I19=""),"",IFERROR(ROUND(IF(F19="Short",G19-I19,I19-G19)/ABS(G19-H19),2),"")) | K19: =IF(J19="","",IF(ABS(J19)<=Settings!$C$6,"BE",IF(J19>0,"Win","Loss"))) | L19: =IF(J19="","",ROUND(SUM(J$14:J19),2)) | O19: =IF(Lists!$G$10="","",Lists!$G$10) -> Breaker Block | P19: =IF($O19="","",COUNTIFS($E$14:$E$313,$O19,$K$14:$K$313,"?*")) -> 0 | Q19: =IF($O19="","",IFERROR(COUNTIFS($E$14:$E$313,$O19,$K$14:$K$313,"Win")/P19,0)) -> 0 | R19: =IF($O19="","",SUMIFS($J$14:$J$313,$E$14:$E$313,$O19)) -> 0 | S19: =IF($O19="","",IFERROR(R19/P19,0)) -> 0
B20: =IF(C20="","",ROW()-13) | J20: =IF(OR(G20="",H20="",I20=""),"",IFERROR(ROUND(IF(F20="Short",G20-I20,I20-G20)/ABS(G20-H20),2),"")) | K20: =IF(J20="","",IF(ABS(J20)<=Settings!$C$6,"BE",IF(J20>0,"Win","Loss"))) | L20: =IF(J20="","",ROUND(SUM(J$14:J20),2)) | O20: =IF(Lists!$G$11="","",Lists!$G$11) -> Supply/Demand Zone Reaction | P20: =IF($O20="","",COUNTIFS($E$14:$E$313,$O20,$K$14:$K$313,"?*")) -> 0 | Q20: =IF($O20="","",IFERROR(COUNTIFS($E$14:$E$313,$O20,$K$14:$K$313,"Win")/P20,0)) -> 0 | R20: =IF($O20="","",SUMIFS($J$14:$J$313,$E$14:$E$313,$O20)) -> 0 | S20: =IF($O20="","",IFERROR(R20/P20,0)) -> 0
B21: =IF(C21="","",ROW()-13) | J21: =IF(OR(G21="",H21="",I21=""),"",IFERROR(ROUND(IF(F21="Short",G21-I21,I21-G21)/ABS(G21-H21),2),"")) | K21: =IF(J21="","",IF(ABS(J21)<=Settings!$C$6,"BE",IF(J21>0,"Win","Loss"))) | L21: =IF(J21="","",ROUND(SUM(J$14:J21),2)) | O21: =IF(Lists!$G$12="","",Lists!$G$12) -> Trend Pullback | P21: =IF($O21="","",COUNTIFS($E$14:$E$313,$O21,$K$14:$K$313,"?*")) -> 0 | Q21: =IF($O21="","",IFERROR(COUNTIFS($E$14:$E$313,$O21,$K$14:$K$313,"Win")/P21,0)) -> 0 | R21: =IF($O21="","",SUMIFS($J$14:$J$313,$E$14:$E$313,$O21)) -> 0 | S21: =IF($O21="","",IFERROR(R21/P21,0)) -> 0
B22: =IF(C22="","",ROW()-13) | J22: =IF(OR(G22="",H22="",I22=""),"",IFERROR(ROUND(IF(F22="Short",G22-I22,I22-G22)/ABS(G22-H22),2),"")) | K22: =IF(J22="","",IF(ABS(J22)<=Settings!$C$6,"BE",IF(J22>0,"Win","Loss"))) | L22: =IF(J22="","",ROUND(SUM(J$14:J22),2)) | O22: =IF(Lists!$G$13="","",Lists!$G$13) -> Range Edge Fade | P22: =IF($O22="","",COUNTIFS($E$14:$E$313,$O22,$K$14:$K$313,"?*")) -> 0 | Q22: =IF($O22="","",IFERROR(COUNTIFS($E$14:$E$313,$O22,$K$14:$K$313,"Win")/P22,0)) -> 0 | R22: =IF($O22="","",SUMIFS($J$14:$J$313,$E$14:$E$313,$O22)) -> 0 | S22: =IF($O22="","",IFERROR(R22/P22,0)) -> 0
B23: =IF(C23="","",ROW()-13) | J23: =IF(OR(G23="",H23="",I23=""),"",IFERROR(ROUND(IF(F23="Short",G23-I23,I23-G23)/ABS(G23-H23),2),"")) | K23: =IF(J23="","",IF(ABS(J23)<=Settings!$C$6,"BE",IF(J23>0,"Win","Loss"))) | L23: =IF(J23="","",ROUND(SUM(J$14:J23),2)) | O23: =IF(Lists!$G$14="","",Lists!$G$14) -> Asia Range Sweep | P23: =IF($O23="","",COUNTIFS($E$14:$E$313,$O23,$K$14:$K$313,"?*")) -> 0 | Q23: =IF($O23="","",IFERROR(COUNTIFS($E$14:$E$313,$O23,$K$14:$K$313,"Win")/P23,0)) -> 0 | R23: =IF($O23="","",SUMIFS($J$14:$J$313,$E$14:$E$313,$O23)) -> 0 | S23: =IF($O23="","",IFERROR(R23/P23,0)) -> 0
B24: =IF(C24="","",ROW()-13) | J24: =IF(OR(G24="",H24="",I24=""),"",IFERROR(ROUND(IF(F24="Short",G24-I24,I24-G24)/ABS(G24-H24),2),"")) | K24: =IF(J24="","",IF(ABS(J24)<=Settings!$C$6,"BE",IF(J24>0,"Win","Loss"))) | L24: =IF(J24="","",ROUND(SUM(J$14:J24),2)) | O24: =IF(Lists!$G$15="","",Lists!$G$15) -> Other | P24: =IF($O24="","",COUNTIFS($E$14:$E$313,$O24,$K$14:$K$313,"?*")) -> 0 | Q24: =IF($O24="","",IFERROR(COUNTIFS($E$14:$E$313,$O24,$K$14:$K$313,"Win")/P24,0)) -> 0 | R24: =IF($O24="","",SUMIFS($J$14:$J$313,$E$14:$E$313,$O24)) -> 0 | S24: =IF($O24="","",IFERROR(R24/P24,0)) -> 0
B25: =IF(C25="","",ROW()-13) | J25: =IF(OR(G25="",H25="",I25=""),"",IFERROR(ROUND(IF(F25="Short",G25-I25,I25-G25)/ABS(G25-H25),2),"")) | K25: =IF(J25="","",IF(ABS(J25)<=Settings!$C$6,"BE",IF(J25>0,"Win","Loss"))) | L25: =IF(J25="","",ROUND(SUM(J$14:J25),2)) | O25: =IF(Lists!$G$16="","",Lists!$G$16) | P25: =IF($O25="","",COUNTIFS($E$14:$E$313,$O25,$K$14:$K$313,"?*")) | Q25: =IF($O25="","",IFERROR(COUNTIFS($E$14:$E$313,$O25,$K$14:$K$313,"Win")/P25,0)) | R25: =IF($O25="","",SUMIFS($J$14:$J$313,$E$14:$E$313,$O25)) | S25: =IF($O25="","",IFERROR(R25/P25,0))
B26: =IF(C26="","",ROW()-13) | J26: =IF(OR(G26="",H26="",I26=""),"",IFERROR(ROUND(IF(F26="Short",G26-I26,I26-G26)/ABS(G26-H26),2),"")) | K26: =IF(J26="","",IF(ABS(J26)<=Settings!$C$6,"BE",IF(J26>0,"Win","Loss"))) | L26: =IF(J26="","",ROUND(SUM(J$14:J26),2)) | O26: =IF(Lists!$G$17="","",Lists!$G$17) | P26: =IF($O26="","",COUNTIFS($E$14:$E$313,$O26,$K$14:$K$313,"?*")) | Q26: =IF($O26="","",IFERROR(COUNTIFS($E$14:$E$313,$O26,$K$14:$K$313,"Win")/P26,0)) | R26: =IF($O26="","",SUMIFS($J$14:$J$313,$E$14:$E$313,$O26)) | S26: =IF($O26="","",IFERROR(R26/P26,0))
B27: =IF(C27="","",ROW()-13) | J27: =IF(OR(G27="",H27="",I27=""),"",IFERROR(ROUND(IF(F27="Short",G27-I27,I27-G27)/ABS(G27-H27),2),"")) | K27: =IF(J27="","",IF(ABS(J27)<=Settings!$C$6,"BE",IF(J27>0,"Win","Loss"))) | L27: =IF(J27="","",ROUND(SUM(J$14:J27),2))
B28: =IF(C28="","",ROW()-13) | J28: =IF(OR(G28="",H28="",I28=""),"",IFERROR(ROUND(IF(F28="Short",G28-I28,I28-G28)/ABS(G28-H28),2),"")) | K28: =IF(J28="","",IF(ABS(J28)<=Settings!$C$6,"BE",IF(J28>0,"Win","Loss"))) | L28: =IF(J28="","",ROUND(SUM(J$14:J28),2))
B29: =IF(C29="","",ROW()-13) | J29: =IF(OR(G29="",H29="",I29=""),"",IFERROR(ROUND(IF(F29="Short",G29-I29,I29-G29)/ABS(G29-H29),2),"")) | K29: =IF(J29="","",IF(ABS(J29)<=Settings!$C$6,"BE",IF(J29>0,"Win","Loss"))) | L29: =IF(J29="","",ROUND(SUM(J$14:J29),2))
B30: =IF(C30="","",ROW()-13) | J30: =IF(OR(G30="",H30="",I30=""),"",IFERROR(ROUND(IF(F30="Short",G30-I30,I30-G30)/ABS(G30-H30),2),"")) | K30: =IF(J30="","",IF(ABS(J30)<=Settings!$C$6,"BE",IF(J30>0,"Win","Loss"))) | L30: =IF(J30="","",ROUND(SUM(J$14:J30),2))
B31: =IF(C31="","",ROW()-13) | J31: =IF(OR(G31="",H31="",I31=""),"",IFERROR(ROUND(IF(F31="Short",G31-I31,I31-G31)/ABS(G31-H31),2),"")) | K31: =IF(J31="","",IF(ABS(J31)<=Settings!$C$6,"BE",IF(J31>0,"Win","Loss"))) | L31: =IF(J31="","",ROUND(SUM(J$14:J31),2))
B32: =IF(C32="","",ROW()-13) | J32: =IF(OR(G32="",H32="",I32=""),"",IFERROR(ROUND(IF(F32="Short",G32-I32,I32-G32)/ABS(G32-H32),2),"")) | K32: =IF(J32="","",IF(ABS(J32)<=Settings!$C$6,"BE",IF(J32>0,"Win","Loss"))) | L32: =IF(J32="","",ROUND(SUM(J$14:J32),2))
B33: =IF(C33="","",ROW()-13) | J33: =IF(OR(G33="",H33="",I33=""),"",IFERROR(ROUND(IF(F33="Short",G33-I33,I33-G33)/ABS(G33-H33),2),"")) | K33: =IF(J33="","",IF(ABS(J33)<=Settings!$C$6,"BE",IF(J33>0,"Win","Loss"))) | L33: =IF(J33="","",ROUND(SUM(J$14:J33),2))
B34: =IF(C34="","",ROW()-13) | J34: =IF(OR(G34="",H34="",I34=""),"",IFERROR(ROUND(IF(F34="Short",G34-I34,I34-G34)/ABS(G34-H34),2),"")) | K34: =IF(J34="","",IF(ABS(J34)<=Settings!$C$6,"BE",IF(J34>0,"Win","Loss"))) | L34: =IF(J34="","",ROUND(SUM(J$14:J34),2))
B35: =IF(C35="","",ROW()-13) | J35: =IF(OR(G35="",H35="",I35=""),"",IFERROR(ROUND(IF(F35="Short",G35-I35,I35-G35)/ABS(G35-H35),2),"")) | K35: =IF(J35="","",IF(ABS(J35)<=Settings!$C$6,"BE",IF(J35>0,"Win","Loss"))) | L35: =IF(J35="","",ROUND(SUM(J$14:J35),2))
B36: =IF(C36="","",ROW()-13) | J36: =IF(OR(G36="",H36="",I36=""),"",IFERROR(ROUND(IF(F36="Short",G36-I36,I36-G36)/ABS(G36-H36),2),"")) | K36: =IF(J36="","",IF(ABS(J36)<=Settings!$C$6,"BE",IF(J36>0,"Win","Loss"))) | L36: =IF(J36="","",ROUND(SUM(J$14:J36),2))
B37: =IF(C37="","",ROW()-13) | J37: =IF(OR(G37="",H37="",I37=""),"",IFERROR(ROUND(IF(F37="Short",G37-I37,I37-G37)/ABS(G37-H37),2),"")) | K37: =IF(J37="","",IF(ABS(J37)<=Settings!$C$6,"BE",IF(J37>0,"Win","Loss"))) | L37: =IF(J37="","",ROUND(SUM(J$14:J37),2))
B38: =IF(C38="","",ROW()-13) | J38: =IF(OR(G38="",H38="",I38=""),"",IFERROR(ROUND(IF(F38="Short",G38-I38,I38-G38)/ABS(G38-H38),2),"")) | K38: =IF(J38="","",IF(ABS(J38)<=Settings!$C$6,"BE",IF(J38>0,"Win","Loss"))) | L38: =IF(J38="","",ROUND(SUM(J$14:J38),2))
... B313: =IF(C313="","",ROW()-13) | J313: =IF(OR(G313="",H313="",I313=""),"",IFERROR(ROUND(IF(F313="Short",G313-I313,I313-G313)/ABS(G313-H313),2),"")) | K313: =IF(J313="","",IF(ABS(J313)<=Settings!$C$6,"BE",IF(J313>0,"Win","Loss"))) | L313: =IF(J313="","",ROUND(SUM(J$14:J313),2))

Sheet Settings
B1: SETTINGS
B2: Blue text on yellow = editable. Every tab updates from these values.
B4: GENERAL | F4: Account | G4: Starting Balance ($) | H4: Note
B5: Default Risk per Trade (%) | C5: 0.01 | D5: Used when a journal row's Risk % is blank | F5: Main Account | G5: 10000 | H5: Placeholder balance - replace
B6: Break-even Threshold (+/- R) | C6: 0.1 | D6: A result within this many R of zero is labelled BE | F6: Prop Challenge | G6: 50000 | H6: Placeholder balance - replace
B7: Journal Start Date | C7: 46293 | D7: Drives Daily Journal, Weekly Review, Monthly tables and Goals
B9: RISK RULES (flagged on Journal and Dashboard)
B10: Max Trades per Day | C10: 3 | D10: Trade #4 on the same day (same account) is flagged
B11: Max Daily Loss (% of day-start balance) | C11: 0.03 | D11: Trades taken after this loss is reached are flagged | F11: Up to 6 accounts (live, demo, prop). Each keeps its own balance, drawdown and rule checks.
B12: Max Weekly Loss (% of week-start balance) | C12: 0.06 | D12: Trades taken after this weekly loss are flagged
B13: Lot Size Tolerance | C13: 0.1 | D13: 'Oversized' if lots exceed the suggested size by more than this | F13: SESSION REFERENCE (approx. UTC; shifts with daylight saving)
F14: Session | G14: Approx. UTC | H14: Note
B15: SETUP GRADE (confirmations ticked Yes, out of 7) | F15: Asia | G15: 00:00 - 08:00 | H15: Builds the Asian range; its high/low is a common sweep target
B16: A+ needs at least | C16: 6 | F16: London | G16: 07:00 - 16:00 | H16: Often sweeps the Asian range early
B17: A needs at least | C17: 5 | F17: New York | G17: 12:00 - 21:00 | H17: High volume around US data
B18: B needs at least | C18: 3 | D18: Anything lower is graded C | F18: London-NY Overlap | G18: 12:00 - 16:00 | H18: Usually the most liquid window
B20: PROP FIRM TRACKER (placeholders - enter your challenge rules)
B21: Prop Account (from Accounts table) | C21: Prop Challenge | D21: Goals & Prop tab and Dashboard read this account
B22: Profit Target (%) | C22: 0.08 | D22: Placeholder
B23: Max Daily Loss Limit (%) | C23: 0.05 | D23: Placeholder; measured on worst realised day-so-far
B24: Max Drawdown Limit (%) | C24: 0.1 | D24: Placeholder; measured peak to trough
B25: Challenge End Date | C25: 46387 | D25: Placeholder
B27: ACTIVE VIEW (automatic - do not edit)
B28: Dashboard Account View | C28: =Dashboard!$L$1 -> All Accounts | D28: Change it with the dropdown on the Dashboard
B29: View Starting Balance ($) | C29: =IF(C28="All Accounts",SUM(G5:G10),IFERROR(INDEX(G5:G10,MATCH(C28,F5:F10,0)),SUM(G5:G10))) -> 60000 | D29: Sum of all accounts, or the selected one

Sheet Lists
B1: LISTS
B2: Feeds every dropdown. Rename items or fill the blank yellow cells. Pip size / value are approximate - confirm with your broker.
B5: Pair | C5: Pip Size | D5: Pip Value ($ / 1 lot) | F5: Session | G5: Setup / Model | H5: Zone Type | I5: Sweep Type | J5: HTF Bias | K5: Emotion | L5: Mistake Tag | M5: Direction (keep) | N5: Yes / No (keep) | O5: Account Views (auto) | P5: Daily Mood | Q5: Rule Check Labels (keep)
B6: XAUUSD | C6: 0.1 | D6: 10 | F6: Asia | G6: Liquidity Sweep Reversal | H6: Order Block | I6: None | J6: Bullish | K6: Calm / Focused | L6: None (Followed Plan) | M6: Long | N6: Yes | O6: All Accounts | P6: Calm & Focused | Q6: OK
B7: EURUSD | C7: 0.0001 | D7: 10 | F7: London | G7: Order Block Retest | H7: Demand Zone | I7: Asia High | J7: Bearish | K7: Confident | L7: Entered Early | M7: Short | N7: No | O7: =IF(Settings!$F$5="","",Settings!$F$5) -> Main Account | P7: Energised | Q7: Oversized
B8: GBPUSD | C8: 0.0001 | D8: 10 | F8: New York | G8: Break & Retest | H8: Supply Zone | I8: Asia Low | J8: Range / Unclear | K8: Fearful | L8: Chased Entry | O8: =IF(Settings!$F$6="","",Settings!$F$6) -> Prop Challenge | P8: Neutral | Q8: Overtraded
B9: USDJPY | C9: 0.01 | D9: 6.7 | F9: London-NY Overlap | G9: FVG Entry | H9: FVG / Imbalance | I9: Prev Day High | K9: Greedy / FOMO | L9: Moved Stop Loss | O9: =IF(Settings!$F$7="","",Settings!$F$7) | P9: Tired | Q9: Daily loss hit
B10: GBPJPY | C10: 0.01 | D10: 6.7 | G10: Breaker Block | H10: Breaker Block | I10: Prev Day Low | K10: Anxious | L10: Closed Early | O10: =IF(Settings!$F$8="","",Settings!$F$8) | P10: Stressed | Q10: Weekly loss hit
B11: AUDUSD | C11: 0.0001 | D11: 10 | G11: Supply/Demand Zone Reaction | H11: Mitigation Block | I11: Equal Highs | K11: Bored | L11: Held Too Long | O11: =IF(Settings!$F$9="","",Settings!$F$9) | P11: Distracted
B12: USDCAD | C12: 0.0001 | D12: 7.3 | G12: Trend Pullback | H12: Key Level (S/R) | I12: Equal Lows | K12: Revenge | L12: Oversized | O12: =IF(Settings!$F$10="","",Settings!$F$10)
B13: NZDUSD | C13: 0.0001 | D13: 10 | G13: Range Edge Fade | H13: Trendline | I13: Swing High/Low | K13: Overconfident | L13: No Confirmation
B14: USDCHF | C14: 0.0001 | D14: 11 | G14: Asia Range Sweep | L14: Overtraded
B15: EURJPY | C15: 0.01 | D15: 6.7 | G15: Other | L15: Traded News
B19: XAUUSD convention used here: 1 pip = $0.10 price move. Change it to match your broker. Pip values move with exchange rates.

Sheet Chart Data
B1: CHART DATA & KPI ENGINE
B2: Calculation sheet that feeds the Dashboard cards and charts. No inputs here - do not edit.
B4: KPI ENGINE | E4: EQUITY WINDOW (100 trades) | J4: OUTCOME MIX | M4: P&L BY SESSION | Q4: P&L BY WEEKDAY | U4: P&L BY MISTAKE TAG | Y4: P&L BY SETUP RANK KEY | AA4: P&L BY SETUP (TOP 6) | AE4: P&L BY PAIR RANK KEY | AG4: P&L BY PAIR (TOP 6)
B5: Closed trades in view | C5: =SUM(Journal!$BP$6:$BP$505) -> 1 | E5: Pt | F5: Trade # | G5: Balance ($) | H5: Drawdown % | J5: Outcome | K5: Trades | M5: Label | N5: Profit | O5: Loss | Q5: Label | R5: Profit | S5: Loss | U5: Label | V5: Profit | W5: Loss | Y5: Rank key | AA5: Label | AB5: Profit | AC5: Loss | AE5: Rank key | AG5: Label | AH5: Profit | AI5: Loss
B6: Wins | C6: =COUNTIFS(Journal!$BP$6:$BP$505,1,Journal!$AL$6:$AL$505,"Win") -> 1 | E6: 0 | F6: Start | G6: =IF(Dashboard!$L$27<=1,$C$17,IFERROR(INDEX(Journal!$BR$6:$BR$505,MATCH(Dashboard!$L$27-1,Journal!$BQ$6:$BQ$505,0)),$C$17)) -> 60000 | H6: =IF(Dashboard!$L$27<=1,0,IFERROR(INDEX(Journal!$BT$6:$BT$505,MATCH(Dashboard!$L$27-1,Journal!$BQ$6:$BQ$505,0)),0)) -> 0 | J6: Win | K6: =$C$6 -> 1 | M6: =Analytics!$B$7 -> Asia | N6: =MAX(0,N(Analytics!$J$7)) -> 0 | O6: =MIN(0,N(Analytics!$J$7)) -> 0 | Q6: =Analytics!$B$101 -> Mon | R6: =MAX(0,N(Analytics!$J$101)) -> 229.5 | S6: =MIN(0,N(Analytics!$J$101)) -> 0 | U6: =Analytics!$B$160 -> None (Followed Plan) | V6: =MAX(0,N(Analytics!$J$160)) -> 229.5 | W6: =MIN(0,N(Analytics!$J$160)) -> 0 | Y6: =IF(OR(Analytics!$B$33="",N(Analytics!$C$33)=0),"",Analytics!$J$33+ROW()*0.000000001) -> 229.5 | AA6: =IFERROR(INDEX(Analytics!$B$33:$B$44,MATCH(LARGE($Y$6:$Y$17,1),$Y$6:$Y$17,0)),"") -> Liquidity Sweep Reversal | AB6: =MAX(0,IFERROR(INDEX(Analytics!$J$33:$J$44,MATCH(LARGE($Y$6:$Y$17,1),$Y$6:$Y$17,0)),0)) -> 229.5 | AC6: =MIN(0,IFERROR(INDEX(Analytics!$J$33:$J$44,MATCH(LARGE($Y$6:$Y$17,1),$Y$6:$Y$17,0)),0)) -> 0 | AE6: =IF(OR(Analytics!$B$17="",N(Analytics!$C$17)=0),"",Analytics!$J$17+ROW()*0.000000001) -> 229.5 | AG6: =IFERROR(INDEX(Analytics!$B$17:$B$28,MATCH(LARGE($AE$6:$AE$17,1),$AE$6:$AE$17,0)),"") -> XAUUSD | AH6: =MAX(0,IFERROR(INDEX(Analytics!$J$17:$J$28,MATCH(LARGE($AE$6:$AE$17,1),$AE$6:$AE$17,0)),0)) -> 229.5 | AI6: =MIN(0,IFERROR(INDEX(Analytics!$J$17:$J$28,MATCH(LARGE($AE$6:$AE$17,1),$AE$6:$AE$17,0)),0)) -> 0
B7: Losses | C7: =COUNTIFS(Journal!$BP$6:$BP$505,1,Journal!$AL$6:$AL$505,"Loss") -> 0 | E7: 1 | F7: =IF((Dashboard!$L$27+E7-1)<=$C$5,(Dashboard!$L$27+E7-1),"") -> 1 | G7: =IF((Dashboard!$L$27+E7-1)<=$C$5,INDEX(Journal!$BR$6:$BR$505,MATCH((Dashboard!$L$27+E7-1),Journal!$BQ$6:$BQ$505,0)),G6) -> 60229.5 | H7: =IF((Dashboard!$L$27+E7-1)<=$C$5,INDEX(Journal!$BT$6:$BT$505,MATCH((Dashboard!$L$27+E7-1),Journal!$BQ$6:$BQ$505,0)),H6) -> 0 | J7: Loss | K7: =$C$7 -> 0 | M7: =Analytics!$B$8 -> London | N7: =MAX(0,N(Analytics!$J$8)) -> 229.5 | O7: =MIN(0,N(Analytics!$J$8)) -> 0 | Q7: =Analytics!$B$102 -> Tue | R7: =MAX(0,N(Analytics!$J$102)) -> 0 | S7: =MIN(0,N(Analytics!$J$102)) -> 0 | U7: =Analytics!$B$161 -> Entered Early | V7: =MAX(0,N(Analytics!$J$161)) -> 0 | W7: =MIN(0,N(Analytics!$J$161)) -> 0 | Y7: =IF(OR(Analytics!$B$34="",N(Analytics!$C$34)=0),"",Analytics!$J$34+ROW()*0.000000001) | AA7: =IFERROR(INDEX(Analytics!$B$33:$B$44,MATCH(LARGE($Y$6:$Y$17,2),$Y$6:$Y$17,0)),"") | AB7: =MAX(0,IFERROR(INDEX(Analytics!$J$33:$J$44,MATCH(LARGE($Y$6:$Y$17,2),$Y$6:$Y$17,0)),0)) -> 0 | AC7: =MIN(0,IFERROR(INDEX(Analytics!$J$33:$J$44,MATCH(LARGE($Y$6:$Y$17,2),$Y$6:$Y$17,0)),0)) -> 0 | AE7: =IF(OR(Analytics!$B$18="",N(Analytics!$C$18)=0),"",Analytics!$J$18+ROW()*0.000000001) | AG7: =IFERROR(INDEX(Analytics!$B$17:$B$28,MATCH(LARGE($AE$6:$AE$17,2),$AE$6:$AE$17,0)),"") | AH7: =MAX(0,IFERROR(INDEX(Analytics!$J$17:$J$28,MATCH(LARGE($AE$6:$AE$17,2),$AE$6:$AE$17,0)),0)) -> 0 | AI7: =MIN(0,IFERROR(INDEX(Analytics!$J$17:$J$28,MATCH(LARGE($AE$6:$AE$17,2),$AE$6:$AE$17,0)),0)) -> 0
B8: Break-even | C8: =COUNTIFS(Journal!$BP$6:$BP$505,1,Journal!$AL$6:$AL$505,"BE") -> 0 | E8: 2 | F8: =IF((Dashboard!$L$27+E8-1)<=$C$5,(Dashboard!$L$27+E8-1),"") | G8: =IF((Dashboard!$L$27+E8-1)<=$C$5,INDEX(Journal!$BR$6:$BR$505,MATCH((Dashboard!$L$27+E8-1),Journal!$BQ$6:$BQ$505,0)),G7) -> 60229.5 | H8: =IF((Dashboard!$L$27+E8-1)<=$C$5,INDEX(Journal!$BT$6:$BT$505,MATCH((Dashboard!$L$27+E8-1),Journal!$BQ$6:$BQ$505,0)),H7) -> 0 | J8: Break-even | K8: =$C$8 -> 0 | M8: =Analytics!$B$9 -> New York | N8: =MAX(0,N(Analytics!$J$9)) -> 0 | O8: =MIN(0,N(Analytics!$J$9)) -> 0 | Q8: =Analytics!$B$103 -> Wed | R8: =MAX(0,N(Analytics!$J$103)) -> 0 | S8: =MIN(0,N(Analytics!$J$103)) -> 0 | U8: =Analytics!$B$162 -> Chased Entry | V8: =MAX(0,N(Analytics!$J$162)) -> 0 | W8: =MIN(0,N(Analytics!$J$162)) -> 0 | Y8: =IF(OR(Analytics!$B$35="",N(Analytics!$C$35)=0),"",Analytics!$J$35+ROW()*0.000000001) | AA8: =IFERROR(INDEX(Analytics!$B$33:$B$44,MATCH(LARGE($Y$6:$Y$17,3),$Y$6:$Y$17,0)),"") | AB8: =MAX(0,IFERROR(INDEX(Analytics!$J$33:$J$44,MATCH(LARGE($Y$6:$Y$17,3),$Y$6:$Y$17,0)),0)) -> 0 | AC8: =MIN(0,IFERROR(INDEX(Analytics!$J$33:$J$44,MATCH(LARGE($Y$6:$Y$17,3),$Y$6:$Y$17,0)),0)) -> 0 | AE8: =IF(OR(Analytics!$B$19="",N(Analytics!$C$19)=0),"",Analytics!$J$19+ROW()*0.000000001) | AG8: =IFERROR(INDEX(Analytics!$B$17:$B$28,MATCH(LARGE($AE$6:$AE$17,3),$AE$6:$AE$17,0)),"") | AH8: =MAX(0,IFERROR(INDEX(Analytics!$J$17:$J$28,MATCH(LARGE($AE$6:$AE$17,3),$AE$6:$AE$17,0)),0)) -> 0 | AI8: =MIN(0,IFERROR(INDEX(Analytics!$J$17:$J$28,MATCH(LARGE($AE$6:$AE$17,3),$AE$6:$AE$17,0)),0)) -> 0
B9: Net P&L ($) | C9: =SUMIFS(Journal!$AM$6:$AM$505,Journal!$BP$6:$BP$505,1) -> 229.5 | E9: 3 | F9: =IF((Dashboard!$L$27+E9-1)<=$C$5,(Dashboard!$L$27+E9-1),"") | G9: =IF((Dashboard!$L$27+E9-1)<=$C$5,INDEX(Journal!$BR$6:$BR$505,MATCH((Dashboard!$L$27+E9-1),Journal!$BQ$6:$BQ$505,0)),G8) -> 60229.5 | H9: =IF((Dashboard!$L$27+E9-1)<=$C$5,INDEX(Journal!$BT$6:$BT$505,MATCH((Dashboard!$L$27+E9-1),Journal!$BQ$6:$BQ$505,0)),H8) -> 0 | M9: =Analytics!$B$10 -> London-NY Overlap | N9: =MAX(0,N(Analytics!$J$10)) -> 0 | O9: =MIN(0,N(Analytics!$J$10)) -> 0 | Q9: =Analytics!$B$104 -> Thu | R9: =MAX(0,N(Analytics!$J$104)) -> 0 | S9: =MIN(0,N(Analytics!$J$104)) -> 0 | U9: =Analytics!$B$163 -> Moved Stop Loss | V9: =MAX(0,N(Analytics!$J$163)) -> 0 | W9: =MIN(0,N(Analytics!$J$163)) -> 0 | Y9: =IF(OR(Analytics!$B$36="",N(Analytics!$C$36)=0),"",Analytics!$J$36+ROW()*0.000000001) | AA9: =IFERROR(INDEX(Analytics!$B$33:$B$44,MATCH(LARGE($Y$6:$Y$17,4),$Y$6:$Y$17,0)),"") | AB9: =MAX(0,IFERROR(INDEX(Analytics!$J$33:$J$44,MATCH(LARGE($Y$6:$Y$17,4),$Y$6:$Y$17,0)),0)) -> 0 | AC9: =MIN(0,IFERROR(INDEX(Analytics!$J$33:$J$44,MATCH(LARGE($Y$6:$Y$17,4),$Y$6:$Y$17,0)),0)) -> 0 | AE9: =IF(OR(Analytics!$B$20="",N(Analytics!$C$20)=0),"",Analytics!$J$20+ROW()*0.000000001) | AG9: =IFERROR(INDEX(Analytics!$B$17:$B$28,MATCH(LARGE($AE$6:$AE$17,4),$AE$6:$AE$17,0)),"") | AH9: =MAX(0,IFERROR(INDEX(Analytics!$J$17:$J$28,MATCH(LARGE($AE$6:$AE$17,4),$AE$6:$AE$17,0)),0)) -> 0 | AI9: =MIN(0,IFERROR(INDEX(Analytics!$J$17:$J$28,MATCH(LARGE($AE$6:$AE$17,4),$AE$6:$AE$17,0)),0)) -> 0
B10: Gross profit ($) | C10: =SUMIFS(Journal!$AM$6:$AM$505,Journal!$BP$6:$BP$505,1,Journal!$AM$6:$AM$505,">0") -> 229.5 | E10: 4 | F10: =IF((Dashboard!$L$27+E10-1)<=$C$5,(Dashboard!$L$27+E10-1),"") | G10: =IF((Dashboard!$L$27+E10-1)<=$C$5,INDEX(Journal!$BR$6:$BR$505,MATCH((Dashboard!$L$27+E10-1),Journal!$BQ$6:$BQ$505,0)),G9) -> 60229.5 | H10: =IF((Dashboard!$L$27+E10-1)<=$C$5,INDEX(Journal!$BT$6:$BT$505,MATCH((Dashboard!$L$27+E10-1),Journal!$BQ$6:$BQ$505,0)),H9) -> 0 | Q10: =Analytics!$B$105 -> Fri | R10: =MAX(0,N(Analytics!$J$105)) -> 0 | S10: =MIN(0,N(Analytics!$J$105)) -> 0 | U10: =Analytics!$B$164 -> Closed Early | V10: =MAX(0,N(Analytics!$J$164)) -> 0 | W10: =MIN(0,N(Analytics!$J$164)) -> 0 | Y10: =IF(OR(Analytics!$B$37="",N(Analytics!$C$37)=0),"",Analytics!$J$37+ROW()*0.000000001) | AA10: =IFERROR(INDEX(Analytics!$B$33:$B$44,MATCH(LARGE($Y$6:$Y$17,5),$Y$6:$Y$17,0)),"") | AB10: =MAX(0,IFERROR(INDEX(Analytics!$J$33:$J$44,MATCH(LARGE($Y$6:$Y$17,5),$Y$6:$Y$17,0)),0)) -> 0 | AC10: =MIN(0,IFERROR(INDEX(Analytics!$J$33:$J$44,MATCH(LARGE($Y$6:$Y$17,5),$Y$6:$Y$17,0)),0)) -> 0 | AE10: =IF(OR(Analytics!$B$21="",N(Analytics!$C$21)=0),"",Analytics!$J$21+ROW()*0.000000001) | AG10: =IFERROR(INDEX(Analytics!$B$17:$B$28,MATCH(LARGE($AE$6:$AE$17,5),$AE$6:$AE$17,0)),"") | AH10: =MAX(0,IFERROR(INDEX(Analytics!$J$17:$J$28,MATCH(LARGE($AE$6:$AE$17,5),$AE$6:$AE$17,0)),0)) -> 0 | AI10: =MIN(0,IFERROR(INDEX(Analytics!$J$17:$J$28,MATCH(LARGE($AE$6:$AE$17,5),$AE$6:$AE$17,0)),0)) -> 0
B11: Gross loss ($) | C11: =ABS(SUMIFS(Journal!$AM$6:$AM$505,Journal!$BP$6:$BP$505,1,Journal!$AM$6:$AM$505,"<0")) -> 0 | E11: 5 | F11: =IF((Dashboard!$L$27+E11-1)<=$C$5,(Dashboard!$L$27+E11-1),"") | G11: =IF((Dashboard!$L$27+E11-1)<=$C$5,INDEX(Journal!$BR$6:$BR$505,MATCH((Dashboard!$L$27+E11-1),Journal!$BQ$6:$BQ$505,0)),G10) -> 60229.5 | H11: =IF((Dashboard!$L$27+E11-1)<=$C$5,INDEX(Journal!$BT$6:$BT$505,MATCH((Dashboard!$L$27+E11-1),Journal!$BQ$6:$BQ$505,0)),H10) -> 0 | U11: =Analytics!$B$165 -> Held Too Long | V11: =MAX(0,N(Analytics!$J$165)) -> 0 | W11: =MIN(0,N(Analytics!$J$165)) -> 0 | Y11: =IF(OR(Analytics!$B$38="",N(Analytics!$C$38)=0),"",Analytics!$J$38+ROW()*0.000000001) | AA11: =IFERROR(INDEX(Analytics!$B$33:$B$44,MATCH(LARGE($Y$6:$Y$17,6),$Y$6:$Y$17,0)),"") | AB11: =MAX(0,IFERROR(INDEX(Analytics!$J$33:$J$44,MATCH(LARGE($Y$6:$Y$17,6),$Y$6:$Y$17,0)),0)) -> 0 | AC11: =MIN(0,IFERROR(INDEX(Analytics!$J$33:$J$44,MATCH(LARGE($Y$6:$Y$17,6),$Y$6:$Y$17,0)),0)) -> 0 | AE11: =IF(OR(Analytics!$B$22="",N(Analytics!$C$22)=0),"",Analytics!$J$22+ROW()*0.000000001) | AG11: =IFERROR(INDEX(Analytics!$B$17:$B$28,MATCH(LARGE($AE$6:$AE$17,6),$AE$6:$AE$17,0)),"") | AH11: =MAX(0,IFERROR(INDEX(Analytics!$J$17:$J$28,MATCH(LARGE($AE$6:$AE$17,6),$AE$6:$AE$17,0)),0)) -> 0 | AI11: =MIN(0,IFERROR(INDEX(Analytics!$J$17:$J$28,MATCH(LARGE($AE$6:$AE$17,6),$AE$6:$AE$17,0)),0)) -> 0
B12: Total R | C12: =SUMIFS(Journal!$AK$6:$AK$505,Journal!$BP$6:$BP$505,1) -> 2.33 | E12: 6 | F12: =IF((Dashboard!$L$27+E12-1)<=$C$5,(Dashboard!$L$27+E12-1),"") | G12: =IF((Dashboard!$L$27+E12-1)<=$C$5,INDEX(Journal!$BR$6:$BR$505,MATCH((Dashboard!$L$27+E12-1),Journal!$BQ$6:$BQ$505,0)),G11) -> 60229.5 | H12: =IF((Dashboard!$L$27+E12-1)<=$C$5,INDEX(Journal!$BT$6:$BT$505,MATCH((Dashboard!$L$27+E12-1),Journal!$BQ$6:$BQ$505,0)),H11) -> 0 | U12: =Analytics!$B$166 -> Oversized | V12: =MAX(0,N(Analytics!$J$166)) -> 0 | W12: =MIN(0,N(Analytics!$J$166)) -> 0 | Y12: =IF(OR(Analytics!$B$39="",N(Analytics!$C$39)=0),"",Analytics!$J$39+ROW()*0.000000001) | AE12: =IF(OR(Analytics!$B$23="",N(Analytics!$C$23)=0),"",Analytics!$J$23+ROW()*0.000000001)
B13: Average win (R) | C13: =IFERROR(AVERAGEIFS(Journal!$AK$6:$AK$505,Journal!$BP$6:$BP$505,1,Journal!$AL$6:$AL$505,"Win"),0) -> 2.33 | E13: 7 | F13: =IF((Dashboard!$L$27+E13-1)<=$C$5,(Dashboard!$L$27+E13-1),"") | G13: =IF((Dashboard!$L$27+E13-1)<=$C$5,INDEX(Journal!$BR$6:$BR$505,MATCH((Dashboard!$L$27+E13-1),Journal!$BQ$6:$BQ$505,0)),G12) -> 60229.5 | H13: =IF((Dashboard!$L$27+E13-1)<=$C$5,INDEX(Journal!$BT$6:$BT$505,MATCH((Dashboard!$L$27+E13-1),Journal!$BQ$6:$BQ$505,0)),H12) -> 0 | U13: =Analytics!$B$167 -> No Confirmation | V13: =MAX(0,N(Analytics!$J$167)) -> 0 | W13: =MIN(0,N(Analytics!$J$167)) -> 0 | Y13: =IF(OR(Analytics!$B$40="",N(Analytics!$C$40)=0),"",Analytics!$J$40+ROW()*0.000000001) | AE13: =IF(OR(Analytics!$B$24="",N(Analytics!$C$24)=0),"",Analytics!$J$24+ROW()*0.000000001)
B14: Average loss (R) | C14: =IFERROR(AVERAGEIFS(Journal!$AK$6:$AK$505,Journal!$BP$6:$BP$505,1,Journal!$AL$6:$AL$505,"Loss"),0) -> 0 | E14: 8 | F14: =IF((Dashboard!$L$27+E14-1)<=$C$5,(Dashboard!$L$27+E14-1),"") | G14: =IF((Dashboard!$L$27+E14-1)<=$C$5,INDEX(Journal!$BR$6:$BR$505,MATCH((Dashboard!$L$27+E14-1),Journal!$BQ$6:$BQ$505,0)),G13) -> 60229.5 | H14: =IF((Dashboard!$L$27+E14-1)<=$C$5,INDEX(Journal!$BT$6:$BT$505,MATCH((Dashboard!$L$27+E14-1),Journal!$BQ$6:$BQ$505,0)),H13) -> 0 | U14: =Analytics!$B$168 -> Overtraded | V14: =MAX(0,N(Analytics!$J$168)) -> 0 | W14: =MIN(0,N(Analytics!$J$168)) -> 0 | Y14: =IF(OR(Analytics!$B$41="",N(Analytics!$C$41)=0),"",Analytics!$J$41+ROW()*0.000000001) | AE14: =IF(OR(Analytics!$B$25="",N(Analytics!$C$25)=0),"",Analytics!$J$25+ROW()*0.000000001)
